Workbook

Sheet Table-View(LOAN_POS_DTLS)
A1: 1. View Name - | B1: Liability Balance | F1: Please read review comments on Table Functional Description, Data Type and Business Definition
A2: 2. Table Name (From DA Team) - | B2: LBY_BAL
A3: 3. View Schema Name -
A4: 4. Table Schema Name - | B4: CCAL_BAL_OWNER
A5: 5. Table Functional Description /Comment in Oracle/Redshift - | B5: This consists the list/tally of liability positions or loans consisting of Arrangements data, balance amounts and date, Owner financial advisor reference data and entity data, Relationships. | F5: BA Responsbility | G5: BA Responsbility | H5: BA Responsbility | I5: DA Responsibility
A6: 6. Filter Criteria - | B6: None
A7: 7. Grain - Please see Grain Columns sheet.
A8: Target | N8: Source | S8: Transformation
A9: Logical Name of Attribute (Name of column in View without underscores) | B9: Physical Name of Attribute (Name of column in Table) Supplied by DA Team | C9: Data type in Oracle VARCHAR2(n), DATE, NUMBER(m,n), TIMETSTAMP(6) | D9: Nullable in Table and in Oracle View NULL, NOT NULL | E9: Data type in Redshift | F9: Nullable in View in Redshift | G9: Business Definition (To go into comments and into Meta Data Hub) | H9: Sample data values | I9: Action on Attribute Add,Update,Remove, Blank | J9: Comments on when it was added / updated. List the PBI or Bug number. | K9: Include in View. Populated with N only when not to be shown in the view. | L9: Is on Data Model DA responsibility | M9: Model Data Type match TRUE/FALSE DA Responsibilty | N9: Source Schema | O9: Source Table | P9: Source Attribute Name | Q9: Data Type | R9: Nullable? | S9: Transformation /Business Rules /Join Conditions | T9: Notes / Comments
A10: Liability Balance Id | B10: LBY_BAL_ID | C10: NUMBER(38,0) | D10: No | E10: NUMERIC(38) | F10: No | G10: Surrogate key for Liability Balance Fact. | I10: Add | J10: PBI#2405850 | K10: N | S10: This is Surrogate Key for this table. Comes from Sequence
A11: As of Date | B11: AS_OF_DT | C11: DATE | D11: No | E11: Timestamp without time zone | F11: No | G11: Date on which liability balance was recalculated in source system | I11: Add | J11: PBI#2405850 | N11: LOAN_STG_OWNER | O11: LOAN_POS_DTLS | P11: AS_OF_DT
A12: Balance Date | B12: BAL_DT | C12: DATE | D12: No | E12: Timestamp without time zone | F12: No | G12: Batch/snapshot date of the data load. | I12: Add | J12: PBI#2405850 | N12: LOAN_STG_OWNER | O12: LOAN_POS_DTLS | P12: SNPST_DT
A13: Balance Datetime | B13: BAL_DTM | C13: DATE | D13: No | E13: Timestamp without time zone | F13: No | G13: Batch/snapshot datetime of the data load. | I13: Add | J13: PBI#2405850 | N13: LOAN_STG_OWNER | O13: LOAN_POS_DTLS | P13: SNPST_DT | S13: LOAN_POS_DTLS.SNPST_DT||' 00:00:00'
A14: Arrangement Id | B14: AR_ID | C14: NUMBER(38,0) | D14: No | E14: NUMERIC(38) | F14: No | G14: The CDS assigned identifier for the arrangement - used for data lineage The relationship of the loan is identified by arrangement id. For syndicate loans this is the facility arrangement. | I14: Add | J14: PBI#2405850 | N14: LOAN_STG_OWNER | O14: LOAN_POS_DTLS | P14: AR_ID
A15: Brokerage Arrangement Id | B15: BKR_AR_ID | C15: NUMBER(38,0) | D15: Yes | E15: NUMERIC(38) | F15: Yes | G15: Associated Broker Arrangement Identifier (eg. AR ID for brokerage acct linked to Loan), if linked. | I15: Add | J15: PBI#2405850 | P15: Derived | S15: If SRC_STM_ID = 5017, set LINKED_BKR_AR_ID to NULL; otherwise, follow the steps below to determine LINKED_BKR_AR_ID. Step1: Below is the logic to find the RJBNK1 AR_ID corresponding to each RJBNK2 AR_ID for RJBNK2 records where SRC_STM_ID equals 93. --RJbank SELECT lac.ar_id rjbnk2_ar_id, arxr_rjb1.ar_id linked_rjbnk1_ar_id FROM loan_stg_owner.loan_pos_dtls lpd LEFT JOIN loan_stg_owner.loan_ac lac ON lpd.ac_id = lac.ac_id LEFT JOIN ccsi_owner.ar_xref arxr ON arxr.ar_id = lac.ar_id AND arxr.src_stm_id = 93 AND arxr.orig_pvdr_src_stm_id = 93 LEFT JOIN ccsi_owner.ar_xref arxr_rjb1 ON ltrim(arxr_rjb1.legacy_id, '0') = ltrim(arxr.legacy_id, '0') AND arxr_rjb1.src_stm_id = 5 AND arxr_rjb1.orig_pvdr_src_stm_id = 5 WHERE lac.ar_id IN (SELECT ar_id FROM ccsi_owner.ar_xref WHERE src_stm_id = 93 AND orig_pvdr_src_stm_id = 93; Step2: Below is the logic to find the RJBNK1 AR_ID corresponding to each RJB RESI AR_ID for RJB RESI records where SRC_STM_ID equals 5016. --Resi SELECT a.src_stm_id, a.ar_id resi_ar_id, b.ar_id linked_rjbnk1_ar_id FROM loan_stg_owner.loan_pos_dtls lpd LEFT JOIN loan_stg_owner.loan_ac a ON lpd.AC_ID = a.AC_ID LEFT JOIN ccsi_owner.ar_xref b ON ltrim(b.legacy_id, '0') = ltrim(a.orig_ac_num, '0') AND b.src_stm_id = 5 AND b.orig_pvdr_src_stm_id = 5 WHERE a.src_stm_id = '5016'; Step3: From the above steps, we obtain LINKED_RJBNK1_AR_ID and use it in the query below for lookup. SELECT ar_grp_id FROM reference_owner.ar_grp_x_ar where ar_grp_x_ar_tp_id = 1 and ar_id = LINKED_RJBNK1_AR_ID (sample: 6324753341); Step4: Use ar_grp_id from Step 3 to look up and retrieve the corresponding LINKED_BKR_AR_ID select AR_ID as LINKED_BKR_AR_ID from ccsi_owner.ar_xref where ar_id in ( SELECT ar_id FROM reference_owner.ar_grp_x_ar where AR_GRP_ID = "ar_grp_id from step 3 " (sample: 6680587)) and SRC_STM_ID =2 and ORIG_PVDR_SRC_STM_ID =1; | U15: logic changed
A16: Account Id | B16: AC_ID | C16: NUMBER(38,0) | D16: Yes | E16: NUMERIC(38) | F16: Yes | G16: The CDS assigned identifier for the account - used for data lineage. Account Id represents the identifier for the bank account associated with the arrangement. Multiple accounts can be associated with single arrangement, for syndicate loans it represents loan taken for the facilities. | I16: Add | J16: PBI#2405850 | N16: LOAN_STG_OWNER | O16: LOAN_POS_DTLS | P16: AC_ID
A17: Accounting Type Code | B17: ACG_TP_CODE | C17: VARCHAR2(1) | D17: Yes | E17: Character varying(1) | F17: Yes | G17: Code for the Accounting Type | I17: Add | J17: PBI#2405850 | N17: CCAL_OWNER | O17: AST_LBY_POS | P17: ACG_TP_CODE | S17: Join LOAN_STG_OWNER.LOAN_POS_DTLS with CCAL_OWNER.AST_LBY_POS on basis of AST_LBY_POS_ID populate ACG_TP_CODE
A18: Asset Liability Position Identifier | B18: AST_LBY_POS_ID | C18: NUMBER(38,0) | D18: Yes | E18: NUMERIC(38) | F18: Yes | G18: Numeric identifier of the Asset Liability Position assigned by CDS included as degenerate Dim supporting linneage | I18: Add | J18: PBI#2405850 | N18: LOAN_STG_OWNER | O18: LOAN_POS_DTLS | P18: AST_LBY_POS_ID
A19: Owed in Currency Balance Amount | B19: OW_IN_CCY_BAL_AMT | C19: NUMBER(36,8) | D19: Yes | E19: NUMERIC(36,8) | F19: Yes | G19: Balance amount on the loan, in loan owed Currency. | I19: Add | J19: PBI#2405850 | N19: LOAN_STG_OWNER | O19: LOAN_POS_DTLS | P19: BAL_AMT
A20: Local Currency Balance Amount | B20: LCL_CCY_BAL_AMT | C20: NUMBER(36,8) | D20: Yes | E20: NUMERIC(36,8) | F20: Yes | G20: Balance amount on the loan in currency of the place where loan is issued. | I20: Add | J20: PBI#2405850 | N20: LOAN_STG_OWNER | O20: LOAN_POS_DTLS | P20: SBC_GL_BAL_AMT
A21: USD Currency Balance Amount | B21: CCY_BAL_AMT_USD | C21: NUMBER(36,8) | D21: Yes | E21: NUMERIC(36,8) | F21: Yes | G21: Balance amount on the loan in USD currency. It is called Realized Compound Yield General Ledger Balance Amount in source system. | I21: Add | J21: PBI#2405850 | N21: LOAN_STG_OWNER | O21: LOAN_POS_DTLS | P21: RCY_GL_BAL_AMT
A22: Balance Type Id | B22: BAL_TP_ID | C22: NUMBER(38,0) | D22: Yes | E22: NUMERIC(38) | F22: Yes | G22: Identifier for the Type of Balance amount on the loan. | I22: Add | J22: PBI#2405850 | N22: LOAN_STG_OWNER | O22: LOAN_POS_DTLS | P22: BAL_TP_ID
A23: RJ Bank Branch Number | B23: RJ_BNK_BR_NUM | C23: VARCHAR2(5) | D23: Yes | E23: Character varying(5) | F23: Yes | G23: Branch(Entity) for the facility. | I23: Add | J23: PBI#2405850 | N23: LOAN_STG_OWNER | O23: LOAN_POS_DTLS | P23: BR_CODE
A24: Owed in Currency Code | B24: OW_IN_CCY_CODE | C24: VARCHAR2(3) | D24: Yes | E24: Character varying(3) | F24: Yes | G24: Currency in which the Loan is owed. | I24: Add | J24: PBI#2405850 | N24: LOAN_STG_OWNER | O24: LOAN_POS_DTLS | P24: CCY_CODE
A25: Local Currency Code | B25: LCL_CCY_CODE | C25: VARCHAR2(3) | D25: Yes | E25: Character varying(3) | F25: Yes | G25: Currency of the place where loan is issued.. | I25: Add | J25: PBI#2405850 | N25: LOAN_STG_OWNER | O25: LOAN_POS_DTLS | P25: LCL_CCY_CODE
A26: Expense Code Id | B26: EXPN_CODE_ID | C26: NUMBER(38,0) | D26: Yes | E26: NUMERIC(38) | F26: Yes | G26: Identifier for the Expense code. | I26: Add | J26: PBI#2405850 | N26: LOAN_STG_OWNER | O26: LOAN_POS_DTLS | P26: EXPN_CODE_ID
A27: General Ledger Account number | B27: GL_AC_NUM | C27: VARCHAR2(20) | D27: Yes | E27: Character varying(20) | F27: Yes | G27: General Ledger Accounts are used to categorize types of financial transactions. General Ledger is a complete record of a company's transactions over a period of time, documenting changes to assets, liabilities, equity, expenses, and revenue. | I27: Add | J27: PBI#2405850 | N27: LOAN_STG_OWNER | O27: LOAN_POS_DTLS | P27: GL_AC_ID
A28: General Ledger Type Id | B28: GL_TP_ID | C28: NUMBER(38,0) | D28: Yes | E28: NUMERIC(38) | F28: Yes | G28: Identifier for the Type of General Ledger. | I28: Add | J28: PBI#2405850 | N28: LOAN_STG_OWNER | O28: LOAN_POS_DTLS | P28: GL_TP_ID
A29: Portfolio Type Id | B29: PRTFL_TP_ID | C29: NUMBER(38,0) | D29: Yes | E29: NUMERIC(38) | F29: Yes | G29: Identifier for the Portfolio type. | I29: Add | J29: PBI#2405850 | N29: LOAN_STG_OWNER | O29: LOAN_POS_DTLS | P29: PRTFL_TP_ID
... A32: Source System Id | B32: SRC_STM_ID | C32: NUMBER(38,0) | D32: Yes | E32: NUMERIC(38) | F32: Yes | G32: CDS assigned identifier for the source system - used for data lineage | I32: Add | J32: PBI#2405850 | N32: LOAN_STG_OWNER | O32: LOAN_POS_DTLS | P32: SRC_STM_ID
A33: Create Datetime | B33: CRT_DTM | C33: TTIMESTAMP(6) | D33: No | E33: Timestamp without time zone | F33: No | G33: The exact date and time when a row was first created. | I33: Add | J33: PBI#2405850 | S33: Audit columns to be populated as part of the load
A34: Create User Name | B34: CRT_USR_NM | C34: VARCHAR2(256) | D34: No | E34: Character varying(256) | F34: No | G34: The name that represents the user or application who created the row | I34: Add | J34: PBI#2405850 | S34: Audit columns to be populated as part of the load
A35: Last Update Datetime | B35: LAST_UDT_DTM | C35: TTIMESTAMP(6) | D35: No | E35: Timestamp without time zone | F35: No | G35: The exact date and time when an occurrence is inserted, updated, or deleted a row | I35: Add | J35: PBI#2405850 | S35: Audit columns to be populated as part of the load
A36: Last Update User Name | B36: LAST_UDT_USR_NM | C36: VARCHAR2(256) | D36: No | E36: Character varying(256) | F36: No | G36: The name that represents the user or application who inserted, updated, or deleted each occurrence of row | I36: Add | J36: PBI#2405850 | S36: Audit columns to be populated as part of the load
A37: Original Account Number | B37: ORIG_AC_NUM | C37: VARCHAR2(20) | D37: Yes | E37: Character varying(20) | F37: Yes | G37: The set of alphanumeric characters that identifies the unique instantiation of an Account Arrangement. | I37: Add | J37: PBI#2405850 | N37: LOAN_STG_OWNER | O37: LOAN_AC | P37: ORIG_AC_NUM | S37: Get LAC.ORIG_AC_NUM from LOAN_STG_OWNER.LOAN_POS_DTLS LPD join LOAN_STG_OWNER.LOAN_AC LAC ON LAC.AC_ID = LPD.AC_ID and LAC.AR_ID = LPD.AR_ID
A38: Liability Balance Interest Rate | B38: LBY_BAL_INT_RATE | C38: NUMBER(24,10) | D38: Yes | E38: NUMERIC(24,10) | F38: Yes | G38: This is the percentage of the loan amount that a lender charges a borrower for using the money. It’s essentially the cost of borrowing and is typically expressed as an annual percentage rate (APR). Example: Bank loan Interest rate and Margin Interest rate. | I38: Add | J38: PBI#2405850 | N38: LOAN_STG_OWNER | O38: LOAN_AR | P38: CRN_INT_RATE | S38: Join LOAN_STG_OWNER.LOAN_POS_DTLS with LOAN_STG_OWNER.LOAN_AR on basis of AR_ID populate CRN_INT_RATE

Sheet Table-View(EOD_POS)
A1: 1. View Name - | B1: Liability Balance | F1: Please read review comments on Table Functional Description, Data Type and Business Definition
A2: 2. Table Name (From DA Team) - | B2: LBY_BAL
A3: 3. View Schema Name -
A4: 4. Table Schema Name - | B4: CCAL_BAL_OWNER
A5: 5. Table Functional Description /Comment in Oracle/Redshift - | B5: This consists the list/tally of liability positions or loans consisting of Arrangements data, balance amounts and date, Owner financial advisor reference data and entity data, Relationships. | F5: BA Responsbility | G5: BA Responsbility | H5: BA Responsbility | I5: DA Responsibility
A6: 6. Filter Criteria - | B6: Select records from CCAL_OWNER.EOD_POS where preference is given to records with CASH_POS_TP_ID = 9. If records are available, then select records with CASH_POS_TP_ID = 10. | C6: A decision from Praveen Bajaj will confirm whether to use RJBNK1 or RJBNK2
A7: 7. Grain - Please see Grain Columns sheet.
A8: Target | N8: Source | S8: Transformation
A9: Logical Name of Attribute (Name of column in View without underscores) | B9: Physical Name of Attribute (Name of column in Table) Supplied by DA Team | C9: Data type in Oracle VARCHAR2(n), DATE, NUMBER(m,n), TIMETSTAMP(6) | D9: Nullable in Table and in Oracle View NULL, NOT NULL | E9: Data type in Redshift | F9: Nullable in View in Redshift | G9: Business Definition (To go into comments and into Meta Data Hub) | H9: Sample data values | I9: Action on Attribute Add,Update,Remove, Blank | J9: Comments on when it was added / updated. List the PBI or Bug number. | K9: Include in View. Populated with N only when not to be shown in the view. | L9: Is on Data Model DA responsibility | M9: Model Data Type match TRUE/FALSE DA Responsibilty | N9: Source Schema | O9: Source Table | P9: Source Attribute Name | Q9: Data Type | R9: Nullable? | S9: Transformation /Business Rules /Join Conditions | T9: Notes / Comments
A10: Liability Balance Fact Id | B10: LBY_BAL_ID | C10: NUMBER(38) | D10: No | E10: NUMERIC(38) | F10: No | G10: Surrogate key for Liability Balance Fact. | I10: Add | J10: PBI#2405850 | K10: N | S10: This is Surrogate Key for this table. Comes from Sequence
A11: As of Date | B11: AS_OF_DT | C11: DATE | D11: No | E11: Timestamp without time zone | F11: No | G11: Date on which liability balance was recalculated in source system | I11: Add | J11: PBI#2405850 | S11: During the load, for an arrangement, we have to find the date on which EOD_POS.TD_MKT_VAL_AMT is changing and populate EOD_POS.EOD_POS_DTM of that record. Till we encounter next change in EOD_POS.TD_MKT_VAL_AMT value we have to retain previously derived date in this field.
A12: Balance Date | B12: BAL_DT | C12: DATE | D12: No | E12: Timestamp without time zone | F12: No | G12: Batch/snapshot date of the data load. | I12: Add | J12: PBI#2405850 | N12: CCAL_OWNER | O12: EOD_POS | P12: EOD_POS_DTM
A13: Balance Datetime | B13: BAL_DTM | C13: DATE | D13: No | E13: Timestamp without time zone | F13: No | G13: Batch/snapshot datetime of the data load. | I13: Add | J13: PBI#2405850 | N13: CCAL_OWNER | O13: EOD_POS | P13: EOD_POS_DTM | S13: eod_pos.eod_pos_dtm||' 23:59:59'
A14: Arrangement Id | B14: AR_ID | C14: NUMBER(38) | D14: No | E14: NUMERIC(38) | F14: No | G14: The CDS assigned identifier for the arrangement - used for data lineage The relationship of the loan is identified by arrangement id. For syndicate loans this is the facility arrangement. | I14: Add | J14: PBI#2405850 | N14: CCAL_OWNER | O14: AST_LBY_POS | P14: AR_ID
A15: Brokerage Arrangement Id | B15: BKR_AR_ID | C15: NUMBER(38) | D15: Yes | E15: NUMERIC(38) | F15: Yes | G15: Associated Broker Arrangement Identifier (eg. AR ID for brokerage acct linked to Loan), if linked. | I15: Add | J15: PBI#2405850 | N15: CCAL_OWNER | O15: EOD_POS | P15: BKR_AR_ID | S15: Nvl(eod_pos.bkr_ar_id, eod_pos.ar_id)
A16: Account Id | B16: AC_ID | C16: NUMBER(38) | D16: Yes | E16: NUMERIC(38) | F16: Yes | G16: The CDS assigned identifier for the account - used for data lineage. Account Id represents the identifier for the bank account associated with the arrangement. Multiple accounts can be associated with single arrangement, for syndicate loans it represents loan taken for the facilities. | I16: Add | J16: PBI#2405850 | N16: CCAL_OWNER | O16: EOD_POS | P16: AC_ID
A17: Accounting Type Code | B17: ACG_TP_CODE | C17: VARCHAR2(1) | D17: Yes | E17: Character varying(1) | F17: Yes | G17: Code for the Accounting Type | I17: Add | J17: PBI#2405850 | N17: CCAL_OWNER | O17: AST_LBY_POS | P17: ACG_TP_CODE | S17: Join LOAN_STG_OWNER.LOAN_POS_DTLS with CCAL_OWNER.AST_LBY_POS on basis of AST_LBY_POS_ID populate ACG_TP_CODE
A18: Asset Liability Position Identifier | B18: AST_LBY_POS_ID | C18: NUMBER(38) | D18: Yes | E18: NUMERIC(38) | F18: Yes | G18: Numeric identifier of the Asset Liability Position assigned by CDS included as degenerate Dim supporting linneage | I18: Add | J18: PBI#2405850 | N18: CCAL_OWNER | O18: EOD_POS | P18: AST_LBY_POS_ID
A19: Owed in Currency Balance Amount | B19: OW_IN_CCY_BAL_AMT | C19: NUMBER(36,8) | D19: Yes | E19: NUMERIC(36,8) | F19: Yes | G19: Balance amount on the loan, in loan owed Currency. | I19: Add | J19: PBI#2405850 | N19: CCAL_OWNER | O19: EOD_POS | P19: SD_MKT_VAL_AMT | T19: Source changed from TD_MKT_VAL_AMT to SD_MKT_VAL_AMT (Bug: 2646935)
A20: Local Currency Balance Amount | B20: LCL_CCY_BAL_AMT | C20: NUMBER(36,8) | D20: Yes | E20: NUMERIC(36,8) | F20: Yes | G20: Balance amount on the loan in currency of the place where loan is issued. | I20: Add | J20: PBI#2405850 | S20: set to Null
A21: USD Currency Balance Amount | B21: CCY_BAL_AMT_USD | C21: NUMBER(36,8) | D21: Yes | E21: NUMERIC(36,8) | F21: Yes | G21: Balance amount on the loan in USD currency. It is called Realized Compound Yield General Ledger Balance Amount in source system. | I21: Add | J21: PBI#2405850 | N21: CCAL_OWNER | O21: EOD_POS | P21: SBC_SD_MKT_VAL_AMT | T21: Source changed from SBC_TD_MKT_VAL_AMT to SBC_SD_MKT_VAL_AMT (Bug: 2646935)
A22: Balance Type Id | B22: BAL_TP_ID | C22: NUMBER(38) | D22: Yes | E22: NUMERIC(38) | F22: Yes | G22: Identifier for the Type of Balance amount on the loan. | I22: Add | J22: PBI#2405850 | S22: Take CL_VAL_ID where CL_VAL_NM is equal to 'Principal Balance' and CL_SCM_ID = '12089' | T22: LOAN_STG_OWNER.CL_VAL.CL_VAL_ID='120890028'
A23: RJ Bank Branch Number | B23: RJ_BNK_BR_NUM | C23: VARCHAR2(5) | D23: Yes | E23: Character varying(5) | F23: Yes | G23: Branch(Entity) for the facility. | I23: Add | J23: PBI#2405850 | S23: set to Null
A24: Owed in Currency Code | B24: OW_IN_CCY_CODE | C24: VARCHAR2(3) | D24: Yes | E24: Character varying(3) | F24: Yes | G24: Currency in which the Loan is owed. | I24: Add | J24: PBI#2405850 | N24: CCAL_OWNER | O24: EOD_POS | P24: CCY_CODE
A25: Local Currency Code | B25: LCL_CCY_CODE | C25: VARCHAR2(3) | D25: Yes | E25: Character varying(3) | F25: Yes | G25: Currency of the place where loan is issued.. | I25: Add | J25: PBI#2405850 | S25: set to Null
A26: Expense Code Id | B26: EXPN_CODE_ID | C26: NUMBER(38) | D26: Yes | E26: NUMERIC(38) | F26: Yes | G26: Identifier for the Expense code. | I26: Add | J26: PBI#2405850 | S26: set to Null
A27: General Ledger Account Number | B27: GL_AC_NUM | C27: VARCHAR2(20) | D27: Yes | E27: Character varying(20) | F27: Yes | G27: General Ledger Accounts are used to categorize types of financial transactions. General Ledger is a complete record of a company's transactions over a period of time, documenting changes to assets, liabilities, equity, expenses, and revenue. | I27: Add | J27: PBI#2405850 | S27: set to Null
A28: General Ledger Type Id | B28: GL_TP_ID | C28: NUMBER(38) | D28: Yes | E28: NUMERIC(38) | F28: Yes | G28: Identifier for the Type of General Ledger. | I28: Add | J28: PBI#2405850 | S28: set to Null
A29: Portfolio Type Id | B29: PRTFL_TP_ID | C29: NUMBER(38) | D29: Yes | E29: NUMERIC(38) | F29: Yes | G29: Identifier for the Portfolio type. | I29: Add | J29: PBI#2405850 | S29: set to Null
A30: Period Type Id | B30: PRD_TP_ID | C30: NUMBER(38) | D30: Yes | E30: NUMERIC(38) | F30: Yes | G30: Identifier for the period type. | I30: Add | J30: PBI#2405850 | S30: Take CL_VAL_ID where CL_VAL_NM is equal to 'Current Month' and CL_SCM_ID = '12090' | T30: LOAN_STG_OWNER.CL_VAL.CL_VAL_ID='120900001'
A31: Unique Source Id | B31: UNQ_SRC_ID | C31: NUMBER(38) | D31: Yes | E31: NUMERIC(38) | F31: Yes | G31: Unique Source Identifier coming from CECL system | I31: Add | J31: PBI#2405850 | S31: set to Null
A32: Source System Id | B32: SRC_STM_ID | C32: NUMBER(38) | D32: Yes | E32: NUMERIC(38) | F32: Yes | G32: CDS assigned identifier for the source system - used for data lineage | I32: Add | J32: PBI#2405850 | N32: CCAL_OWNER | O32: EOD_POS | P32: SRC_STM_ID
A33: Create Datetime | B33: CRT_DTM | C33: DATE | D33: No | E33: Timestamp without time zone | F33: No | G33: The exact date and time when a row was first created. | I33: Add | J33: PBI#2405850 | S33: Audit columns to be populated as part of the load
A34: Create User Name | B34: CRT_USR_NM | C34: VARCHAR2(256) | D34: No | E34: Character varying(256) | F34: No | G34: The name that represents the user or application who created the row | I34: Add | J34: PBI#2405850 | S34: Audit columns to be populated as part of the load
A35: Last Update Datetime | B35: LAST_UDT_DTM | C35: DATE | D35: No | E35: Timestamp without time zone | F35: No | G35: The exact date and time when an occurrence is inserted, updated, or deleted a row | I35: Add | J35: PBI#2405850 | S35: Audit columns to be populated as part of the load
A36: Last Update User Name | B36: LAST_UDT_USR_NM | C36: VARCHAR2(256) | D36: No | E36: Character varying(256) | F36: No | G36: The name that represents the user or application who inserted, updated, or deleted each occurrence of row | I36: Add | J36: PBI#2405850 | S36: Audit columns to be populated as part of the load
A37: Original Account Number | B37: ORIG_AC_NUM | C37: VARCHAR2(20) | D37: Yes | E37: Character varying(20) | F37: Yes | G37: The set of alphanumeric characters that identifies the unique instantiation of an Account Arrangement. | I37: Add | J37: PBI#2405850 | N37: CCSI_OWNER | O37: AR_XREF | P37: LEGACY_ID | S37: Join CCAL_OWNER.EOD_POS ep and CCSI_OWNER.AR_XREF AX ON EP.AR_ID=AX.AR_ID where AX.ORIG_PVDR_SRC_STM_ID = 1
A38: Liability Balance Interest Rate | B38: LBY_BAL_INT_RATE | C38: NUMBER(24,10) | D38: Yes | E38: NUMERIC(24,10) | F38: Yes | G38: This is the percentage of the loan amount that a lender charges a borrower for using the money. It’s essentially the cost of borrowing and is typically expressed as an annual percentage rate (APR). Example: Bank loan Interest rate and Margin Interest rate. | I38: Add | J38: PBI#2405850 | N38: CCAL_OWNER | O38: EOD_POS | P38: MRGN_DB_INT_RATE

Sheet Attribute
A1: Entity Name (Logical table Name) | B1: Table Name (Physical Table name) | C1: Attribute Name (Target Attribute Logical) | D1: Column Name (Target attribute physical) | E1: Data type ( varchar2/ date / Number etc.) | F1: Table Definition | G1: Attribute Definition | H1: Nullability - 'NULL' or 'NOT NULL' | I1: Primary Key - 'True' or 'False' | J1: domain | K1: DOmain DIctionary | N1: PBI
A2: Liability Balance | C2: ='Table-View(LOAN_POS_DTLS)'!A10 -> Liability Balance Id | E2: NUMERIC(38,0) | F2: This consists the list/tally of liability positions or loans consisting of Arrangements data, balance amounts and date, Owner financial advisor reference data and entity data, Relationships. | G2: ='Table-View(LOAN_POS_DTLS)'!G10 -> Surrogate key for Liability Balance Fact. | H2: =IF('Table-View(LOAN_POS_DTLS)'!D10="No","NOT NULL","NULL") -> NOT NULL | K2: Light House DataDictionary
A3: Liability Balance | C3: ='Table-View(LOAN_POS_DTLS)'!A11 -> As of Date | E3: DATE | F3: This consists the list/tally of liability positions or loans consisting of Arrangements data, balance amounts and date, Owner financial advisor reference data and entity data, Relationships. | G3: ='Table-View(LOAN_POS_DTLS)'!G11 -> Date on which liability balance was recalculated in source system | H3: =IF('Table-View(LOAN_POS_DTLS)'!D11="No","NOT NULL","NULL") -> NOT NULL | K3: Light House DataDictionary
A4: Liability Balance | C4: ='Table-View(LOAN_POS_DTLS)'!A12 -> Balance Date | E4: DATE | F4: This consists the list/tally of liability positions or loans consisting of Arrangements data, balance amounts and date, Owner financial advisor reference data and entity data, Relationships. | G4: ='Table-View(LOAN_POS_DTLS)'!G12 -> Batch/snapshot date of the data load. | H4: =IF('Table-View(LOAN_POS_DTLS)'!D12="No","NOT NULL","NULL") -> NOT NULL | K4: Light House DataDictionary
A5: Liability Balance | C5: ='Table-View(LOAN_POS_DTLS)'!A13 -> Balance Datetime | E5: DATE | F5: This consists the list/tally of liability positions or loans consisting of Arrangements data, balance amounts and date, Owner financial advisor reference data and entity data, Relationships. | G5: ='Table-View(LOAN_POS_DTLS)'!G13 -> Batch/snapshot datetime of the data load. | H5: =IF('Table-View(LOAN_POS_DTLS)'!D13="No","NOT NULL","NULL") -> NOT NULL | K5: Light House DataDictionary
A6: Liability Balance | C6: ='Table-View(LOAN_POS_DTLS)'!A14 -> Arrangement Id | E6: NUMERIC(38,0) | F6: This consists the list/tally of liability positions or loans consisting of Arrangements data, balance amounts and date, Owner financial advisor reference data and entity data, Relationships. | G6: ='Table-View(LOAN_POS_DTLS)'!G14 -> The CDS assigned identifier for the arrangement - used for data lineage The relationship of the loan is identified by arrangement id. For syndicate loans this is the facility arrangement. | H6: =IF('Table-View(LOAN_POS_DTLS)'!D14="No","NOT NULL","NULL") -> NOT NULL | K6: Light House DataDictionary
A7: Liability Balance | C7: ='Table-View(LOAN_POS_DTLS)'!A15 -> Brokerage Arrangement Id | E7: NUMERIC(38,0) | F7: This consists the list/tally of liability positions or loans consisting of Arrangements data, balance amounts and date, Owner financial advisor reference data and entity data, Relationships. | G7: ='Table-View(LOAN_POS_DTLS)'!G15 -> Associated Broker Arrangement Identifier (eg. AR ID for brokerage acct linked to Loan), if linked. | H7: =IF('Table-View(LOAN_POS_DTLS)'!D15="No","NOT NULL","NULL") -> NULL | K7: Light House DataDictionary
A8: Liability Balance | C8: ='Table-View(LOAN_POS_DTLS)'!A16 -> Account Id | E8: NUMERIC(38,0) | F8: This consists the list/tally of liability positions or loans consisting of Arrangements data, balance amounts and date, Owner financial advisor reference data and entity data, Relationships. | G8: ='Table-View(LOAN_POS_DTLS)'!G16 -> The CDS assigned identifier for the account - used for data lineage. Account Id represents the identifier for the bank account associated with the arrangement. Multiple accounts can be associated with single arrangement, for syndicate loans it represents loan taken for the facilities. | H8: =IF('Table-View(LOAN_POS_DTLS)'!D16="No","NOT NULL","NULL") -> NULL | K8: Light House DataDictionary
A9: Liability Balance | C9: ='Table-View(LOAN_POS_DTLS)'!A17 -> Accounting Type Code | E9: VARCHAR(1) | F9: This consists the list/tally of liability positions or loans consisting of Arrangements data, balance amounts and date, Owner financial advisor reference data and entity data, Relationships. | G9: ='Table-View(LOAN_POS_DTLS)'!G17 -> Code for the Accounting Type | H9: =IF('Table-View(LOAN_POS_DTLS)'!D17="No","NOT NULL","NULL") -> NULL | K9: Light House DataDictionary
A10: Liability Balance | C10: ='Table-View(LOAN_POS_DTLS)'!A18 -> Asset Liability Position Identifier | E10: NUMERIC(38,0) | F10: This consists the list/tally of liability positions or loans consisting of Arrangements data, balance amounts and date, Owner financial advisor reference data and entity data, Relationships. | G10: ='Table-View(LOAN_POS_DTLS)'!G18 -> Numeric identifier of the Asset Liability Position assigned by CDS included as degenerate Dim supporting linneage | H10: =IF('Table-View(LOAN_POS_DTLS)'!D18="No","NOT NULL","NULL") -> NULL | K10: Light House DataDictionary
A11: Liability Balance | C11: ='Table-View(LOAN_POS_DTLS)'!A19 -> Owed in Currency Balance Amount | E11: NUMERIC(36,8) | F11: This consists the list/tally of liability positions or loans consisting of Arrangements data, balance amounts and date, Owner financial advisor reference data and entity data, Relationships. | G11: ='Table-View(LOAN_POS_DTLS)'!G19 -> Balance amount on the loan, in loan owed Currency. | H11: =IF('Table-View(LOAN_POS_DTLS)'!D19="No","NOT NULL","NULL") -> NULL | K11: Light House DataDictionary
A12: Liability Balance | C12: ='Table-View(LOAN_POS_DTLS)'!A20 -> Local Currency Balance Amount | E12: NUMERIC(36,8) | F12: This consists the list/tally of liability positions or loans consisting of Arrangements data, balance amounts and date, Owner financial advisor reference data and entity data, Relationships. | G12: ='Table-View(LOAN_POS_DTLS)'!G20 -> Balance amount on the loan in currency of the place where loan is issued. | H12: =IF('Table-View(LOAN_POS_DTLS)'!D20="No","NOT NULL","NULL") -> NULL | K12: Light House DataDictionary
A13: Liability Balance | C13: ='Table-View(LOAN_POS_DTLS)'!A21 -> USD Currency Balance Amount | E13: NUMERIC(36,8) | F13: This consists the list/tally of liability positions or loans consisting of Arrangements data, balance amounts and date, Owner financial advisor reference data and entity data, Relationships. | G13: ='Table-View(LOAN_POS_DTLS)'!G21 -> Balance amount on the loan in USD currency. It is called Realized Compound Yield General Ledger Balance Amount in source system. | H13: =IF('Table-View(LOAN_POS_DTLS)'!D21="No","NOT NULL","NULL") -> NULL | K13: Light House DataDictionary
... A29: Liability Balance | C29: ='Table-View(LOAN_POS_DTLS)'!A37 -> Original Account Number | E29: VARCHAR(20) | F29: This consists the list/tally of liability positions or loans consisting of Arrangements data, balance amounts and date, Owner financial advisor reference data and entity data, Relationships. | G29: ='Table-View(LOAN_POS_DTLS)'!G37 -> The set of alphanumeric characters that identifies the unique instantiation of an Account Arrangement. | H29: =IF('Table-View(LOAN_POS_DTLS)'!D37="No","NOT NULL","NULL") -> NULL | K29: Light House DataDictionary

Sheet Grian
A1: Arrangement Id
A2: Balance Date
A3: Asset Liability Position Identifier
A4: Balance Type Id
A5: Owed in Currency Code
A6: Expense Code Id
A7: Portfolio Type Id
A8: Period Type Id
A9: General Ledger Account number
A10: General Ledger Type Id
A11: original account number

Sheet Sheet1
A1: For LOANIQ we don't have Linked brokerage arrangements
