Workbook

Sheet Table-View (2)
A1: 1. View Name - | I1: Please read review comments on Table Functional Description, Data Type and Business Definition
A2: 2. Table Name - | B2: AVY_FACT_SIDE
A3: 3. View Schema Name -
A4: 4. Table Schema Name - | B4: TRANSACTIONS_OWNER
A5: 5. Table Functional Description - | B5: This table consists of trades and transactions (Cash and Securities) to meet investment objective of a client. | I5: BA Responsbility | J5: BA Responsbility | K5: BA Responsbility | L5: DA Responsibility
A6: 6. Filter Criteria - | B6: Transaction Trade Date >= DATE '2017-10-01'. Refer to [ETL Notes] tab for more filters
A7: 7. Grain (Logical primary key) - | B7: Refer to [ETL Notes] tab
A8: 8. Semantic View Schema Name -
A9: 9. Semantic View Name -
A10: Note:
A11: Lighthouse Target | Y11: Source | AD11: Transformation
A12: Logical Name of Attribute (Name of column in View without underscores) | B12: Physical Name of Attribute (Name of column in Table) Supplied by DA Team | C12: Semantic Column Name | D12: Data type in Oracle VARCHAR2(n), DATE, NUMBER(m,n), TIMETSTAMP(6) | E12: Nullable in Table and in Oracle View NULL, NOT NULL | F12: Data type in Redshift | G12: Nullable in RedshiftTable | H12: Business Definition (To go into comments and into Meta Data Hub) | I12: Sample data values | J12: Action on Attribute Add,Update,Remove, Blank | K12: Action Version | L12: Table PBI Number | M12: List Functional PBI | N12: Include in View. Populated with N only when not to be shown in the view. | O12: Is on Data Model DA responsibility | P12: Model Data Type match TRUE/FALSE DA Responsibilty | Q12: Column2 | R12: Model Defs. Match | S12: Model Nullable Match | T12: On Table | U12: table data type | V12: table Nullable | W12: table defintions | X12: On View | Y12: Source Schema | Z12: Source Table | AA12: Source Attribute Name | AB12: Data Type | AC12: Nullable? | AD12: Transformation /Business Rules /Join Conditions | AE12: Notes / Comments | AF12: Indicator | AG12: Domain | AH12: Cross-Domain
A13: SHADOW Transaction Type Code | B13: SHDW_TXN_TP_CD | C13: Shadow_Transaction_Type_Code | D13: VARCHAR2(50) | E13: Yes | F13: character varying(50) | G13: Yes | H13: Possible values: ORG, OLD, NEW, REV, REP. | I13: OLD ORG REP REV NEW | J13: Add | K13: 3 | O13: =VLOOKUP(A13,[1]Model!C$2:J$559,2,FALSE)=B13 -> TRUE | P13: =VLOOKUP(A13,Model!C$2:G$228,5,FALSE)=D13 -> #N/A | Q13: =VLOOKUP(A13,[2]Model!C$2:L$228,8,FALSE) -> 179 | R13: =VLOOKUP(A13,[2]Model!C$2:G$228,3,FALSE)=[3]!Table14[[#This Row],[Business Definition (To go into comments and into Meta Data Hub)]] -> #REF! | S13: =IF([3]!Table14[[#This Row],[Nullable in Table and in Oracle View NULL, NOT NULL]]="No","NOT NULL","NULL")=VLOOKUP(A13,[2]Model!C$2:I$228,6,FALSE) -> #REF! | T13: =VLOOKUP(B13,[2]Table!A$2:F$415,1,FALSE)=[3]!Table14[[#This Row],[Physical Name of Attribute (Name of column in Table) Supplied by DA Team]] -> #REF! | U13: =VLOOKUP(B13,Table!A$2:F$319,2,FALSE)=Table14[[#This Row],[Data type in Oracle VARCHAR2(n), DATE, NUMBER(m,n), TIMETSTAMP(6)]] -> FALSE | V13: =VLOOKUP(B13,Table!A$2:F$231,3,FALSE)=Table14[[#This Row],[Nullable in Table and in Oracle View NULL, NOT NULL]] -> TRUE | W13: =VLOOKUP(B13,Table!A$2:H$228,6,FALSE)=Table14[[#This Row],[Business Definition (To go into comments and into Meta Data Hub)]] -> TRUE | X13: =VLOOKUP((UPPER(SUBSTITUTE(A13," ","_"))),'[2]Consumer View'!A$2:I$329,1,FALSE) -> SHADOW_TRANSACTION_TYPE_CODE | Y13: CCAL_REPL_OWNER | Z13: TXN | AA13: SRC_TXN_TP | AH13: N
A14: SHADOW Transaction Type Name | B14: SHDW_TXN_TP_NM | C14: Shadow_Transaction_Type | D14: VARCHAR2(50) | E14: Yes | F14: character varying(50) | G14: Yes | H14: Name of the Shadow Transaction Type Code. | J14: Add | K14: 3 | O14: =VLOOKUP(A14,[1]Model!C$2:J$559,2,FALSE)=B14 -> TRUE | P14: =VLOOKUP(A14,Model!C$2:G$228,5,FALSE)=D14 -> #N/A | Q14: =VLOOKUP(A14,[2]Model!C$2:L$228,8,FALSE) -> 177 | R14: =VLOOKUP(A14,[2]Model!C$2:G$228,3,FALSE)=[3]!Table14[[#This Row],[Business Definition (To go into comments and into Meta Data Hub)]] -> #REF! | S14: =IF([3]!Table14[[#This Row],[Nullable in Table and in Oracle View NULL, NOT NULL]]="No","NOT NULL","NULL")=VLOOKUP(A14,[2]Model!C$2:I$228,6,FALSE) -> #REF! | T14: =VLOOKUP(B14,[2]Table!A$2:F$415,1,FALSE)=[3]!Table14[[#This Row],[Physical Name of Attribute (Name of column in Table) Supplied by DA Team]] -> #REF! | U14: =VLOOKUP(B14,Table!A$2:F$319,2,FALSE)=Table14[[#This Row],[Data type in Oracle VARCHAR2(n), DATE, NUMBER(m,n), TIMETSTAMP(6)]] -> FALSE | V14: =VLOOKUP(B14,Table!A$2:F$231,3,FALSE)=Table14[[#This Row],[Nullable in Table and in Oracle View NULL, NOT NULL]] -> TRUE | W14: =VLOOKUP(B14,Table!A$2:H$228,6,FALSE)=Table14[[#This Row],[Business Definition (To go into comments and into Meta Data Hub)]] -> TRUE | X14: =VLOOKUP((UPPER(SUBSTITUTE(A14," ","_"))),'[2]Consumer View'!A$2:I$329,1,FALSE) -> SHADOW_TRANSACTION_TYPE_NAME | Y14: CCAL_REPL_OWNER | Z14: SHDW_TXN_TP | AA14: SRC_TXN_TP_NM | AD14: Look up using TXN.SRC_TXN_TP=SHDW_TXN_TP.SRC_TXN_TP | AH14: N
A15: IMPACT Source Action Code | B15: IMP_SRC_ACTN_CD | C15: IMPACT_Source_Action_Code | D15: VARCHAR2(1) | E15: Yes | F15: character varying(1) | G15: Yes | H15: Code representing Action Type in IMPACT source system | I15: M C I F A P N R Y S K Q U V T | J15: Add | K15: 3 | O15: =VLOOKUP(A15,[1]Model!C$2:J$559,2,FALSE)=B15 -> TRUE | P15: =VLOOKUP(A15,Model!C$2:G$228,5,FALSE)=D15 -> TRUE | Q15: =VLOOKUP(A15,[2]Model!C$2:L$228,8,FALSE) -> 181 | R15: =VLOOKUP(A15,[2]Model!C$2:G$228,3,FALSE)=[3]!Table14[[#This Row],[Business Definition (To go into comments and into Meta Data Hub)]] -> #REF! | S15: =IF([3]!Table14[[#This Row],[Nullable in Table and in Oracle View NULL, NOT NULL]]="No","NOT NULL","NULL")=VLOOKUP(A15,[2]Model!C$2:I$228,6,FALSE) -> #REF! | T15: =VLOOKUP(B15,[2]Table!A$2:F$415,1,FALSE)=[3]!Table14[[#This Row],[Physical Name of Attribute (Name of column in Table) Supplied by DA Team]] -> #REF! | U15: =VLOOKUP(B15,Table!A$2:F$319,2,FALSE)=Table14[[#This Row],[Data type in Oracle VARCHAR2(n), DATE, NUMBER(m,n), TIMETSTAMP(6)]] -> FALSE | V15: =VLOOKUP(B15,Table!A$2:F$231,3,FALSE)=Table14[[#This Row],[Nullable in Table and in Oracle View NULL, NOT NULL]] -> TRUE | W15: =VLOOKUP(B15,Table!A$2:H$228,6,FALSE)=Table14[[#This Row],[Business Definition (To go into comments and into Meta Data Hub)]] -> TRUE | X15: =VLOOKUP((UPPER(SUBSTITUTE(A15," ","_"))),'[2]Consumer View'!A$2:I$329,1,FALSE) -> IMPACT_SOURCE_ACTION_CODE | Y15: CCAL_REPL_OWNER | Z15: TXN | AA15: SRC_ACTN_CODE | AH15: N
A16: IMPACT Source Action Name | B16: IMP_SRC_ACTN_NM | C16: IMPACT_Source_Action | D16: VARCHAR2(100) | E16: Yes | F16: character varying(100) | G16: Yes | H16: Name representing Action Type in IMPACT source system | I16: 1 Security offering document is changed A Amend B Blind Broker Fail C Cancel D Trade Settled F Pool Factor Change I Insert K Failed Trade L Trade Canceled (was matched) M Trade Matched (was unmatched) N Trade Settled O Failed obligation in Net P Trade Settled Q Trade Revision R Rate Revision S Trade Settled T Failed Trade U Trade Un-Netted V DK W Trade Revision X Trade Unmatched (was matched) Y Trade Settled | J16: Add | K16: 3 | O16: =VLOOKUP(A16,[1]Model!C$2:J$559,2,FALSE)=B16 -> TRUE | P16: =VLOOKUP(A16,Model!C$2:G$228,5,FALSE)=D16 -> TRUE | Q16: =VLOOKUP(A16,[2]Model!C$2:L$228,8,FALSE) -> 183 | R16: =VLOOKUP(A16,[2]Model!C$2:G$228,3,FALSE)=[3]!Table14[[#This Row],[Business Definition (To go into comments and into Meta Data Hub)]] -> #REF! | S16: =IF([3]!Table14[[#This Row],[Nullable in Table and in Oracle View NULL, NOT NULL]]="No","NOT NULL","NULL")=VLOOKUP(A16,[2]Model!C$2:I$228,6,FALSE) -> #REF! | T16: =VLOOKUP(B16,[2]Table!A$2:F$415,1,FALSE)=[3]!Table14[[#This Row],[Physical Name of Attribute (Name of column in Table) Supplied by DA Team]] -> #REF! | U16: =VLOOKUP(B16,Table!A$2:F$319,2,FALSE)=Table14[[#This Row],[Data type in Oracle VARCHAR2(n), DATE, NUMBER(m,n), TIMETSTAMP(6)]] -> FALSE | V16: =VLOOKUP(B16,Table!A$2:F$231,3,FALSE)=Table14[[#This Row],[Nullable in Table and in Oracle View NULL, NOT NULL]] -> TRUE | W16: =VLOOKUP(B16,Table!A$2:H$228,6,FALSE)=Table14[[#This Row],[Business Definition (To go into comments and into Meta Data Hub)]] -> TRUE | X16: =VLOOKUP((UPPER(SUBSTITUTE(A16," ","_"))),'[2]Consumer View'!A$2:I$329,1,FALSE) -> IMPACT_SOURCE_ACTION_NAME | Y16: REFERENCE_REPL_OWNER | Z16: IMPCT_ACTION_LKU | AA16: desc_text | AD16: ccal_repl_owner.txn t left join ccal_repl_owner.impct_action_lku lk ON t.src_actn_code = impct_action_lku.action_code | AE16: Note to Dev team: IMPCT_ACTION_LKU table exists only in CDS DB but not available in SSDS/Lighthouse DB. [6/3/24]: Modified target data type for Oracle and Redshift. PBI 1912566 | AH16: N
A17: SIS Detailed Events Id | B17: SIS_DLTD_EV_ID | D17: NUMBER(38,0) | E17: Yes | F17: numeric (38,0) | G17: Yes | H17: Identifier that determines what type of transaction the record contains. For SIS activity the values depend on the record type. | I17: 3214 | J17: Add | K17: 3 | O17: =VLOOKUP(A17,[1]Model!C$2:J$559,2,FALSE)=B17 -> TRUE | P17: =VLOOKUP(A17,Model!C$2:G$228,5,FALSE)=D17 -> #N/A | Q17: =VLOOKUP(A17,[2]Model!C$2:L$228,8,FALSE) -> 144 | R17: =VLOOKUP(A17,[2]Model!C$2:G$228,3,FALSE)=[3]!Table14[[#This Row],[Business Definition (To go into comments and into Meta Data Hub)]] -> #REF! | S17: =IF([3]!Table14[[#This Row],[Nullable in Table and in Oracle View NULL, NOT NULL]]="No","NOT NULL","NULL")=VLOOKUP(A17,[2]Model!C$2:I$228,6,FALSE) -> #REF! | T17: =VLOOKUP(B17,[2]Table!A$2:F$415,1,FALSE)=[3]!Table14[[#This Row],[Physical Name of Attribute (Name of column in Table) Supplied by DA Team]] -> #REF! | U17: =VLOOKUP(B17,Table!A$2:F$319,2,FALSE)=Table14[[#This Row],[Data type in Oracle VARCHAR2(n), DATE, NUMBER(m,n), TIMETSTAMP(6)]] -> TRUE | V17: =VLOOKUP(B17,Table!A$2:F$231,3,FALSE)=Table14[[#This Row],[Nullable in Table and in Oracle View NULL, NOT NULL]] -> TRUE | W17: =VLOOKUP(B17,Table!A$2:H$228,6,FALSE)=Table14[[#This Row],[Business Definition (To go into comments and into Meta Data Hub)]] -> TRUE | X17: =VLOOKUP((UPPER(SUBSTITUTE(A17," ","_"))),'[2]Consumer View'!A$2:I$329,1,FALSE) -> SIS_DETAILED_EVENTS_ID | Y17: CCAL_REPL_OWNER | Z17: TXN | AA17: SRC_BUY_SELL_MULTI_ID | AE17: [6/3/24]: Modified target data type for Oracle and Redshift. PBI 1912566 | AH17: N
A18: SIS Detailed Events Name | B18: SIS_DLTD_EV_NM | C18: SIS_Detailed_Event_Name | D18: VARCHAR2(200) | E18: Yes | F18: character varying(200) | G18: Yes | H18: Name that determines what type of transaction the record contains. For SIS activity the values depend on the record type. | I18: 3219 Stock dividends 3214 Cash Dividend 3247 Corporate actions 3229 Cash receipts 3230 Disbursements 3234 Credit interest or Foreign Withholding 3246 Disbursements (receive stock) 3233 Debit interest 3231 Journals, Income, Expenses 3245 Cash receipts (deliver stock) | J18: Add | K18: 3 | O18: =VLOOKUP(A18,[1]Model!C$2:J$559,2,FALSE)=B18 -> TRUE | P18: =VLOOKUP(A18,Model!C$2:G$228,5,FALSE)=D18 -> #N/A | Q18: =VLOOKUP(A18,[2]Model!C$2:L$228,8,FALSE) -> 145 | R18: =VLOOKUP(A18,[2]Model!C$2:G$228,3,FALSE)=[3]!Table14[[#This Row],[Business Definition (To go into comments and into Meta Data Hub)]] -> #REF! | S18: =IF([3]!Table14[[#This Row],[Nullable in Table and in Oracle View NULL, NOT NULL]]="No","NOT NULL","NULL")=VLOOKUP(A18,[2]Model!C$2:I$228,6,FALSE) -> #REF! | T18: =VLOOKUP(B18,[2]Table!A$2:F$415,1,FALSE)=[3]!Table14[[#This Row],[Physical Name of Attribute (Name of column in Table) Supplied by DA Team]] -> #REF! | U18: =VLOOKUP(B18,Table!A$2:F$319,2,FALSE)=Table14[[#This Row],[Data type in Oracle VARCHAR2(n), DATE, NUMBER(m,n), TIMETSTAMP(6)]] -> FALSE | V18: =VLOOKUP(B18,Table!A$2:F$231,3,FALSE)=Table14[[#This Row],[Nullable in Table and in Oracle View NULL, NOT NULL]] -> TRUE | W18: =VLOOKUP(B18,Table!A$2:H$228,6,FALSE)=Table14[[#This Row],[Business Definition (To go into comments and into Meta Data Hub)]] -> TRUE | X18: =VLOOKUP((UPPER(SUBSTITUTE(A18," ","_"))),'[2]Consumer View'!A$2:I$329,1,FALSE) -> SIS_DETAILED_EVENTS_NAME | Y18: CCAL_REPL_OWNER | Z18: CL_VAL | AA18: CL_VAL_NM | AD18: ccal_repl_owner.cl_val cv left join ccal_repl_owner.cl_val cv ON cv.cl_val_id = t.SRC_BUY_SELL_MULTI_ID and cv.CL_SCM_ID = '99' | AE18: [6/3/24]: Modified target data type for Oracle and Redshift. PBI 1912566 | AH18: N (add Code, existing PBI)
A19: SIS User Id | B19: SIS_USR_ID | C19: SIS_User_Id | D19: VARCHAR2(255) | E19: Yes | F19: character varying(255) | G19: Yes | H19: Identifier of the process or user that creates the records sourced from SIS Money Movement | I19: LL015 | J19: Add | K19: 3 | O19: =VLOOKUP(A19,[1]Model!C$2:J$559,2,FALSE)=B19 -> TRUE | P19: =VLOOKUP(A19,Model!C$2:G$228,5,FALSE)=D19 -> #N/A | Q19: =VLOOKUP(A19,[2]Model!C$2:L$228,8,FALSE) -> 146 | R19: =VLOOKUP(A19,[2]Model!C$2:G$228,3,FALSE)=[3]!Table14[[#This Row],[Business Definition (To go into comments and into Meta Data Hub)]] -> #REF! | S19: =IF([3]!Table14[[#This Row],[Nullable in Table and in Oracle View NULL, NOT NULL]]="No","NOT NULL","NULL")=VLOOKUP(A19,[2]Model!C$2:I$228,6,FALSE) -> #REF! | T19: =VLOOKUP(B19,[2]Table!A$2:F$415,1,FALSE)=[3]!Table14[[#This Row],[Physical Name of Attribute (Name of column in Table) Supplied by DA Team]] -> #REF! | U19: =VLOOKUP(B19,Table!A$2:F$319,2,FALSE)=Table14[[#This Row],[Data type in Oracle VARCHAR2(n), DATE, NUMBER(m,n), TIMETSTAMP(6)]] -> FALSE | V19: =VLOOKUP(B19,Table!A$2:F$231,3,FALSE)=Table14[[#This Row],[Nullable in Table and in Oracle View NULL, NOT NULL]] -> TRUE | W19: =VLOOKUP(B19,Table!A$2:H$228,6,FALSE)=Table14[[#This Row],[Business Definition (To go into comments and into Meta Data Hub)]] -> TRUE | X19: =VLOOKUP((UPPER(SUBSTITUTE(A19," ","_"))),'[2]Consumer View'!A$2:I$329,1,FALSE) -> SIS_USER_ID | Y19: CCAL_REPL_OWNER | Z19: TXN | AA19: USR_ID | AH19: N
A20: SIS Account Classification Code | B20: SIS_AC_CL_CD | C20: SIS_Account_Classification_Code | D20: VARCHAR2(50) | E20: Yes | F20: character varying(50) | G20: Yes | H20: SIS account classification codes | I20: Z | J20: Add | K20: 3 | O20: =VLOOKUP(A20,[1]Model!C$2:J$559,2,FALSE)=B20 -> TRUE | P20: =VLOOKUP(A20,Model!C$2:G$228,5,FALSE)=D20 -> #N/A | Q20: =VLOOKUP(A20,[2]Model!C$2:L$228,8,FALSE) -> 147 | R20: =VLOOKUP(A20,[2]Model!C$2:G$228,3,FALSE)=[3]!Table14[[#This Row],[Business Definition (To go into comments and into Meta Data Hub)]] -> #REF! | S20: =IF([3]!Table14[[#This Row],[Nullable in Table and in Oracle View NULL, NOT NULL]]="No","NOT NULL","NULL")=VLOOKUP(A20,[2]Model!C$2:I$228,6,FALSE) -> #REF! | T20: =VLOOKUP(B20,[2]Table!A$2:F$415,1,FALSE)=[3]!Table14[[#This Row],[Physical Name of Attribute (Name of column in Table) Supplied by DA Team]] -> #REF! | U20: =VLOOKUP(B20,Table!A$2:F$319,2,FALSE)=Table14[[#This Row],[Data type in Oracle VARCHAR2(n), DATE, NUMBER(m,n), TIMETSTAMP(6)]] -> FALSE | V20: =VLOOKUP(B20,Table!A$2:F$231,3,FALSE)=Table14[[#This Row],[Nullable in Table and in Oracle View NULL, NOT NULL]] -> TRUE | W20: =VLOOKUP(B20,Table!A$2:H$228,6,FALSE)=Table14[[#This Row],[Business Definition (To go into comments and into Meta Data Hub)]] -> TRUE | X20: =VLOOKUP((UPPER(SUBSTITUTE(A20," ","_"))),'[2]Consumer View'!A$2:I$329,1,FALSE) -> SIS_ACCOUNT_CLASSIFICATION_CODE | Y20: CCAL_REPL_OWNER | Z20: TXN | AA20: SRC_PRIM_CL | AH20: N
A21: Source Cancellation Reason Id | B21: SRC_CNCL_RSN_ID | D21: NUMBER(38,0) | E21: Yes | F21: NUMERIC(38,0) | G21: Yes | H21: Id representing Reason for cancellation in source system | I21: 3248, 3249 | J21: Add | K21: 3 | O21: =VLOOKUP(A21,[1]Model!C$2:J$559,2,FALSE)=B21 -> TRUE | P21: =VLOOKUP(A21,Model!C$2:G$228,5,FALSE)=D21 -> #N/A | Q21: =VLOOKUP(A21,[2]Model!C$2:L$228,8,FALSE) -> 148 | R21: =VLOOKUP(A21,[2]Model!C$2:G$228,3,FALSE)=[3]!Table14[[#This Row],[Business Definition (To go into comments and into Meta Data Hub)]] -> #REF! | S21: =IF([3]!Table14[[#This Row],[Nullable in Table and in Oracle View NULL, NOT NULL]]="No","NOT NULL","NULL")=VLOOKUP(A21,[2]Model!C$2:I$228,6,FALSE) -> #REF! | T21: =VLOOKUP(B21,[2]Table!A$2:F$415,1,FALSE)=[3]!Table14[[#This Row],[Physical Name of Attribute (Name of column in Table) Supplied by DA Team]] -> #REF! | U21: =VLOOKUP(B21,Table!A$2:F$319,2,FALSE)=Table14[[#This Row],[Data type in Oracle VARCHAR2(n), DATE, NUMBER(m,n), TIMETSTAMP(6)]] -> TRUE | V21: =VLOOKUP(B21,Table!A$2:F$231,3,FALSE)=Table14[[#This Row],[Nullable in Table and in Oracle View NULL, NOT NULL]] -> TRUE | W21: =VLOOKUP(B21,Table!A$2:H$228,6,FALSE)=Table14[[#This Row],[Business Definition (To go into comments and into Meta Data Hub)]] -> TRUE | X21: =VLOOKUP((UPPER(SUBSTITUTE(A21," ","_"))),'[2]Consumer View'!A$2:I$329,1,FALSE) -> SOURCE_CANCELLATION_REASON_ID | Y21: CCAL_REPL_OWNER | Z21: TXN | AA21: SRC_CNCL_RSN_ID | AH21: N
A22: Source Cancellation Reason Code | B22: SRC_CNCL_RSN_CD | C22: Source_Cancellation_Reason_Code | D22: VARCHAR2(20) | E22: Yes | F22: character varying(20) | G22: Yes | H22: Code representing Reason for cancellation in source system Valid Values - A ,N, Y, null/blank Valid values include: 'Y' - Trade is cancelled due to correction, and will not be processed as a new trade 'N' - Trade is an outright cancel. 'A' - Trade is a cancel/correction due to allocation, and will be processed as allocated trade. | I22: Y, N, A, null | J22: Add | K22: 3 | O22: =VLOOKUP(A22,[1]Model!C$2:J$559,2,FALSE)=B22 -> TRUE | P22: =VLOOKUP(A22,Model!C$2:G$228,5,FALSE)=D22 -> #N/A | Q22: =VLOOKUP(A22,[2]Model!C$2:L$228,8,FALSE) -> 149 | R22: =VLOOKUP(A22,[2]Model!C$2:G$228,3,FALSE)=[3]!Table14[[#This Row],[Business Definition (To go into comments and into Meta Data Hub)]] -> #VALUE! | S22: =IF([3]!Table14[[#This Row],[Nullable in Table and in Oracle View NULL, NOT NULL]]="No","NOT NULL","NULL")=VLOOKUP(A22,[2]Model!C$2:I$228,6,FALSE) -> #REF! | T22: =VLOOKUP(B22,[2]Table!A$2:F$415,1,FALSE)=[3]!Table14[[#This Row],[Physical Name of Attribute (Name of column in Table) Supplied by DA Team]] -> #REF! | U22: =VLOOKUP(B22,Table!A$2:F$319,2,FALSE)=Table14[[#This Row],[Data type in Oracle VARCHAR2(n), DATE, NUMBER(m,n), TIMETSTAMP(6)]] -> FALSE | V22: =VLOOKUP(B22,Table!A$2:F$231,3,FALSE)=Table14[[#This Row],[Nullable in Table and in Oracle View NULL, NOT NULL]] -> TRUE | W22: =VLOOKUP(B22,Table!A$2:H$228,6,FALSE)=Table14[[#This Row],[Business Definition (To go into comments and into Meta Data Hub)]] -> FALSE | X22: =VLOOKUP((UPPER(SUBSTITUTE(A22," ","_"))),'[2]Consumer View'!A$2:I$329,1,FALSE) -> SOURCE_CANCELLATION_REASON_CODE | Y22: CCAL_REPL_OWNER | Z22: CL_VAL | AA22: CL_VAL_CODE | AD22: ccal_repl_owner.txn t left join ccal_repl_owner.cl_val cv ON cl_val.cl_val_id = t.SRC_CNCL_RSN_ID cs.cl_scm_id = '102' | AE22: [6/3/24]: Modified target data type for Oracle and Redshift. PBI 1912566 | AH22: N
A23: Source Cancellation Reason Name | B23: SRC_CNCL_RSN_NM | C23: Source_Cancellation_Reason | D23: VARCHAR2(200) | E23: Yes | F23: character varying(200) | G23: Yes | H23: Name representing Reason for cancellation in source system | I23: Correction Outright Cancel Account Allocation | J23: Add | K23: 3 | O23: =VLOOKUP(A23,[1]Model!C$2:J$559,2,FALSE)=B23 -> TRUE | P23: =VLOOKUP(A23,Model!C$2:G$228,5,FALSE)=D23 -> #N/A | Q23: =VLOOKUP(A23,[2]Model!C$2:L$228,8,FALSE) -> 150 | R23: =VLOOKUP(A23,[2]Model!C$2:G$228,3,FALSE)=[3]!Table14[[#This Row],[Business Definition (To go into comments and into Meta Data Hub)]] -> #REF! | S23: =IF([3]!Table14[[#This Row],[Nullable in Table and in Oracle View NULL, NOT NULL]]="No","NOT NULL","NULL")=VLOOKUP(A23,[2]Model!C$2:I$228,6,FALSE) -> #REF! | T23: =VLOOKUP(B23,[2]Table!A$2:F$415,1,FALSE)=[3]!Table14[[#This Row],[Physical Name of Attribute (Name of column in Table) Supplied by DA Team]] -> #REF! | U23: =VLOOKUP(B23,Table!A$2:F$319,2,FALSE)=Table14[[#This Row],[Data type in Oracle VARCHAR2(n), DATE, NUMBER(m,n), TIMETSTAMP(6)]] -> FALSE | V23: =VLOOKUP(B23,Table!A$2:F$231,3,FALSE)=Table14[[#This Row],[Nullable in Table and in Oracle View NULL, NOT NULL]] -> TRUE | W23: =VLOOKUP(B23,Table!A$2:H$228,6,FALSE)=Table14[[#This Row],[Business Definition (To go into comments and into Meta Data Hub)]] -> TRUE | X23: =VLOOKUP((UPPER(SUBSTITUTE(A23," ","_"))),'[2]Consumer View'!A$2:I$329,1,FALSE) -> SOURCE_CANCELLATION_REASON_NAME | Y23: CCAL_REPL_OWNER | Z23: CL_VAL | AA23: CL_VAL_NM | AD23: ccal_repl_owner.txn t left join ccal_repl_owner.cl_val cv ON cl_val.cl_val_id = t.SRC_CNCL_RSN_ID cs.cl_scm_id = '102' | AH23: N
A24: Source Transaction Sequence Number | B24: SRC_TXN_SEQ_NUM | C24: Source_Transaction_Sequence_Number | D24: NUMBER(38,0) | E24: Yes | F24: NUMERIC(38,0) | G24: Yes | H24: Transaction number assigned to the transaction in the source system. | I24: 2878 | J24: Add | K24: 3 | O24: =VLOOKUP(A24,[1]Model!C$2:J$559,2,FALSE)=B24 -> TRUE | P24: =VLOOKUP(A24,Model!C$2:G$228,5,FALSE)=D24 -> #N/A | Q24: =VLOOKUP(A24,[2]Model!C$2:L$228,8,FALSE) -> 151 | R24: =VLOOKUP(A24,[2]Model!C$2:G$228,3,FALSE)=[3]!Table14[[#This Row],[Business Definition (To go into comments and into Meta Data Hub)]] -> #REF! | S24: =IF([3]!Table14[[#This Row],[Nullable in Table and in Oracle View NULL, NOT NULL]]="No","NOT NULL","NULL")=VLOOKUP(A24,[2]Model!C$2:I$228,6,FALSE) -> #REF! | T24: =VLOOKUP(B24,[2]Table!A$2:F$415,1,FALSE)=[3]!Table14[[#This Row],[Physical Name of Attribute (Name of column in Table) Supplied by DA Team]] -> #REF! | U24: =VLOOKUP(B24,Table!A$2:F$319,2,FALSE)=Table14[[#This Row],[Data type in Oracle VARCHAR2(n), DATE, NUMBER(m,n), TIMETSTAMP(6)]] -> TRUE | V24: =VLOOKUP(B24,Table!A$2:F$231,3,FALSE)=Table14[[#This Row],[Nullable in Table and in Oracle View NULL, NOT NULL]] -> TRUE | W24: =VLOOKUP(B24,Table!A$2:H$228,6,FALSE)=Table14[[#This Row],[Business Definition (To go into comments and into Meta Data Hub)]] -> TRUE | X24: =VLOOKUP((UPPER(SUBSTITUTE(A24," ","_"))),'[2]Consumer View'!A$2:I$329,1,FALSE) -> SOURCE_TRANSACTION_SEQUENCE_NUMBER | Y24: CCAL_REPL_OWNER | Z24: TXN | AA24: SRC_TXN_SEQ_NUM | AH24: N
A25: Dividend Record Date | B25: DVDN_RCRD_DT | C25: Dividend_Record_Date | D25: DATE | E25: Yes | F25: timestamp without time zone | G25: Yes | H25: The cut-off date that an organization is expected to use to determine which shareholders are eligible to receive a dividend or income distribution. | I25: 42398 | J25: Add | K25: 3 | O25: =VLOOKUP(A25,[1]Model!C$2:J$559,2,FALSE)=B25 -> TRUE | P25: =VLOOKUP(A25,Model!C$2:G$228,5,FALSE)=D25 -> TRUE | Q25: =VLOOKUP(A25,[2]Model!C$2:L$228,8,FALSE) -> 152 | R25: =VLOOKUP(A25,[2]Model!C$2:G$228,3,FALSE)=[3]!Table14[[#This Row],[Business Definition (To go into comments and into Meta Data Hub)]] -> #REF! | S25: =IF([3]!Table14[[#This Row],[Nullable in Table and in Oracle View NULL, NOT NULL]]="No","NOT NULL","NULL")=VLOOKUP(A25,[2]Model!C$2:I$228,6,FALSE) -> #REF! | T25: =VLOOKUP(B25,[2]Table!A$2:F$415,1,FALSE)=[3]!Table14[[#This Row],[Physical Name of Attribute (Name of column in Table) Supplied by DA Team]] -> #REF! | U25: =VLOOKUP(B25,Table!A$2:F$319,2,FALSE)=Table14[[#This Row],[Data type in Oracle VARCHAR2(n), DATE, NUMBER(m,n), TIMETSTAMP(6)]] -> TRUE | V25: =VLOOKUP(B25,Table!A$2:F$231,3,FALSE)=Table14[[#This Row],[Nullable in Table and in Oracle View NULL, NOT NULL]] -> TRUE | W25: =VLOOKUP(B25,Table!A$2:H$228,6,FALSE)=Table14[[#This Row],[Business Definition (To go into comments and into Meta Data Hub)]] -> TRUE | X25: =VLOOKUP((UPPER(SUBSTITUTE(A25," ","_"))),'[2]Consumer View'!A$2:I$329,1,FALSE) -> DIVIDEND_RECORD_DATE | Y25: CCAL_REPL_OWNER | Z25: TXN | AA25: DVDN_RCRD_DT | AH25: N
A26: Owner IMPACT FA Number | B26: OWN_IMP_FA_NUM | C26: Brokerage_Owner_FA_Fixed_Income_IMPACT_Number | D26: VARCHAR2(20) | E26: Yes | F26: character varying(20) | G26: Yes | H26: FA Number as given in Impact system | I26: 01A | J26: Add | K26: 3 | O26: =VLOOKUP(A26,[1]Model!C$2:J$559,2,FALSE)=B26 -> TRUE | P26: =VLOOKUP(A26,Model!C$2:G$228,5,FALSE)=D26 -> TRUE | Q26: =VLOOKUP(A26,[2]Model!C$2:L$228,8,FALSE) -> 153 | R26: =VLOOKUP(A26,[2]Model!C$2:G$228,3,FALSE)=[3]!Table14[[#This Row],[Business Definition (To go into comments and into Meta Data Hub)]] -> #REF! | S26: =IF([3]!Table14[[#This Row],[Nullable in Table and in Oracle View NULL, NOT NULL]]="No","NOT NULL","NULL")=VLOOKUP(A26,[2]Model!C$2:I$228,6,FALSE) -> #REF! | T26: =VLOOKUP(B26,[2]Table!A$2:F$415,1,FALSE)=[3]!Table14[[#This Row],[Physical Name of Attribute (Name of column in Table) Supplied by DA Team]] -> #REF! | U26: =VLOOKUP(B26,Table!A$2:F$319,2,FALSE)=Table14[[#This Row],[Data type in Oracle VARCHAR2(n), DATE, NUMBER(m,n), TIMETSTAMP(6)]] -> FALSE | V26: =VLOOKUP(B26,Table!A$2:F$231,3,FALSE)=Table14[[#This Row],[Nullable in Table and in Oracle View NULL, NOT NULL]] -> TRUE | W26: =VLOOKUP(B26,Table!A$2:H$228,6,FALSE)=Table14[[#This Row],[Business Definition (To go into comments and into Meta Data Hub)]] -> TRUE | X26: =VLOOKUP((UPPER(SUBSTITUTE(A26," ","_"))),'[2]Consumer View'!A$2:I$329,1,FALSE) -> OWNER_IMPACT_FA_NUMBER | Y26: CCAL_REPL_OWNER | Z26: TXN | AA26: SALE_PSN_NUM | AH26: N
A27: Owner FA Number | B27: OWN_FA_NUM | C27: Brokerage_Owner_FA_Number | D27: VARCHAR2(6) | E27: Yes | F27: character varying(6) | G27: Yes | H27: Owner FA Number is a FA Number that owns the Arrangement for which activity is recorded | I27: 25T3 | J27: Add | K27: 3 | O27: =VLOOKUP(A27,[1]Model!C$2:J$559,2,FALSE)=B27 -> TRUE | P27: =VLOOKUP(A27,Model!C$2:G$228,5,FALSE)=D27 -> TRUE | Q27: =VLOOKUP(A27,[2]Model!C$2:L$228,8,FALSE) -> 154 | R27: =VLOOKUP(A27,[2]Model!C$2:G$228,3,FALSE)=[3]!Table14[[#This Row],[Business Definition (To go into comments and into Meta Data Hub)]] -> #REF! | S27: =IF([3]!Table14[[#This Row],[Nullable in Table and in Oracle View NULL, NOT NULL]]="No","NOT NULL","NULL")=VLOOKUP(A27,[2]Model!C$2:I$228,6,FALSE) -> #REF! | T27: =VLOOKUP(B27,[2]Table!A$2:F$415,1,FALSE)=[3]!Table14[[#This Row],[Physical Name of Attribute (Name of column in Table) Supplied by DA Team]] -> #REF! | U27: =VLOOKUP(B27,Table!A$2:F$319,2,FALSE)=Table14[[#This Row],[Data type in Oracle VARCHAR2(n), DATE, NUMBER(m,n), TIMETSTAMP(6)]] -> FALSE | V27: =VLOOKUP(B27,Table!A$2:F$231,3,FALSE)=Table14[[#This Row],[Nullable in Table and in Oracle View NULL, NOT NULL]] -> TRUE | W27: =VLOOKUP(B27,Table!A$2:H$228,6,FALSE)=Table14[[#This Row],[Business Definition (To go into comments and into Meta Data Hub)]] -> TRUE | X27: =VLOOKUP((UPPER(SUBSTITUTE(A27," ","_"))),'[2]Consumer View'!A$2:I$329,1,FALSE) -> OWNER_FA_NUMBER | Y27: CCSI_OWNER | Z27: AR_GRP_SUBDIM | AA27: FA_NUM | AD27: select fa.FA_NUM from ccal_repl_owner.txn t LEFT JOIN ccsi_owner.AR_GRP_SUBDIM fa ON t.AR_ID = fa.AR_ID and t.td >= fa.EFF_DT and t.td < fa.END_DT; | AE27: [9/11/24]: Reflected the change to use TXN.TD from Product Backlog Item 1912566: Change join condition and update data types for Activity | AH27: Y
A28: Owner FA Number Entity Code | B28: OWN_FA_NUM_ENT_CD | C28: Brokerage_Owner_FA_Number_Entity_Code | D28: VARCHAR2(20) | E28: Yes | F28: character varying(20) | G28: Yes | H28: Entity Code that owns the Owner FA Number | I28: 10D00 | J28: Add | K28: 3 | O28: =VLOOKUP(A28,[1]Model!C$2:J$559,2,FALSE)=B28 -> TRUE | P28: =VLOOKUP(A28,Model!C$2:G$228,5,FALSE)=D28 -> TRUE | Q28: =VLOOKUP(A28,[2]Model!C$2:L$228,8,FALSE) -> 155 | R28: =VLOOKUP(A28,[2]Model!C$2:G$228,3,FALSE)=[3]!Table14[[#This Row],[Business Definition (To go into comments and into Meta Data Hub)]] -> #REF! | S28: =IF([3]!Table14[[#This Row],[Nullable in Table and in Oracle View NULL, NOT NULL]]="No","NOT NULL","NULL")=VLOOKUP(A28,[2]Model!C$2:I$228,6,FALSE) -> #REF! | T28: =VLOOKUP(B28,[2]Table!A$2:F$415,1,FALSE)=[3]!Table14[[#This Row],[Physical Name of Attribute (Name of column in Table) Supplied by DA Team]] -> #REF! | U28: =VLOOKUP(B28,Table!A$2:F$319,2,FALSE)=Table14[[#This Row],[Data type in Oracle VARCHAR2(n), DATE, NUMBER(m,n), TIMETSTAMP(6)]] -> FALSE | V28: =VLOOKUP(B28,Table!A$2:F$231,3,FALSE)=Table14[[#This Row],[Nullable in Table and in Oracle View NULL, NOT NULL]] -> TRUE | W28: =VLOOKUP(B28,Table!A$2:H$228,6,FALSE)=Table14[[#This Row],[Business Definition (To go into comments and into Meta Data Hub)]] -> TRUE | X28: =VLOOKUP((UPPER(SUBSTITUTE(A28," ","_"))),'[2]Consumer View'!A$2:I$329,1,FALSE) -> OWNER_FA_NUMBER_ENTITY_CODE | Y28: SSDS_DAL_OWNER | Z28: FA_NUMBER_V | AA28: FA_NUMBER_ENTITY_CODE | AD28: Derive based on OWN_FA_NUM field. left join SSDS_DAL_OWNER.FA_NUMBER_V fn on fn.FA_NUMBER = OWN_FA_NUM and t.td >= fn.EFF_DT AND t.td < fn.END_DT | AE28: [6/8/24]: Modified target data type for Oracle and Redshift. PBI 1912566 [9/11/24]: Reflected the change to use TXN.TD from Product Backlog Item 1912566: Change join condition and update data types for Activity | AH28: Y
A29: Owner FA Employee Id | B29: FA_OWN_EMPE_ID | C29: Brokerage_Owner_FA_Responsible_Party_Employee_ID | D29: VARCHAR2(44) | E29: Yes | F29: character varying(44) | G29: Yes | H29: PeopleWorks Identifier for the Responsible Party for an FA Number | I29: 49139 | J29: Add | K29: 3 | O29: =VLOOKUP(A29,[1]Model!C$2:J$559,2,FALSE)=B29 -> TRUE | P29: =VLOOKUP(A29,Model!C$2:G$228,5,FALSE)=D29 -> TRUE | Q29: =VLOOKUP(A29,[2]Model!C$2:L$228,8,FALSE) -> 156 | R29: =VLOOKUP(A29,[2]Model!C$2:G$228,3,FALSE)=[3]!Table14[[#This Row],[Business Definition (To go into comments and into Meta Data Hub)]] -> #REF! | S29: =IF([3]!Table14[[#This Row],[Nullable in Table and in Oracle View NULL, NOT NULL]]="No","NOT NULL","NULL")=VLOOKUP(A29,[2]Model!C$2:I$228,6,FALSE) -> #REF! | T29: =VLOOKUP(B29,[2]Table!A$2:F$415,1,FALSE)=[3]!Table14[[#This Row],[Physical Name of Attribute (Name of column in Table) Supplied by DA Team]] -> #REF! | U29: =VLOOKUP(B29,Table!A$2:F$319,2,FALSE)=Table14[[#This Row],[Data type in Oracle VARCHAR2(n), DATE, NUMBER(m,n), TIMETSTAMP(6)]] -> FALSE | V29: =VLOOKUP(B29,Table!A$2:F$231,3,FALSE)=Table14[[#This Row],[Nullable in Table and in Oracle View NULL, NOT NULL]] -> TRUE | W29: =VLOOKUP(B29,Table!A$2:H$228,6,FALSE)=Table14[[#This Row],[Business Definition (To go into comments and into Meta Data Hub)]] -> TRUE | X29: =VLOOKUP((UPPER(SUBSTITUTE(A29," ","_"))),'[2]Consumer View'!A$2:I$329,1,FALSE) -> OWNER_FA_EMPLOYEE_ID | Y29: SSDS_DAL_OWNER | Z29: FA_NUMBER_V | AA29: RESPONSIBLE_PARTY_EMPLOYEE_ID | AE29: [6/8/24]: Modified target data type for Oracle and Redshift. PBI 1912566 | AH29: Y
A30: Owner FA Number Entity Enterprise Id | B30: OWN_FA_NUM_ENT_ENTP_ID | C30: Brokerage_Owner_FA_entity_enterprise_id | D30: NUMBER(22,0) | E30: Yes | F30: NUMERIC(22,0) | G30: Yes | H30: Enterprise Id of the Entity that owns the Owner FA Number | I30: AHK00 | J30: Add | K30: 3 | O30: =VLOOKUP(A30,[1]Model!C$2:J$559,2,FALSE)=B30 -> TRUE | P30: =VLOOKUP(A30,Model!C$2:G$228,5,FALSE)=D30 -> TRUE | Q30: =VLOOKUP(A30,[2]Model!C$2:L$228,8,FALSE) -> 157 | R30: =VLOOKUP(A30,[2]Model!C$2:G$228,3,FALSE)=[3]!Table14[[#This Row],[Business Definition (To go into comments and into Meta Data Hub)]] -> #REF! | S30: =IF([3]!Table14[[#This Row],[Nullable in Table and in Oracle View NULL, NOT NULL]]="No","NOT NULL","NULL")=VLOOKUP(A30,[2]Model!C$2:I$228,6,FALSE) -> #REF! | T30: =VLOOKUP(B30,[2]Table!A$2:F$415,1,FALSE)=[3]!Table14[[#This Row],[Physical Name of Attribute (Name of column in Table) Supplied by DA Team]] -> #REF! | U30: =VLOOKUP(B30,Table!A$2:F$319,2,FALSE)=Table14[[#This Row],[Data type in Oracle VARCHAR2(n), DATE, NUMBER(m,n), TIMETSTAMP(6)]] -> TRUE | V30: =VLOOKUP(B30,Table!A$2:F$231,3,FALSE)=Table14[[#This Row],[Nullable in Table and in Oracle View NULL, NOT NULL]] -> TRUE | W30: =VLOOKUP(B30,Table!A$2:H$228,6,FALSE)=Table14[[#This Row],[Business Definition (To go into comments and into Meta Data Hub)]] -> TRUE | X30: =VLOOKUP((UPPER(SUBSTITUTE(A30," ","_"))),'[2]Consumer View'!A$2:I$329,1,FALSE) -> OWNER_FA_NUMBER_ENTITY_ENTERPRISE_ID | Y30: SSDS_DAL_OWNER | Z30: ENTERPRISE_ENTITY_DIM_V | AA30: ENTITY_ENTERPRISE_ID | AD30: Derive based on OWN_FA_NUM_ENT_CD field. LEFT JOIN SSDS_DAL_OWNER.ENTERPRISE_ENTITY_DIM_V e ON e.Entity_code_long = OWN_FA_NUM_ENT_CD AND t.td >= e.EFF_DT AND t.td < e.END_DT AND e.ENTITY_RECYCLED_BOOLEAN='0' AND e.ENTITY_FINANCIAL_RIA_BOOLEAN = '0' | AE30: [6/5/24]: Updated data type from VARCHAR to NUMBER. PBI 1912566 [6/25/24]: As a part of PBI 1912566 ROWNUM logic to pick one record at the very last stage was implemented to avoid duplicates in Entity Dim. The logic is to be revised in the future to write an exception for dupes [9/11/24]: Reflected the change to use TXN.TD from Product Backlog Item 1912566: Change join condition and update data types for Activity | AH30: Y (PBI 1931139)
A31: ACAT Contra Firm Clearing Number | B31: ACAT_CNTRA_FIRM_CLRG_NUM | C31: ACAT_Contra_Firm_Clearing_Number | D31: VARCHAR2(4) | E31: Yes | F31: character varying(4) | G31: Yes | H31: This is the logical identifier for the entity/system (in this case ACAT) that is providing this transaction information or responsible for creation/maintenance of the information. In a case where the information is created and maintained. Identifier of the system from which CDS database receives/obtains the underlying record. This identifier is specifc to ACAT Contra Firm clearing | I31: 0352 | J31: Add | K31: 3 | O31: =VLOOKUP(A31,[1]Model!C$2:J$559,2,FALSE)=B31 -> TRUE | P31: =VLOOKUP(A31,Model!C$2:G$228,5,FALSE)=D31 -> TRUE | Q31: =VLOOKUP(A31,[2]Model!C$2:L$228,8,FALSE) -> 158 | R31: =VLOOKUP(A31,[2]Model!C$2:G$228,3,FALSE)=[3]!Table14[[#This Row],[Business Definition (To go into comments and into Meta Data Hub)]] -> #VALUE! | S31: =IF([3]!Table14[[#This Row],[Nullable in Table and in Oracle View NULL, NOT NULL]]="No","NOT NULL","NULL")=VLOOKUP(A31,[2]Model!C$2:I$228,6,FALSE) -> #REF! | T31: =VLOOKUP(B31,[2]Table!A$2:F$415,1,FALSE)=[3]!Table14[[#This Row],[Physical Name of Attribute (Name of column in Table) Supplied by DA Team]] -> #REF! | U31: =VLOOKUP(B31,Table!A$2:F$319,2,FALSE)=Table14[[#This Row],[Data type in Oracle VARCHAR2(n), DATE, NUMBER(m,n), TIMETSTAMP(6)]] -> FALSE | V31: =VLOOKUP(B31,Table!A$2:F$231,3,FALSE)=Table14[[#This Row],[Nullable in Table and in Oracle View NULL, NOT NULL]] -> TRUE | W31: =VLOOKUP(B31,Table!A$2:H$228,6,FALSE)=Table14[[#This Row],[Business Definition (To go into comments and into Meta Data Hub)]] -> FALSE | X31: =VLOOKUP((UPPER(SUBSTITUTE(A31," ","_"))),'[2]Consumer View'!A$2:I$329,1,FALSE) -> ACAT_CONTRA_FIRM_CLEARING_NUMBER | Y31: CCAL_REPL_OWNER | Z31: TXN | AA31: ORIG_SRC_STM_CODE | AD31: ccal_repl_owner.txn t where t.src_stm_id IN ( 53, 54 ) | AH31: N
A32: ACAT Contra Firm Name | B32: ACAT_CNTRA_FIRM_NM | C32: ACAT_Contra_Firm | D32: VARCHAR2(50) | E32: Yes | F32: character varying(50) | G32: Yes | H32: ACAT Contra Firm Clearing Name | I32: 0352 | J32: Add | K32: 3 | O32: =VLOOKUP(A32,[1]Model!C$2:J$559,2,FALSE)=B32 -> TRUE | P32: =VLOOKUP(A32,Model!C$2:G$228,5,FALSE)=D32 -> TRUE | Q32: =VLOOKUP(A32,[2]Model!C$2:L$228,8,FALSE) -> 159 | R32: =VLOOKUP(A32,[2]Model!C$2:G$228,3,FALSE)=[3]!Table14[[#This Row],[Business Definition (To go into comments and into Meta Data Hub)]] -> #REF! | S32: =IF([3]!Table14[[#This Row],[Nullable in Table and in Oracle View NULL, NOT NULL]]="No","NOT NULL","NULL")=VLOOKUP(A32,[2]Model!C$2:I$228,6,FALSE) -> #REF! | T32: =VLOOKUP(B32,[2]Table!A$2:F$415,1,FALSE)=[3]!Table14[[#This Row],[Physical Name of Attribute (Name of column in Table) Supplied by DA Team]] -> #REF! | U32: =VLOOKUP(B32,Table!A$2:F$319,2,FALSE)=Table14[[#This Row],[Data type in Oracle VARCHAR2(n), DATE, NUMBER(m,n), TIMETSTAMP(6)]] -> FALSE | V32: =VLOOKUP(B32,Table!A$2:F$231,3,FALSE)=Table14[[#This Row],[Nullable in Table and in Oracle View NULL, NOT NULL]] -> TRUE | W32: =VLOOKUP(B32,Table!A$2:H$228,6,FALSE)=Table14[[#This Row],[Business Definition (To go into comments and into Meta Data Hub)]] -> TRUE | X32: =VLOOKUP((UPPER(SUBSTITUTE(A32," ","_"))),'[2]Consumer View'!A$2:I$329,1,FALSE) -> ACAT_CONTRA_FIRM_NAME | Y32: CCAL_REPL_OWNER | Z32: ACATS_BROKER | AA32: BROKER_NAME | AD32: ccal_repl_owner.txn t LEFT join ccal_repl_owner.acats_broker ON b.broker_id = t.orig_src_stm_code and t.src_stm_id IN ( 53, 54 ) | AE32: Note to Dev team: ACATS_BROKER table is available in CDS DB but not available in SSDS/Lighthouse DB. [11/18/25] Corrected orig_src_stm_id with orig_src_stm_code in mapping | AH32: N
A33: ACAT Contra Firm Short Name | B33: ACAT_CNTRA_FIRM_SHRT_NM | D33: VARCHAR2(15) | E33: Yes | F33: character varying(15) | G33: Yes | H33: ACAT Contra Firm Clearing Short Name | I33: 0352 | J33: Add | K33: 3 | O33: =VLOOKUP(A33,[1]Model!C$2:J$559,2,FALSE)=B33 -> TRUE | P33: =VLOOKUP(A33,Model!C$2:G$228,5,FALSE)=D33 -> TRUE | Q33: =VLOOKUP(A33,[2]Model!C$2:L$228,8,FALSE) -> 160 | R33: =VLOOKUP(A33,[2]Model!C$2:G$228,3,FALSE)=[3]!Table14[[#This Row],[Business Definition (To go into comments and into Meta Data Hub)]] -> #REF! | S33: =IF([3]!Table14[[#This Row],[Nullable in Table and in Oracle View NULL, NOT NULL]]="No","NOT NULL","NULL")=VLOOKUP(A33,[2]Model!C$2:I$228,6,FALSE) -> #REF! | T33: =VLOOKUP(B33,[2]Table!A$2:F$415,1,FALSE)=[3]!Table14[[#This Row],[Physical Name of Attribute (Name of column in Table) Supplied by DA Team]] -> #REF! | U33: =VLOOKUP(B33,Table!A$2:F$319,2,FALSE)=Table14[[#This Row],[Data type in Oracle VARCHAR2(n), DATE, NUMBER(m,n), TIMETSTAMP(6)]] -> FALSE | V33: =VLOOKUP(B33,Table!A$2:F$231,3,FALSE)=Table14[[#This Row],[Nullable in Table and in Oracle View NULL, NOT NULL]] -> TRUE | W33: =VLOOKUP(B33,Table!A$2:H$228,6,FALSE)=Table14[[#This Row],[Business Definition (To go into comments and into Meta Data Hub)]] -> TRUE | X33: =VLOOKUP((UPPER(SUBSTITUTE(A33," ","_"))),'[2]Consumer View'!A$2:I$329,1,FALSE) -> ACAT_CONTRA_FIRM_SHORT_NAME | Y33: CCAL_REPL_OWNER | Z33: ACATS_BROKER | AA33: BROKER_SHORT_NAME | AD33: ccal_repl_owner.txn t LEFT join ccal_repl_owner.acats_broker ON b.broker_id = t.orig_src_stm_code and t.src_stm_id IN ( 53, 54 ) | AE33: Note to Dev team: ACATS_BROKER table is available in CDS DB but not available in SSDS/Lighthouse DB. | AH33: N
A34: ACAT Contra Firm Clearing ID Type Code | B34: ACAT_CNTRA_FIRM_CLRG_ID_TP_CD | D34: VARCHAR2(1) | E34: Yes | F34: character varying(1) | G34: Yes | H34: ACAT Broker ID Type | I34: 2 | J34: Add | K34: 3 | O34: =VLOOKUP(A34,[1]Model!C$2:J$559,2,FALSE)=B34 -> TRUE | P34: =VLOOKUP(A34,Model!C$2:G$228,5,FALSE)=D34 -> TRUE | Q34: =VLOOKUP(A34,[2]Model!C$2:L$228,8,FALSE) -> 161 | R34: =VLOOKUP(A34,[2]Model!C$2:G$228,3,FALSE)=[3]!Table14[[#This Row],[Business Definition (To go into comments and into Meta Data Hub)]] -> #REF! | S34: =IF([3]!Table14[[#This Row],[Nullable in Table and in Oracle View NULL, NOT NULL]]="No","NOT NULL","NULL")=VLOOKUP(A34,[2]Model!C$2:I$228,6,FALSE) -> #REF! | T34: =VLOOKUP(B34,[2]Table!A$2:F$415,1,FALSE)=[3]!Table14[[#This Row],[Physical Name of Attribute (Name of column in Table) Supplied by DA Team]] -> #REF! | U34: =VLOOKUP(B34,Table!A$2:F$319,2,FALSE)=Table14[[#This Row],[Data type in Oracle VARCHAR2(n), DATE, NUMBER(m,n), TIMETSTAMP(6)]] -> FALSE | V34: =VLOOKUP(B34,Table!A$2:F$231,3,FALSE)=Table14[[#This Row],[Nullable in Table and in Oracle View NULL, NOT NULL]] -> TRUE | W34: =VLOOKUP(B34,Table!A$2:H$228,6,FALSE)=Table14[[#This Row],[Business Definition (To go into comments and into Meta Data Hub)]] -> TRUE | X34: =VLOOKUP((UPPER(SUBSTITUTE(A34," ","_"))),'[2]Consumer View'!A$2:I$329,1,FALSE) -> ACAT_CONTRA_FIRM_CLEARING_ID_TYPE_CODE | Y34: CCAL_REPL_OWNER | Z34: ACATS_BROKER | AA34: BROKER_ID_TYPE | AD34: ccal_repl_owner.txn t LEFT join ccal_repl_owner.acats_broker b ON b.broker_id = t.orig_src_stm_code and t.src_stm_id IN ( 53, 54 ) | AE34: Note to Dev team: ACATS_BROKER table is available in CDS DB but not available in SSDS/Lighthouse DB. | AH34: N
A35: Money Movement Alternate Id | B35: MM_ALT_ID | C35: Money_Movement_Alternate_Id | D35: VARCHAR2(50) | E35: Yes | F35: character varying(50) | G35: Yes | H35: Identifier on all Money movement transactions | I35: MM1423054 | J35: Add | K35: 3 | O35: =VLOOKUP(A35,[1]Model!C$2:J$559,2,FALSE)=B35 -> TRUE | P35: =VLOOKUP(A35,Model!C$2:G$228,5,FALSE)=D35 -> TRUE | Q35: =VLOOKUP(A35,[2]Model!C$2:L$228,8,FALSE) -> 162 | R35: =VLOOKUP(A35,[2]Model!C$2:G$228,3,FALSE)=[3]!Table14[[#This Row],[Business Definition (To go into comments and into Meta Data Hub)]] -> #REF! | S35: =IF([3]!Table14[[#This Row],[Nullable in Table and in Oracle View NULL, NOT NULL]]="No","NOT NULL","NULL")=VLOOKUP(A35,[2]Model!C$2:I$228,6,FALSE) -> #REF! | T35: =VLOOKUP(B35,[2]Table!A$2:F$415,1,FALSE)=[3]!Table14[[#This Row],[Physical Name of Attribute (Name of column in Table) Supplied by DA Team]] -> #REF! | U35: =VLOOKUP(B35,Table!A$2:F$319,2,FALSE)=Table14[[#This Row],[Data type in Oracle VARCHAR2(n), DATE, NUMBER(m,n), TIMETSTAMP(6)]] -> FALSE | V35: =VLOOKUP(B35,Table!A$2:F$231,3,FALSE)=Table14[[#This Row],[Nullable in Table and in Oracle View NULL, NOT NULL]] -> TRUE | W35: =VLOOKUP(B35,Table!A$2:H$228,6,FALSE)=Table14[[#This Row],[Business Definition (To go into comments and into Meta Data Hub)]] -> TRUE | X35: =VLOOKUP((UPPER(SUBSTITUTE(A35," ","_"))),'[2]Consumer View'!A$2:I$329,1,FALSE) -> MONEY_MOVEMENT_ALTERNATE_ID | Y35: CCAL_REPL_OWNER | Z35: TXN | AA35: ORIG_SRC_STM_CODE | AD35: ccal_repl_owner.txn t where t.src_stm_id= '60' and t.ORIG_SRC_STM_CODE like 'MM%' and t.SRC_CRT_USRNM = 'BPMWRAPB'; | AH35: N
A36: Arrangement Originating Source System Code | B36: AR_ORIG_SRC_STM_CD | C36: Arrangement_Originating_Source_System_Provider_Code | D36: VARCHAR2(20) | E36: Yes | F36: character varying(20) | G36: Yes | H36: Code that represents the source system from which CDS database receives/obtains the underlying Arrangement from. | I36: ZTNB.#B066 | J36: Add | K36: 3 | O36: =VLOOKUP(A36,[1]Model!C$2:J$559,2,FALSE)=B36 -> TRUE | P36: =VLOOKUP(A36,Model!C$2:G$228,5,FALSE)=D36 -> TRUE | Q36: =VLOOKUP(A36,[2]Model!C$2:L$228,8,FALSE) -> 185 | R36: =VLOOKUP(A36,[2]Model!C$2:G$228,3,FALSE)=[3]!Table14[[#This Row],[Business Definition (To go into comments and into Meta Data Hub)]] -> #REF! | S36: =IF([3]!Table14[[#This Row],[Nullable in Table and in Oracle View NULL, NOT NULL]]="No","NOT NULL","NULL")=VLOOKUP(A36,[2]Model!C$2:I$228,6,FALSE) -> #REF! | T36: =VLOOKUP(B36,[2]Table!A$2:F$415,1,FALSE)=[3]!Table14[[#This Row],[Physical Name of Attribute (Name of column in Table) Supplied by DA Team]] -> #REF! | U36: =VLOOKUP(B36,Table!A$2:F$319,2,FALSE)=Table14[[#This Row],[Data type in Oracle VARCHAR2(n), DATE, NUMBER(m,n), TIMETSTAMP(6)]] -> FALSE | V36: =VLOOKUP(B36,Table!A$2:F$231,3,FALSE)=Table14[[#This Row],[Nullable in Table and in Oracle View NULL, NOT NULL]] -> TRUE | W36: =VLOOKUP(B36,Table!A$2:H$228,6,FALSE)=Table14[[#This Row],[Business Definition (To go into comments and into Meta Data Hub)]] -> TRUE | X36: =VLOOKUP((UPPER(SUBSTITUTE(A36," ","_"))),'[2]Consumer View'!A$2:I$329,1,FALSE) -> ARRANGEMENT_ORIGINATING_SOURCE_SYSTEM_CODE | Y36: CCSI_OWNER | Z36: AR_DIM | AA36: ORIG_SRC_STM_CD | AD36: ccal_repl_owner.txn t join ccsi_owner.ar_dim ard ON ard.AR_ID = t.AR_ID and ard.eff_dt <= t.td and ard.end_dt > t.td | AE36: [9/6/24]: Reflected the change to use TXN.TD from Product Backlog Item 1912566: Change join condition and update data types for Activity. [9/17/24]: Changing to use TXN.AR_ID per Product Backlog Item 1998220: Fix Activity issues for Historical Load | AH36: Y
A37: Source System Id | B37: SRC_STM_ID | D37: NUMBER(38,0) | E37: Yes | F37: NUMERIC(38,0) | G37: Yes | H37: Source system Id coming from Transaction. This could be different from Source system Id coming from Arrangement information. | I37: 3 | J37: Add | K37: 3 | O37: =VLOOKUP(A37,[1]Model!C$2:J$559,2,FALSE)=B37 -> TRUE | P37: =VLOOKUP(A37,Model!C$2:G$228,5,FALSE)=D37 -> #N/A | Q37: =VLOOKUP(A37,[2]Model!C$2:L$228,8,FALSE) -> 163 | R37: =VLOOKUP(A37,[2]Model!C$2:G$228,3,FALSE)=[3]!Table14[[#This Row],[Business Definition (To go into comments and into Meta Data Hub)]] -> #REF! | S37: =IF([3]!Table14[[#This Row],[Nullable in Table and in Oracle View NULL, NOT NULL]]="No","NOT NULL","NULL")=VLOOKUP(A37,[2]Model!C$2:I$228,6,FALSE) -> #REF! | T37: =VLOOKUP(B37,[2]Table!A$2:F$415,1,FALSE)=[3]!Table14[[#This Row],[Physical Name of Attribute (Name of column in Table) Supplied by DA Team]] -> #REF! | U37: =VLOOKUP(B37,Table!A$2:F$319,2,FALSE)=Table14[[#This Row],[Data type in Oracle VARCHAR2(n), DATE, NUMBER(m,n), TIMETSTAMP(6)]] -> TRUE | V37: =VLOOKUP(B37,Table!A$2:F$231,3,FALSE)=Table14[[#This Row],[Nullable in Table and in Oracle View NULL, NOT NULL]] -> TRUE | W37: =VLOOKUP(B37,Table!A$2:H$228,6,FALSE)=Table14[[#This Row],[Business Definition (To go into comments and into Meta Data Hub)]] -> TRUE | X37: =VLOOKUP((UPPER(SUBSTITUTE(A37," ","_"))),'[2]Consumer View'!A$2:I$329,1,FALSE) -> SOURCE_SYSTEM_ID | Y37: CCAL_REPL_OWNER | Z37: TXN | AA37: SRC_STM_ID | AH37: N
A38: Source System Name | B38: SRC_STM_NM | C38: Source_System | D38: VARCHAR2(60) | E38: Yes | F38: character varying(60) | G38: Yes | H38: Name of the source system information coming from Transaction. e.g., SIS - Securities Industry Software, Raymond James, Raymond James Bank, Shadow Suite | I38: Broadridge Financial Solution IMPACT Back Office System | J38: Add | K38: 3 | O38: =VLOOKUP(A38,[1]Model!C$2:J$559,2,FALSE)=B38 -> TRUE | P38: =VLOOKUP(A38,Model!C$2:G$228,5,FALSE)=D38 -> #N/A | Q38: =VLOOKUP(A38,[2]Model!C$2:L$228,8,FALSE) -> 165 | R38: =VLOOKUP(A38,[2]Model!C$2:G$228,3,FALSE)=[3]!Table14[[#This Row],[Business Definition (To go into comments and into Meta Data Hub)]] -> #REF! | S38: =IF([3]!Table14[[#This Row],[Nullable in Table and in Oracle View NULL, NOT NULL]]="No","NOT NULL","NULL")=VLOOKUP(A38,[2]Model!C$2:I$228,6,FALSE) -> #REF! | T38: =VLOOKUP(B38,[2]Table!A$2:F$415,1,FALSE)=[3]!Table14[[#This Row],[Physical Name of Attribute (Name of column in Table) Supplied by DA Team]] -> #REF! | U38: =VLOOKUP(B38,Table!A$2:F$319,2,FALSE)=Table14[[#This Row],[Data type in Oracle VARCHAR2(n), DATE, NUMBER(m,n), TIMETSTAMP(6)]] -> FALSE | V38: =VLOOKUP(B38,Table!A$2:F$231,3,FALSE)=Table14[[#This Row],[Nullable in Table and in Oracle View NULL, NOT NULL]] -> TRUE | W38: =VLOOKUP(B38,Table!A$2:H$228,6,FALSE)=Table14[[#This Row],[Business Definition (To go into comments and into Meta Data Hub)]] -> TRUE | X38: =VLOOKUP((UPPER(SUBSTITUTE(A38," ","_"))),'[2]Consumer View'!A$2:I$329,1,FALSE) -> SOURCE_SYSTEM_NAME | Y38: COMMON_OWNER | Z38: SRC_STM_DIM | AA38: SRC_STM_NM | AD38: ccal_repl_owner.txn t left JOIN common_owner.src_stm_dim ss on t.src_stm_id = ss.src_stm_id | AH38: N
A39: Source Cancel / Revision Code | B39: SRC_CNCL_X_RVSN_CD | C39: Source_Cancel_or_Revision_Code | D39: VARCHAR2(3) | E39: Yes | F39: character varying(3) | G39: Yes | H39: Cancel or Revise Code in the source system | I39: CAN - Transaction has been canceled before verification or approval. CXL - Transaction has been revised or canceled after verification. CXR - Transaction is a rebill of a previous transaction and that the rebill has been revised or canceled. OFF - Transaction is an offset of a transaction that has been revised or canceled. OFR - Transaction is an offset of a rebill that has been revised or canceled. RBL - Transaction is a rebill of a transaction that has been revised. RTN - Indicates a piece of collateral has been returned during the term of a deal. IMP - Transaction is an offset of a rebill that has a factor adjustment | J39: Add | K39: 3 | O39: =VLOOKUP(A39,[1]Model!C$2:J$559,2,FALSE)=B39 -> TRUE | P39: =VLOOKUP(A39,Model!C$2:G$228,5,FALSE)=D39 -> #N/A | Q39: =VLOOKUP(A39,[2]Model!C$2:L$228,8,FALSE) -> 166 | R39: =VLOOKUP(A39,[2]Model!C$2:G$228,3,FALSE)=[3]!Table14[[#This Row],[Business Definition (To go into comments and into Meta Data Hub)]] -> #REF! | S39: =IF([3]!Table14[[#This Row],[Nullable in Table and in Oracle View NULL, NOT NULL]]="No","NOT NULL","NULL")=VLOOKUP(A39,[2]Model!C$2:I$228,6,FALSE) -> #REF! | T39: =VLOOKUP(B39,[2]Table!A$2:F$415,1,FALSE)=[3]!Table14[[#This Row],[Physical Name of Attribute (Name of column in Table) Supplied by DA Team]] -> #REF! | U39: =VLOOKUP(B39,Table!A$2:F$319,2,FALSE)=Table14[[#This Row],[Data type in Oracle VARCHAR2(n), DATE, NUMBER(m,n), TIMETSTAMP(6)]] -> FALSE | V39: =VLOOKUP(B39,Table!A$2:F$231,3,FALSE)=Table14[[#This Row],[Nullable in Table and in Oracle View NULL, NOT NULL]] -> TRUE | W39: =VLOOKUP(B39,Table!A$2:H$228,6,FALSE)=Table14[[#This Row],[Business Definition (To go into comments and into Meta Data Hub)]] -> TRUE | X39: =VLOOKUP((UPPER(SUBSTITUTE(A39," ","_"))),'[2]Consumer View'!A$2:I$329,1,FALSE) -> #N/A | Y39: CCAL_REPL_OWNER | Z39: TXN | AA39: SRC_CXL_REV | AE39: [6/3/24]: Modified data type for Redshift from 255 to 3 | AH39: N
A40: Source Option Class Code | B40: SRC_OPT_CLSS_CD | C40: Source_Option_Class_Code | D40: VARCHAR2(50) | E40: Yes | F40: character varying(50) | G40: Yes | H40: The code that determines what type of transaction the record contains. For SIS activity the values depend on the record type. | I40: M W C B I H L F P Y R A G J 2 X D T | J40: Add | K40: 3 | O40: =VLOOKUP(A40,[1]Model!C$2:J$559,2,FALSE)=B40 -> TRUE | P40: =VLOOKUP(A40,Model!C$2:G$228,5,FALSE)=D40 -> #N/A | Q40: =VLOOKUP(A40,[2]Model!C$2:L$228,8,FALSE) -> 167 | R40: =VLOOKUP(A40,[2]Model!C$2:G$228,3,FALSE)=[3]!Table14[[#This Row],[Business Definition (To go into comments and into Meta Data Hub)]] -> #REF! | S40: =IF([3]!Table14[[#This Row],[Nullable in Table and in Oracle View NULL, NOT NULL]]="No","NOT NULL","NULL")=VLOOKUP(A40,[2]Model!C$2:I$228,6,FALSE) -> #REF! | T40: =VLOOKUP(B40,[2]Table!A$2:F$415,1,FALSE)=[3]!Table14[[#This Row],[Physical Name of Attribute (Name of column in Table) Supplied by DA Team]] -> #REF! | U40: =VLOOKUP(B40,Table!A$2:F$319,2,FALSE)=Table14[[#This Row],[Data type in Oracle VARCHAR2(n), DATE, NUMBER(m,n), TIMETSTAMP(6)]] -> FALSE | V40: =VLOOKUP(B40,Table!A$2:F$231,3,FALSE)=Table14[[#This Row],[Nullable in Table and in Oracle View NULL, NOT NULL]] -> TRUE | W40: =VLOOKUP(B40,Table!A$2:H$228,6,FALSE)=Table14[[#This Row],[Business Definition (To go into comments and into Meta Data Hub)]] -> TRUE | X40: =VLOOKUP((UPPER(SUBSTITUTE(A40," ","_"))),'[2]Consumer View'!A$2:I$329,1,FALSE) -> SOURCE_OPTION_CLASS_CODE | Y40: CCAL_REPL_OWNER | Z40: TXN | AA40: SRC_OPT_CLS | AH40: N
A41: Transaction Reconciliation Replay Count | B41: TXN_RCNCL_REPL_CNT | D41: NUMBER(38,0) | E41: Yes | F41: NUMERIC(38,0) | G41: Yes | H41: Numeric counter to show how many attempts were done to reconcile transactions on this account/product/type with the corresponding EOD positions. The default value load is '0' and counter is incremented by '1' as transaction is replayed. | I41: 3 | J41: Add | K41: 3 | O41: =VLOOKUP(A41,[1]Model!C$2:J$559,2,FALSE)=B41 -> TRUE | P41: =VLOOKUP(A41,Model!C$2:G$228,5,FALSE)=D41 -> #N/A | Q41: =VLOOKUP(A41,[2]Model!C$2:L$228,8,FALSE) -> 168 | R41: =VLOOKUP(A41,[2]Model!C$2:G$228,3,FALSE)=[3]!Table14[[#This Row],[Business Definition (To go into comments and into Meta Data Hub)]] -> #REF! | S41: =IF([3]!Table14[[#This Row],[Nullable in Table and in Oracle View NULL, NOT NULL]]="No","NOT NULL","NULL")=VLOOKUP(A41,[2]Model!C$2:I$228,6,FALSE) -> #REF! | T41: =VLOOKUP(B41,[2]Table!A$2:F$415,1,FALSE)=[3]!Table14[[#This Row],[Physical Name of Attribute (Name of column in Table) Supplied by DA Team]] -> #REF! | U41: =VLOOKUP(B41,Table!A$2:F$319,2,FALSE)=Table14[[#This Row],[Data type in Oracle VARCHAR2(n), DATE, NUMBER(m,n), TIMETSTAMP(6)]] -> TRUE | V41: =VLOOKUP(B41,Table!A$2:F$231,3,FALSE)=Table14[[#This Row],[Nullable in Table and in Oracle View NULL, NOT NULL]] -> TRUE | W41: =VLOOKUP(B41,Table!A$2:H$228,6,FALSE)=Table14[[#This Row],[Business Definition (To go into comments and into Meta Data Hub)]] -> FALSE | X41: =VLOOKUP((UPPER(SUBSTITUTE(A41," ","_"))),'[2]Consumer View'!A$2:I$329,1,FALSE) -> #N/A | Y41: CCAL_REPL_OWNER | Z41: TXN | AA41: TXN_REPL_CNT | AE41: [7/15/24]: Do not add to the view. Product Backlog Item 1948982: Update columns in Activity Fact and Activity Detail Fact | AH41: N
A42: Transaction Reconciliation Status Id | B42: TXN_RCNCL_ST_ID | D42: NUMBER(38,0) | E42: Yes | F42: NUMERIC(38,0) | G42: Yes | H42: Processing state of a transaction according to specified state transition rules. Ties specifically to reconciliation process a reconciled transaction would indicate for example COM or complete and a transaction that failed reconciliation would indicate FRC code which would be written to Operations Analyst Tool for further investigation. This specifies the status identifier | I42: 1029 | J42: Add | K42: 3 | O42: =VLOOKUP(A42,[1]Model!C$2:J$559,2,FALSE)=B42 -> TRUE | P42: =VLOOKUP(A42,Model!C$2:G$228,5,FALSE)=D42 -> #N/A | Q42: =VLOOKUP(A42,[2]Model!C$2:L$228,8,FALSE) -> 171 | R42: =VLOOKUP(A42,[2]Model!C$2:G$228,3,FALSE)=[3]!Table14[[#This Row],[Business Definition (To go into comments and into Meta Data Hub)]] -> #VALUE! | S42: =IF([3]!Table14[[#This Row],[Nullable in Table and in Oracle View NULL, NOT NULL]]="No","NOT NULL","NULL")=VLOOKUP(A42,[2]Model!C$2:I$228,6,FALSE) -> #REF! | T42: =VLOOKUP(B42,[2]Table!A$2:F$415,1,FALSE)=[3]!Table14[[#This Row],[Physical Name of Attribute (Name of column in Table) Supplied by DA Team]] -> #REF! | U42: =VLOOKUP(B42,Table!A$2:F$319,2,FALSE)=Table14[[#This Row],[Data type in Oracle VARCHAR2(n), DATE, NUMBER(m,n), TIMETSTAMP(6)]] -> TRUE | V42: =VLOOKUP(B42,Table!A$2:F$231,3,FALSE)=Table14[[#This Row],[Nullable in Table and in Oracle View NULL, NOT NULL]] -> TRUE | W42: =VLOOKUP(B42,Table!A$2:H$228,6,FALSE)=Table14[[#This Row],[Business Definition (To go into comments and into Meta Data Hub)]] -> TRUE | X42: =VLOOKUP((UPPER(SUBSTITUTE(A42," ","_"))),'[2]Consumer View'!A$2:I$329,1,FALSE) -> #N/A | Y42: CCAL_REPL_OWNER | Z42: TXN | AA42: TXN_ST_ID | AE42: [7/15/24]: Do not add to the view. Product Backlog Item 1948982: Update columns in Activity Fact and Activity Detail Fact | AH42: N
A43: Transaction Reconciliation Status Code | B43: TXN_RCNCL_ST_CD | D43: VARCHAR2(20) | E43: Yes | F43: character varying(20) | G43: Yes | H43: Processing state of a transaction according to specified state transition rules. Ties specifically to reconciliation process a reconciled transaction would indicate for example COM or complete and a transaction that failed reconciliation would indicate FRC code which would be written to Operations Analyst Tool for further investigation. This specifies the status code | I43: PNR | J43: Add | K43: 3 | O43: =VLOOKUP(A43,[1]Model!C$2:J$559,2,FALSE)=B43 -> TRUE | P43: =VLOOKUP(A43,Model!C$2:G$228,5,FALSE)=D43 -> #N/A | Q43: =VLOOKUP(A43,[2]Model!C$2:L$228,8,FALSE) -> 172 | R43: =VLOOKUP(A43,[2]Model!C$2:G$228,3,FALSE)=[3]!Table14[[#This Row],[Business Definition (To go into comments and into Meta Data Hub)]] -> #VALUE! | S43: =IF([3]!Table14[[#This Row],[Nullable in Table and in Oracle View NULL, NOT NULL]]="No","NOT NULL","NULL")=VLOOKUP(A43,[2]Model!C$2:I$228,6,FALSE) -> #REF! | T43: =VLOOKUP(B43,[2]Table!A$2:F$415,1,FALSE)=[3]!Table14[[#This Row],[Physical Name of Attribute (Name of column in Table) Supplied by DA Team]] -> #REF! | U43: =VLOOKUP(B43,Table!A$2:F$319,2,FALSE)=Table14[[#This Row],[Data type in Oracle VARCHAR2(n), DATE, NUMBER(m,n), TIMETSTAMP(6)]] -> FALSE | V43: =VLOOKUP(B43,Table!A$2:F$231,3,FALSE)=Table14[[#This Row],[Nullable in Table and in Oracle View NULL, NOT NULL]] -> TRUE | W43: =VLOOKUP(B43,Table!A$2:H$228,6,FALSE)=Table14[[#This Row],[Business Definition (To go into comments and into Meta Data Hub)]] -> TRUE | X43: =VLOOKUP((UPPER(SUBSTITUTE(A43," ","_"))),'[2]Consumer View'!A$2:I$329,1,FALSE) -> #N/A | Y43: CCAL_REPL_OWNER | Z43: CL_VAL | AA43: CL_VAL_CODE | AD43: ccal_repl_owner.txn t left join ccal_repl_owner.cl_val cv ON cv.cl_val_id = t.txn_st_id and cv.CL_SCM_ID = 12 | AE43: [7/15/24]: Do not add to the view. Product Backlog Item 1948982: Update columns in Activity Fact and Activity Detail Fact | AH43: N (REMOVE)
A44: Transaction Reconciliation Status Name | B44: TXN_RCNCL_ST_NM | D44: VARCHAR2(200) | E44: Yes | F44: character varying(200) | G44: Yes | H44: Processing state of a transaction according to specified state transition rules. Ties specifically to reconciliation process a reconciled transaction would indicate for example COM or complete and a transaction that failed reconciliation would indicate FRC code which would be written to Operations Analyst Tool for further investigation.This specifies the status name | I44: Pending Reconciliation | J44: Add | K44: 3 | O44: =VLOOKUP(A44,[1]Model!C$2:J$559,2,FALSE)=B44 -> TRUE | P44: =VLOOKUP(A44,Model!C$2:G$228,5,FALSE)=D44 -> #N/A | Q44: =VLOOKUP(A44,[2]Model!C$2:L$228,8,FALSE) -> 173 | R44: =VLOOKUP(A44,[2]Model!C$2:G$228,3,FALSE)=[3]!Table14[[#This Row],[Business Definition (To go into comments and into Meta Data Hub)]] -> #VALUE! | S44: =IF([3]!Table14[[#This Row],[Nullable in Table and in Oracle View NULL, NOT NULL]]="No","NOT NULL","NULL")=VLOOKUP(A44,[2]Model!C$2:I$228,6,FALSE) -> #REF! | T44: =VLOOKUP(B44,[2]Table!A$2:F$415,1,FALSE)=[3]!Table14[[#This Row],[Physical Name of Attribute (Name of column in Table) Supplied by DA Team]] -> #REF! | U44: =VLOOKUP(B44,Table!A$2:F$319,2,FALSE)=Table14[[#This Row],[Data type in Oracle VARCHAR2(n), DATE, NUMBER(m,n), TIMETSTAMP(6)]] -> FALSE | V44: =VLOOKUP(B44,Table!A$2:F$231,3,FALSE)=Table14[[#This Row],[Nullable in Table and in Oracle View NULL, NOT NULL]] -> TRUE | W44: =VLOOKUP(B44,Table!A$2:H$228,6,FALSE)=Table14[[#This Row],[Business Definition (To go into comments and into Meta Data Hub)]] -> TRUE | X44: =VLOOKUP((UPPER(SUBSTITUTE(A44," ","_"))),'[2]Consumer View'!A$2:I$329,1,FALSE) -> #N/A | Y44: CCAL_REPL_OWNER | Z44: CL_VAL | AA44: CL_VAL_NM | AD44: ccal_repl_owner.txn t left join ccal_repl_owner.cl_val cv ON cv.cl_val_id = t.txn_st_id and cv.CL_SCM_ID = 12 | AE44: [7/15/24]: Do not add to the view. Product Backlog Item 1948982: Update columns in Activity Fact and Activity Detail Fact | AH44: N (REMOVE)
A45: MF Account Number | B45: MF_AC_NUM | C45: External_Account_Number | D45: VARCHAR2(30) | E45: Yes | F45: character varying(30) | G45: Yes | H45: Account number of the mutual fund, if the transaction is on mutual fund. | J45: Add | K45: 3 | O45: =VLOOKUP(A45,[1]Model!C$2:J$559,2,FALSE)=B45 -> TRUE | P45: =VLOOKUP(A45,Model!C$2:G$228,5,FALSE)=D45 -> TRUE | Q45: =VLOOKUP(A45,[2]Model!C$2:L$228,8,FALSE) -> 195 | R45: =VLOOKUP(A45,[2]Model!C$2:G$228,3,FALSE)=[3]!Table14[[#This Row],[Business Definition (To go into comments and into Meta Data Hub)]] -> #REF! | S45: =IF([3]!Table14[[#This Row],[Nullable in Table and in Oracle View NULL, NOT NULL]]="No","NOT NULL","NULL")=VLOOKUP(A45,[2]Model!C$2:I$228,6,FALSE) -> #REF! | T45: =VLOOKUP(B45,[2]Table!A$2:F$415,1,FALSE)=[3]!Table14[[#This Row],[Physical Name of Attribute (Name of column in Table) Supplied by DA Team]] -> #REF! | U45: =VLOOKUP(B45,Table!A$2:F$319,2,FALSE)=Table14[[#This Row],[Data type in Oracle VARCHAR2(n), DATE, NUMBER(m,n), TIMETSTAMP(6)]] -> FALSE | V45: =VLOOKUP(B45,Table!A$2:F$231,3,FALSE)=Table14[[#This Row],[Nullable in Table and in Oracle View NULL, NOT NULL]] -> TRUE | W45: =VLOOKUP(B45,Table!A$2:H$228,6,FALSE)=Table14[[#This Row],[Business Definition (To go into comments and into Meta Data Hub)]] -> TRUE | X45: =VLOOKUP((UPPER(SUBSTITUTE(A45," ","_"))),'[2]Consumer View'!A$2:I$329,1,FALSE) -> MF_ACCOUNT_NUMBER | Y45: CCSI_OWNER | Z45: AR_DIM | AA45: MF_DRC_EXT_AC_NUM | AD45: ccal_repl_owner.txn t LEFT join ccsi_owner.ar_dim ard ON ard.AR_ID = t.AR_ID and ard.eff_dt <= t.td and ard.end_dt > t.td | AE45: [9/6/24]: Reflected the change to use TXN.TD from Product Backlog Item 1912566: Change join condition and update data types for Activity. [9/17/24]: Changing to use TXN.AR_ID per Product Backlog Item 1998220: Fix Activity issues for Historical Load | AH45: Y
A46: Offset Originating Source System Arrangement Id | B46: OFST_ORIG_SRC_STM_AR_ID | C46: Offset_Business_assigned_Arrangement_Id | D46: VARCHAR2(50) | E46: Yes | F46: character varying(50) | G46: Yes | H46: If the transaction was between 2 RJ accounts then this field will contain information about the second arrangement called the offset arrangement. This column contains the account number/contract number of the offset Arrangement from the original source system provider - e.g., SIS Account number for brokerage accounts | J46: Add | K46: 3 | O46: =VLOOKUP(A46,[1]Model!C$2:J$559,2,FALSE)=B46 -> TRUE | P46: =VLOOKUP(A46,Model!C$2:G$228,5,FALSE)=D46 -> TRUE | Q46: =VLOOKUP(A46,[2]Model!C$2:L$228,8,FALSE) -> 186 | R46: =VLOOKUP(A46,[2]Model!C$2:G$228,3,FALSE)=[3]!Table14[[#This Row],[Business Definition (To go into comments and into Meta Data Hub)]] -> #VALUE! | S46: =IF([3]!Table14[[#This Row],[Nullable in Table and in Oracle View NULL, NOT NULL]]="No","NOT NULL","NULL")=VLOOKUP(A46,[2]Model!C$2:I$228,6,FALSE) -> #REF! | T46: =VLOOKUP(B46,[2]Table!A$2:F$415,1,FALSE)=[3]!Table14[[#This Row],[Physical Name of Attribute (Name of column in Table) Supplied by DA Team]] -> #REF! | U46: =VLOOKUP(B46,Table!A$2:F$319,2,FALSE)=Table14[[#This Row],[Data type in Oracle VARCHAR2(n), DATE, NUMBER(m,n), TIMETSTAMP(6)]] -> FALSE | V46: =VLOOKUP(B46,Table!A$2:F$231,3,FALSE)=Table14[[#This Row],[Nullable in Table and in Oracle View NULL, NOT NULL]] -> TRUE | W46: =VLOOKUP(B46,Table!A$2:H$228,6,FALSE)=Table14[[#This Row],[Business Definition (To go into comments and into Meta Data Hub)]] -> TRUE | X46: =VLOOKUP((UPPER(SUBSTITUTE(A46," ","_"))),'[2]Consumer View'!A$2:I$329,1,FALSE) -> OFFSET_ORIGINATING_SOURCE_SYSTEM_ARRANGEMENT_ID | Y46: CCSI_OWNER | Z46: AR_DIM | AA46: ORIG_SRC_STM_AR_ID | AD46: ccal_repl_owner.txn t join ccal_repl_owner.apa ap ON ap.exec_id = t.txn_id left join ccsi_owner.ar_dim ad ON AP.OFST_AR_ID = ad.AR_ID and t.td >= ad.EFF_DT and t.td < ad.END_DT | AE46: [9/6/24]: Reflected the change to use TXN.TD from Product Backlog Item 1912566: Change join condition and update data types for Activity | AH46: Y
A47: Offset Arrangement Originating Source System Code | B47: OFST_AR_ORIG_SRC_STM_CD | C47: Offset_Arrangement_Originating_Source_System_Provider_Code | D47: VARCHAR2(20) | E47: Yes | F47: character varying(20) | G47: Yes | H47: If the transaction was between 2 RJ accounts then this field will contain information about the second arrangement called the offset arrangement. This column defines the source system associated with a specific offset arrangement. (e.g., BKRB01, RJB RESI, RJB LOANIQ) | J47: Add | K47: 3 | O47: =VLOOKUP(A47,[1]Model!C$2:J$559,2,FALSE)=B47 -> TRUE | P47: =VLOOKUP(A47,Model!C$2:G$228,5,FALSE)=D47 -> TRUE | Q47: =VLOOKUP(A47,[2]Model!C$2:L$228,8,FALSE) -> 187 | R47: =VLOOKUP(A47,[2]Model!C$2:G$228,3,FALSE)=[3]!Table14[[#This Row],[Business Definition (To go into comments and into Meta Data Hub)]] -> #VALUE! | S47: =IF([3]!Table14[[#This Row],[Nullable in Table and in Oracle View NULL, NOT NULL]]="No","NOT NULL","NULL")=VLOOKUP(A47,[2]Model!C$2:I$228,6,FALSE) -> #REF! | T47: =VLOOKUP(B47,[2]Table!A$2:F$415,1,FALSE)=[3]!Table14[[#This Row],[Physical Name of Attribute (Name of column in Table) Supplied by DA Team]] -> #REF! | U47: =VLOOKUP(B47,Table!A$2:F$319,2,FALSE)=Table14[[#This Row],[Data type in Oracle VARCHAR2(n), DATE, NUMBER(m,n), TIMETSTAMP(6)]] -> FALSE | V47: =VLOOKUP(B47,Table!A$2:F$231,3,FALSE)=Table14[[#This Row],[Nullable in Table and in Oracle View NULL, NOT NULL]] -> TRUE | W47: =VLOOKUP(B47,Table!A$2:H$228,6,FALSE)=Table14[[#This Row],[Business Definition (To go into comments and into Meta Data Hub)]] -> TRUE | X47: =VLOOKUP((UPPER(SUBSTITUTE(A47," ","_"))),'[2]Consumer View'!A$2:I$329,1,FALSE) -> OFFSET_ARRANGEMENT_ORIGINATING_SOURCE_SYSTEM_CODE | Y47: CCSI_OWNER | Z47: AR_DIM | AA47: ORIG_SRC_STM_CD | AD47: ccal_repl_owner.txn t join ccal_repl_owner.apa ap ON ap.exec_id = t.txn_id left join ccsi_owner.ar_dim ad ON AP.OFST_AR_ID = ad.AR_ID and t.td >= ad.EFF_DT and t.td < ad.END_DT | AE47: [9/6/24]: Reflected the change to use TXN.TD from Product Backlog Item 1912566: Change join condition and update data types for Activity | AH47: Y
A48: Offset Arrangement Settlement Type Code | B48: OFST_AR_SETL_TP_CD | C48: Offset_arrangement_settlement_type_code | D48: VARCHAR2(20) | E48: Yes | F48: character varying(20) | G48: Yes | H48: If the APA was satisfied by offsetting with another RJ arrangement then, this column will contain information about the offsetted arrangement. A code that identifies how an arrangement settles its security transactions. This settlement type code is applicable for offset arrangements. | J48: Add | K48: 3 | O48: =VLOOKUP(A48,[1]Model!C$2:J$559,2,FALSE)=B48 -> TRUE | P48: =VLOOKUP(A48,Model!C$2:G$228,5,FALSE)=D48 -> TRUE | Q48: =VLOOKUP(A48,[2]Model!C$2:L$228,8,FALSE) -> 188 | R48: =VLOOKUP(A48,[2]Model!C$2:G$228,3,FALSE)=[3]!Table14[[#This Row],[Business Definition (To go into comments and into Meta Data Hub)]] -> #VALUE! | S48: =IF([3]!Table14[[#This Row],[Nullable in Table and in Oracle View NULL, NOT NULL]]="No","NOT NULL","NULL")=VLOOKUP(A48,[2]Model!C$2:I$228,6,FALSE) -> #REF! | T48: =VLOOKUP(B48,[2]Table!A$2:F$415,1,FALSE)=[3]!Table14[[#This Row],[Physical Name of Attribute (Name of column in Table) Supplied by DA Team]] -> #REF! | U48: =VLOOKUP(B48,Table!A$2:F$319,2,FALSE)=Table14[[#This Row],[Data type in Oracle VARCHAR2(n), DATE, NUMBER(m,n), TIMETSTAMP(6)]] -> FALSE | V48: =VLOOKUP(B48,Table!A$2:F$231,3,FALSE)=Table14[[#This Row],[Nullable in Table and in Oracle View NULL, NOT NULL]] -> TRUE | W48: =VLOOKUP(B48,Table!A$2:H$228,6,FALSE)=Table14[[#This Row],[Business Definition (To go into comments and into Meta Data Hub)]] -> FALSE | X48: =VLOOKUP((UPPER(SUBSTITUTE(A48," ","_"))),'[2]Consumer View'!A$2:I$329,1,FALSE) -> OFFSET_ARRANGEMENT_SETTLEMENT_TYPE_CODE | Y48: CCSI_OWNER | Z48: AR_DIM | AA48: SETL_TP_CD | AD48: ccal_repl_owner.txn t join ccal_repl_owner.apa ap ON ap.exec_id = t.txn_id left join ccsi_owner.ar_dim ad ON AP.OFST_AR_ID = ad.AR_ID and t.td >= ad.EFF_DT and t.td < ad.END_DT | AE48: [9/6/24]: Reflected the change to use TXN.TD from Product Backlog Item 1912566: Change join condition and update data types for Activity | AH48: Y
A49: Offset Arrangement Settlement Type Description | B49: OFST_AR_SETL_TP_DSC | C49: Offset_arrangement_settlement_type | D49: VARCHAR2(100) | E49: Yes | F49: character varying(100) | G49: Yes | H49: If the APA was satisfied by offsetting with another RJ arrangement then, this column will contain information about the offsetted arrangement. A description that identifies how an arrangement settles its security transactions. This settlement type code is applicable for offset arrangements. | J49: Add | K49: 3 | O49: =VLOOKUP(A49,[1]Model!C$2:J$559,2,FALSE)=B49 -> TRUE | P49: =VLOOKUP(A49,Model!C$2:G$228,5,FALSE)=D49 -> TRUE | Q49: =VLOOKUP(A49,[2]Model!C$2:L$228,8,FALSE) -> 189 | R49: =VLOOKUP(A49,[2]Model!C$2:G$228,3,FALSE)=[3]!Table14[[#This Row],[Business Definition (To go into comments and into Meta Data Hub)]] -> #VALUE! | S49: =IF([3]!Table14[[#This Row],[Nullable in Table and in Oracle View NULL, NOT NULL]]="No","NOT NULL","NULL")=VLOOKUP(A49,[2]Model!C$2:I$228,6,FALSE) -> #REF! | T49: =VLOOKUP(B49,[2]Table!A$2:F$415,1,FALSE)=[3]!Table14[[#This Row],[Physical Name of Attribute (Name of column in Table) Supplied by DA Team]] -> #REF! | U49: =VLOOKUP(B49,Table!A$2:F$319,2,FALSE)=Table14[[#This Row],[Data type in Oracle VARCHAR2(n), DATE, NUMBER(m,n), TIMETSTAMP(6)]] -> FALSE | V49: =VLOOKUP(B49,Table!A$2:F$231,3,FALSE)=Table14[[#This Row],[Nullable in Table and in Oracle View NULL, NOT NULL]] -> TRUE | W49: =VLOOKUP(B49,Table!A$2:H$228,6,FALSE)=Table14[[#This Row],[Business Definition (To go into comments and into Meta Data Hub)]] -> FALSE | X49: =VLOOKUP((UPPER(SUBSTITUTE(A49," ","_"))),'[2]Consumer View'!A$2:I$329,1,FALSE) -> OFFSET_ARRANGEMENT_SETTLEMENT_TYPE_DESCRIPTION | Y49: CCSI_OWNER | Z49: AR_DIM | AA49: SETL_TP | AD49: ccal_repl_owner.txn t join ccal_repl_owner.apa ap ON ap.exec_id = t.txn_id left join ccsi_owner.ar_dim ad ON AP.OFST_AR_ID = ad.AR_ID and t.td >= ad.EFF_DT and t.td < ad.END_DT | AE49: [9/6/24]: Reflected the change to use TXN.TD from Product Backlog Item 1912566: Change join condition and update data types for Activity | AH49: Y
A50: Arrangement Settlement Type Code | B50: AR_SETL_TP_CD | C50: Account_Settlement_Type_Code | D50: VARCHAR2(20) | E50: Yes | F50: character varying(20) | G50: Yes | H50: A code that identifies how an arrangement settles its security transactions. | J50: Add | K50: 3 | O50: =VLOOKUP(A50,[1]Model!C$2:J$559,2,FALSE)=B50 -> TRUE | P50: =VLOOKUP(A50,Model!C$2:G$228,5,FALSE)=D50 -> TRUE | Q50: =VLOOKUP(A50,[2]Model!C$2:L$228,8,FALSE) -> 190 | R50: =VLOOKUP(A50,[2]Model!C$2:G$228,3,FALSE)=[3]!Table14[[#This Row],[Business Definition (To go into comments and into Meta Data Hub)]] -> #REF! | S50: =IF([3]!Table14[[#This Row],[Nullable in Table and in Oracle View NULL, NOT NULL]]="No","NOT NULL","NULL")=VLOOKUP(A50,[2]Model!C$2:I$228,6,FALSE) -> #REF! | T50: =VLOOKUP(B50,[2]Table!A$2:F$415,1,FALSE)=[3]!Table14[[#This Row],[Physical Name of Attribute (Name of column in Table) Supplied by DA Team]] -> #REF! | U50: =VLOOKUP(B50,Table!A$2:F$319,2,FALSE)=Table14[[#This Row],[Data type in Oracle VARCHAR2(n), DATE, NUMBER(m,n), TIMETSTAMP(6)]] -> FALSE | V50: =VLOOKUP(B50,Table!A$2:F$231,3,FALSE)=Table14[[#This Row],[Nullable in Table and in Oracle View NULL, NOT NULL]] -> TRUE | W50: =VLOOKUP(B50,Table!A$2:H$228,6,FALSE)=Table14[[#This Row],[Business Definition (To go into comments and into Meta Data Hub)]] -> FALSE | X50: =VLOOKUP((UPPER(SUBSTITUTE(A50," ","_"))),'[2]Consumer View'!A$2:I$329,1,FALSE) -> ARRANGEMENT_SETTLEMENT_TYPE_CODE | Y50: CCSI_OWNER | Z50: AR_DIM | AA50: SETL_TP_CD | AD50: ccal_repl_owner.txn t LEFT join ccsi_owner.ar_dim ard ON ard.AR_ID = t.AR_ID and ard.eff_dt <= t.td and ard.end_dt > t.td | AE50: [9/6/24]: Reflected the change to use TXN.TD from Product Backlog Item 1912566: Change join condition and update data types for Activity. [9/17/24]: Changing to use TXN.AR_ID per Product Backlog Item 1998220: Fix Activity issues for Historical Load | AH50: Y
A51: Arrangement Settlement Type Description | B51: AR_SETL_TP_DSC | C51: Account_Settlement_Type | D51: VARCHAR2(100) | E51: Yes | F51: character varying(100) | G51: Yes | H51: A description that identifies how an arrangement settles its security transactions. | J51: Add | K51: 3 | O51: =VLOOKUP(A51,[1]Model!C$2:J$559,2,FALSE)=B51 -> TRUE | P51: =VLOOKUP(A51,Model!C$2:G$228,5,FALSE)=D51 -> TRUE | Q51: =VLOOKUP(A51,[2]Model!C$2:L$228,8,FALSE) -> 191 | R51: =VLOOKUP(A51,[2]Model!C$2:G$228,3,FALSE)=[3]!Table14[[#This Row],[Business Definition (To go into comments and into Meta Data Hub)]] -> #REF! | S51: =IF([3]!Table14[[#This Row],[Nullable in Table and in Oracle View NULL, NOT NULL]]="No","NOT NULL","NULL")=VLOOKUP(A51,[2]Model!C$2:I$228,6,FALSE) -> #REF! | T51: =VLOOKUP(B51,[2]Table!A$2:F$415,1,FALSE)=[3]!Table14[[#This Row],[Physical Name of Attribute (Name of column in Table) Supplied by DA Team]] -> #REF! | U51: =VLOOKUP(B51,Table!A$2:F$319,2,FALSE)=Table14[[#This Row],[Data type in Oracle VARCHAR2(n), DATE, NUMBER(m,n), TIMETSTAMP(6)]] -> FALSE | V51: =VLOOKUP(B51,Table!A$2:F$231,3,FALSE)=Table14[[#This Row],[Nullable in Table and in Oracle View NULL, NOT NULL]] -> TRUE | W51: =VLOOKUP(B51,Table!A$2:H$228,6,FALSE)=Table14[[#This Row],[Business Definition (To go into comments and into Meta Data Hub)]] -> TRUE | X51: =VLOOKUP((UPPER(SUBSTITUTE(A51," ","_"))),'[2]Consumer View'!A$2:I$329,1,FALSE) -> ARRANGEMENT_SETTLEMENT_TYPE_DESCRIPTION | Y51: CCSI_OWNER | Z51: AR_DIM | AA51: SETL_TP | AD51: ccal_repl_owner.txn t LEFT join ccsi_owner.ar_dim ard ON ard.AR_ID = t.AR_ID and ard.eff_dt <= t.td and ard.end_dt > t.td | AE51: [9/6/24]: Reflected the change to use TXN.TD from Product Backlog Item 1912566: Change join condition and update data types for Activity. [9/17/24]: Changing to use TXN.AR_ID per Product Backlog Item 1998220: Fix Activity issues for Historical Load | AH51: Y
A52: Originating Source System Arrangement Id | B52: ORIG_SRC_STM_AR_ID | C52: Business_Assigned_Arrangement_ID | D52: VARCHAR2(50) | E52: Yes | F52: character varying(50) | G52: Yes | H52: Contains the account number/contract number from the original source system provider - e.g., SIS Account number for brokerage accounts | J52: Add | K52: 3 | O52: =VLOOKUP(A52,[1]Model!C$2:J$559,2,FALSE)=B52 -> TRUE | P52: =VLOOKUP(A52,Model!C$2:G$228,5,FALSE)=D52 -> TRUE | Q52: =VLOOKUP(A52,[2]Model!C$2:L$228,8,FALSE) -> 184 | R52: =VLOOKUP(A52,[2]Model!C$2:G$228,3,FALSE)=[3]!Table14[[#This Row],[Business Definition (To go into comments and into Meta Data Hub)]] -> #REF! | S52: =IF([3]!Table14[[#This Row],[Nullable in Table and in Oracle View NULL, NOT NULL]]="No","NOT NULL","NULL")=VLOOKUP(A52,[2]Model!C$2:I$228,6,FALSE) -> #REF! | T52: =VLOOKUP(B52,[2]Table!A$2:F$415,1,FALSE)=[3]!Table14[[#This Row],[Physical Name of Attribute (Name of column in Table) Supplied by DA Team]] -> #REF! | U52: =VLOOKUP(B52,Table!A$2:F$319,2,FALSE)=Table14[[#This Row],[Data type in Oracle VARCHAR2(n), DATE, NUMBER(m,n), TIMETSTAMP(6)]] -> FALSE | V52: =VLOOKUP(B52,Table!A$2:F$231,3,FALSE)=Table14[[#This Row],[Nullable in Table and in Oracle View NULL, NOT NULL]] -> TRUE | W52: =VLOOKUP(B52,Table!A$2:H$228,6,FALSE)=Table14[[#This Row],[Business Definition (To go into comments and into Meta Data Hub)]] -> TRUE | X52: =VLOOKUP((UPPER(SUBSTITUTE(A52," ","_"))),'[2]Consumer View'!A$2:I$329,1,FALSE) -> ORIGINATING_SOURCE_SYSTEM_ARRANGEMENT_ID | Y52: CCSI_OWNER | Z52: AR_DIM AR_AC_SUBDIM | AA52: ORIG_SRC_STM_AR_ID AC_NUM | AD52: ccal_repl_owner.txn t join ccal_repl_owner.apa apa on apa.exec_id = t.txn_id WHEN txn.src_stm_id = 5 (RJBNK1) and apa.ac_id is not null (NOTE: APA on ESP activity is always APACSH defined on [ETL Notes] tab) THEN left join ccsi_owner.ar_ac_subdim aas ON aas.ar_id = t.ar_id AND aas.dep_ac_setup_id = apa.ac_id and aas.eff_dt <= t.td and aas.end_dt > t.td use aas.AC_NUM ELSE ccal_repl_owner.txn t left join ccsi_owner.ar_dim ard ON ard.AR_ID = t.AR_ID and ard.eff_dt <= t.td and ard.end_dt > t.td use ard.ORIG_SRC_STM_AR_ID | AE52: [9/6/24]: Updated lookup for RJBNK1 ESP accounts. Product Backlog Item 1998220: Fix Activity issues for Historical Load. Also reflected the change to use TXN.TD from Product Backlog Item 1912566: Change join condition and update data types for Activity. [9/18/24]: Corrected Transformation logic to use TXN.AR_ID instead APA.AR_ID. [9/19/24]: Brought back APA join for APA.AC_ID | AH52: Y
A53: Trade Date Dimension Id | B53: TD_DIM_ID | D53: NUMBER(38,0) | E53: No | F53: NUMERIC(38,0) | G53: Yes | H53: Synthetic Key identifying a single date in the DATE Dimension, based on Trade date | J53: Existing | K53: 3 | O53: =VLOOKUP(A53,[1]Model!C$2:J$559,2,FALSE)=B53 -> TRUE | P53: =VLOOKUP(A53,Model!C$2:G$228,5,FALSE)=D53 -> #N/A | Q53: =VLOOKUP(A53,[2]Model!C$2:L$228,8,FALSE) -> 37 | R53: =VLOOKUP(A53,[2]Model!C$2:G$228,3,FALSE)=[3]!Table14[[#This Row],[Business Definition (To go into comments and into Meta Data Hub)]] -> #REF! | S53: =IF([3]!Table14[[#This Row],[Nullable in Table and in Oracle View NULL, NOT NULL]]="No","NOT NULL","NULL")=VLOOKUP(A53,[2]Model!C$2:I$228,6,FALSE) -> #REF! | T53: =VLOOKUP(B53,[2]Table!A$2:F$415,1,FALSE)=[3]!Table14[[#This Row],[Physical Name of Attribute (Name of column in Table) Supplied by DA Team]] -> #REF! | U53: =VLOOKUP(B53,Table!A$2:F$319,2,FALSE)=Table14[[#This Row],[Data type in Oracle VARCHAR2(n), DATE, NUMBER(m,n), TIMETSTAMP(6)]] -> TRUE | V53: =VLOOKUP(B53,Table!A$2:F$231,3,FALSE)=Table14[[#This Row],[Nullable in Table and in Oracle View NULL, NOT NULL]] -> TRUE | W53: =VLOOKUP(B53,Table!A$2:H$228,6,FALSE)=Table14[[#This Row],[Business Definition (To go into comments and into Meta Data Hub)]] -> TRUE | X53: =VLOOKUP((UPPER(SUBSTITUTE(A53," ","_"))),'[2]Consumer View'!A$2:I$329,1,FALSE) -> TRADE_DATE_DIMENSION_ID | Y53: COMMON_OWNER | Z53: DATE_DIM | AA53: DT_DIM_ID | AD53: ccal_repl_owner.txn t LEFT join common_owner.date_dim dd ON t.td = dd.cal_dt | AH53: REMOVE (DIM_ID)
A54: Exchange Dimension Id | B54: EXG_DIM_ID | D54: NUMBER(38,0) | E54: No | F54: NUMERIC(38,0) | G54: Yes | H54: Surrogate key for Exchange Dim - The exchange that the transaction was conducted on | J54: Existing | K54: 3 | O54: =VLOOKUP(A54,[1]Model!C$2:J$559,2,FALSE)=B54 -> TRUE | P54: =VLOOKUP(A54,Model!C$2:G$228,5,FALSE)=D54 -> TRUE | Q54: =VLOOKUP(A54,[2]Model!C$2:L$228,8,FALSE) -> 38 | R54: =VLOOKUP(A54,[2]Model!C$2:G$228,3,FALSE)=[3]!Table14[[#This Row],[Business Definition (To go into comments and into Meta Data Hub)]] -> #REF! | S54: =IF([3]!Table14[[#This Row],[Nullable in Table and in Oracle View NULL, NOT NULL]]="No","NOT NULL","NULL")=VLOOKUP(A54,[2]Model!C$2:I$228,6,FALSE) -> #REF! | T54: =VLOOKUP(B54,[2]Table!A$2:F$415,1,FALSE)=[3]!Table14[[#This Row],[Physical Name of Attribute (Name of column in Table) Supplied by DA Team]] -> #REF! | U54: =VLOOKUP(B54,Table!A$2:F$319,2,FALSE)=Table14[[#This Row],[Data type in Oracle VARCHAR2(n), DATE, NUMBER(m,n), TIMETSTAMP(6)]] -> TRUE | V54: =VLOOKUP(B54,Table!A$2:F$231,3,FALSE)=Table14[[#This Row],[Nullable in Table and in Oracle View NULL, NOT NULL]] -> TRUE | W54: =VLOOKUP(B54,Table!A$2:H$228,6,FALSE)=Table14[[#This Row],[Business Definition (To go into comments and into Meta Data Hub)]] -> TRUE | X54: =VLOOKUP((UPPER(SUBSTITUTE(A54," ","_"))),'[2]Consumer View'!A$2:I$329,1,FALSE) -> EXCHANGE_DIMENSION_ID | Y54: CIRD_OWNER | Z54: EXG_DIM | AA54: EXG_DIM_ID | AD54: ccal_repl_owner.txn t left join cird_owner.exg_dim ed ON ed.EXG_CD = t.exg_code | AE54: SELECT e.exg_dim_id FROM CIRD_OWNER.EXG_DIM e, CCAL_REPL_OWNER.txn t where t.EXG_CODE = e.EXG_CD and t.txn_id = ap.exec_id | AH54: REMOVE (DIM_ID)
A55: Accounting Type Code | B55: ACG_TP_CD | C55: Accounting_Type_Code | D55: VARCHAR2(1) | E55: Yes | F55: character varying(1) | G55: Yes | H55: Accounting type code from SIS (e.g., 1,2) | J55: Existing | K55: 3 | O55: =VLOOKUP(A55,[1]Model!C$2:J$559,2,FALSE)=B55 -> TRUE | P55: =VLOOKUP(A55,Model!C$2:G$228,5,FALSE)=D55 -> TRUE | Q55: =VLOOKUP(A55,[2]Model!C$2:L$228,8,FALSE) -> 102 | R55: =VLOOKUP(A55,[2]Model!C$2:G$228,3,FALSE)=[3]!Table14[[#This Row],[Business Definition (To go into comments and into Meta Data Hub)]] -> #REF! | S55: =IF([3]!Table14[[#This Row],[Nullable in Table and in Oracle View NULL, NOT NULL]]="No","NOT NULL","NULL")=VLOOKUP(A55,[2]Model!C$2:I$228,6,FALSE) -> #REF! | T55: =VLOOKUP(B55,[2]Table!A$2:F$415,1,FALSE)=[3]!Table14[[#This Row],[Physical Name of Attribute (Name of column in Table) Supplied by DA Team]] -> #REF! | U55: =VLOOKUP(B55,Table!A$2:F$319,2,FALSE)=Table14[[#This Row],[Data type in Oracle VARCHAR2(n), DATE, NUMBER(m,n), TIMETSTAMP(6)]] -> FALSE | V55: =VLOOKUP(B55,Table!A$2:F$231,3,FALSE)=Table14[[#This Row],[Nullable in Table and in Oracle View NULL, NOT NULL]] -> TRUE | W55: =VLOOKUP(B55,Table!A$2:H$228,6,FALSE)=Table14[[#This Row],[Business Definition (To go into comments and into Meta Data Hub)]] -> TRUE | X55: =VLOOKUP((UPPER(SUBSTITUTE(A55," ","_"))),'[2]Consumer View'!A$2:I$329,1,FALSE) -> ACCOUNTING_TYPE_CODE | Y55: COMMON_OWNER | Z55: ACG_TP_DIM | AA55: ACG_TP_CD | AD55: First preference is to APACASH and then to APASEC ccal_repl_owner.txn t join ccal_repl_owner.apa ap ON ap.exec_id = t.txn_id left join common_owner.acg_tp_dim atd ON AP.ACG_TP_ID = atd.ACG_TP_ID | AH55: N
A56: Accounting Type Dimension Id | B56: ACG_TP_DIM_ID | D56: NUMBER(38,0) | E56: No | F56: NUMERIC(38,0) | G56: Yes | H56: Surrogate key for SIS Accounting Dimension | J56: Existing | K56: 3 | O56: =VLOOKUP(A56,[1]Model!C$2:J$559,2,FALSE)=B56 -> TRUE | P56: =VLOOKUP(A56,Model!C$2:G$228,5,FALSE)=D56 -> TRUE | Q56: =VLOOKUP(A56,[2]Model!C$2:L$228,8,FALSE) -> 41 | R56: =VLOOKUP(A56,[2]Model!C$2:G$228,3,FALSE)=[3]!Table14[[#This Row],[Business Definition (To go into comments and into Meta Data Hub)]] -> #REF! | S56: =IF([3]!Table14[[#This Row],[Nullable in Table and in Oracle View NULL, NOT NULL]]="No","NOT NULL","NULL")=VLOOKUP(A56,[2]Model!C$2:I$228,6,FALSE) -> #REF! | T56: =VLOOKUP(B56,[2]Table!A$2:F$415,1,FALSE)=[3]!Table14[[#This Row],[Physical Name of Attribute (Name of column in Table) Supplied by DA Team]] -> #REF! | U56: =VLOOKUP(B56,Table!A$2:F$319,2,FALSE)=Table14[[#This Row],[Data type in Oracle VARCHAR2(n), DATE, NUMBER(m,n), TIMETSTAMP(6)]] -> TRUE | V56: =VLOOKUP(B56,Table!A$2:F$231,3,FALSE)=Table14[[#This Row],[Nullable in Table and in Oracle View NULL, NOT NULL]] -> TRUE | W56: =VLOOKUP(B56,Table!A$2:H$228,6,FALSE)=Table14[[#This Row],[Business Definition (To go into comments and into Meta Data Hub)]] -> TRUE | X56: =VLOOKUP((UPPER(SUBSTITUTE(A56," ","_"))),'[2]Consumer View'!A$2:I$329,1,FALSE) -> ACCOUNTING_TYPE_DIMENSION_ID | Y56: COMMON_OWNER | Z56: ACG_TP_DIM | AA56: ACG_TP_DIM_ID | AD56: First preference is to APACASH and then to APASEC ccal_repl_owner.txn t join ccal_repl_owner.apa ap ON ap.exec_id = t.txn_id left join common_owner.acg_tp_dim atd ON AP.ACG_TP_ID = atd.ACG_TP_ID | AH56: REMOVE (DIM_ID)
A57: Accounting Type Name | B57: ACG_TP_NM | C57: Accounting_Type | D57: VARCHAR2(30) | E57: Yes | F57: character varying(30) | G57: Yes | H57: It is the Sub Account associated with the position identifying the regulatory needs of the position. (e.g., cash account,margin account) | J57: Existing | K57: 3 | O57: =VLOOKUP(A57,[1]Model!C$2:J$559,2,FALSE)=B57 -> TRUE | P57: =VLOOKUP(A57,Model!C$2:G$228,5,FALSE)=D57 -> TRUE | Q57: =VLOOKUP(A57,[2]Model!C$2:L$228,8,FALSE) -> 101 | R57: =VLOOKUP(A57,[2]Model!C$2:G$228,3,FALSE)=[3]!Table14[[#This Row],[Business Definition (To go into comments and into Meta Data Hub)]] -> #REF! | S57: =IF([3]!Table14[[#This Row],[Nullable in Table and in Oracle View NULL, NOT NULL]]="No","NOT NULL","NULL")=VLOOKUP(A57,[2]Model!C$2:I$228,6,FALSE) -> #REF! | T57: =VLOOKUP(B57,[2]Table!A$2:F$415,1,FALSE)=[3]!Table14[[#This Row],[Physical Name of Attribute (Name of column in Table) Supplied by DA Team]] -> #REF! | U57: =VLOOKUP(B57,Table!A$2:F$319,2,FALSE)=Table14[[#This Row],[Data type in Oracle VARCHAR2(n), DATE, NUMBER(m,n), TIMETSTAMP(6)]] -> FALSE | V57: =VLOOKUP(B57,Table!A$2:F$231,3,FALSE)=Table14[[#This Row],[Nullable in Table and in Oracle View NULL, NOT NULL]] -> TRUE | W57: =VLOOKUP(B57,Table!A$2:H$228,6,FALSE)=Table14[[#This Row],[Business Definition (To go into comments and into Meta Data Hub)]] -> TRUE | X57: =VLOOKUP((UPPER(SUBSTITUTE(A57," ","_"))),'[2]Consumer View'!A$2:I$329,1,FALSE) -> ACCOUNTING_TYPE_NAME | Y57: COMMON_OWNER | Z57: ACG_TP_DIM | AA57: ACG_TP_NM | AD57: First preference is to APACASH and then to APASEC ccal_repl_owner.txn t join ccal_repl_owner.apa ap ON ap.exec_id = t.txn_id left join common_owner.acg_tp_dim atd ON AP.ACG_TP_ID = atd.ACG_TP_ID | AH57: N
A58: Accounting Type Id | B58: ACG_TP_ID | D58: NUMBER(38,0) | E58: Yes | F58: NUMERIC(38,0) | G58: Yes | H58: Numeric identifier of the accounting type ID (e.g., 1006, 1001) | J58: Add | K58: 3 | O58: =VLOOKUP(A58,[1]Model!C$2:J$559,2,FALSE)=B58 -> TRUE | P58: =VLOOKUP(A58,Model!C$2:G$228,5,FALSE)=D58 -> TRUE | Q58: =VLOOKUP(A58,[2]Model!C$2:L$228,8,FALSE) -> 192 | R58: =VLOOKUP(A58,[2]Model!C$2:G$228,3,FALSE)=[3]!Table14[[#This Row],[Business Definition (To go into comments and into Meta Data Hub)]] -> #REF! | S58: =IF([3]!Table14[[#This Row],[Nullable in Table and in Oracle View NULL, NOT NULL]]="No","NOT NULL","NULL")=VLOOKUP(A58,[2]Model!C$2:I$228,6,FALSE) -> #REF! | T58: =VLOOKUP(B58,[2]Table!A$2:F$415,1,FALSE)=[3]!Table14[[#This Row],[Physical Name of Attribute (Name of column in Table) Supplied by DA Team]] -> #REF! | U58: =VLOOKUP(B58,Table!A$2:F$319,2,FALSE)=Table14[[#This Row],[Data type in Oracle VARCHAR2(n), DATE, NUMBER(m,n), TIMETSTAMP(6)]] -> TRUE | V58: =VLOOKUP(B58,Table!A$2:F$231,3,FALSE)=Table14[[#This Row],[Nullable in Table and in Oracle View NULL, NOT NULL]] -> TRUE | W58: =VLOOKUP(B58,Table!A$2:H$228,6,FALSE)=Table14[[#This Row],[Business Definition (To go into comments and into Meta Data Hub)]] -> TRUE | X58: =VLOOKUP((UPPER(SUBSTITUTE(A58," ","_"))),'[2]Consumer View'!A$2:I$329,1,FALSE) -> ACCOUNTING_TYPE_ID | Y58: CCAL_REPL_OWNER | Z58: APA | AA58: ACG_TP_ID | AD58: First preference is to APACASH and then to APASEC ccal_repl_owner.txn txn join ccal_repl_owner.apa ap ON ap.exec_id = t.txn_id | AH58: N
A59: Active Flag | B59: ACTV_F | C59: Transaction_Active_Flag | D59: VARCHAR2(1) | E59: No | F59: character varying(1) | G59: Yes | H59: Indicates that the row is active | J59: Update | K59: 3 | O59: =VLOOKUP(A59,[1]Model!C$2:J$559,2,FALSE)=B59 -> TRUE | P59: =VLOOKUP(A59,Model!C$2:G$228,5,FALSE)=D59 -> TRUE | Q59: =VLOOKUP(A59,[2]Model!C$2:L$228,8,FALSE) -> 95 | R59: =VLOOKUP(A59,[2]Model!C$2:G$228,3,FALSE)=[3]!Table14[[#This Row],[Business Definition (To go into comments and into Meta Data Hub)]] -> #REF! | S59: =IF([3]!Table14[[#This Row],[Nullable in Table and in Oracle View NULL, NOT NULL]]="No","NOT NULL","NULL")=VLOOKUP(A59,[2]Model!C$2:I$228,6,FALSE) -> #REF! | T59: =VLOOKUP(B59,[2]Table!A$2:F$415,1,FALSE)=[3]!Table14[[#This Row],[Physical Name of Attribute (Name of column in Table) Supplied by DA Team]] -> #REF! | U59: =VLOOKUP(B59,Table!A$2:F$319,2,FALSE)=Table14[[#This Row],[Data type in Oracle VARCHAR2(n), DATE, NUMBER(m,n), TIMETSTAMP(6)]] -> FALSE | V59: =VLOOKUP(B59,Table!A$2:F$231,3,FALSE)=Table14[[#This Row],[Nullable in Table and in Oracle View NULL, NOT NULL]] -> TRUE | W59: =VLOOKUP(B59,Table!A$2:H$228,6,FALSE)=Table14[[#This Row],[Business Definition (To go into comments and into Meta Data Hub)]] -> TRUE | X59: =VLOOKUP((UPPER(SUBSTITUTE(A59," ","_"))),'[2]Consumer View'!A$2:I$329,1,FALSE) -> ACTIVE_FLAG | Y59: CCAL_REPL_OWNER | Z59: TXN | AA59: ACTV_F | AH59: N
A60: Aggregate Original Fees | B60: AGRT_ORIG_FEES | C60: Aggregate_original_fee | D60: NUMBER | E60: Yes | F60: NUMBER | G60: Yes | H60: **Deprecated field. Not supported anymore.** | J60: Remove Restore | K60: 3 | O60: =VLOOKUP(A60,[1]Model!C$2:J$559,2,FALSE)=B60 -> TRUE | P60: =VLOOKUP(A60,Model!C$2:G$228,5,FALSE)=D60 -> FALSE | Q60: =VLOOKUP(A60,[2]Model!C$2:L$228,8,FALSE) -> 87 | R60: =VLOOKUP(A60,[2]Model!C$2:G$228,3,FALSE)=[3]!Table14[[#This Row],[Business Definition (To go into comments and into Meta Data Hub)]] -> #REF! | S60: =IF([3]!Table14[[#This Row],[Nullable in Table and in Oracle View NULL, NOT NULL]]="No","NOT NULL","NULL")=VLOOKUP(A60,[2]Model!C$2:I$228,6,FALSE) -> #REF! | T60: =VLOOKUP(B60,[2]Table!A$2:F$415,1,FALSE)=[3]!Table14[[#This Row],[Physical Name of Attribute (Name of column in Table) Supplied by DA Team]] -> #REF! | U60: =VLOOKUP(B60,Table!A$2:F$319,2,FALSE)=Table14[[#This Row],[Data type in Oracle VARCHAR2(n), DATE, NUMBER(m,n), TIMETSTAMP(6)]] -> TRUE | V60: =VLOOKUP(B60,Table!A$2:F$231,3,FALSE)=Table14[[#This Row],[Nullable in Table and in Oracle View NULL, NOT NULL]] -> TRUE | W60: =VLOOKUP(B60,Table!A$2:H$228,6,FALSE)=Table14[[#This Row],[Business Definition (To go into comments and into Meta Data Hub)]] -> FALSE | X60: =VLOOKUP((UPPER(SUBSTITUTE(A60," ","_"))),'[2]Consumer View'!A$2:I$329,1,FALSE) -> AGGREGATE_ORIGINAL_FEES | Y60: CCAL_REPL_OWNER | Z60: FIP | AA60: FIP_ORIG_AMT | AD60: ccal_repl_owner.txn t join ccal_repl_owner.apa ap ON ap.exec_id = t.txn_id LEFT join ccal_repl_owner.fip f ON f.apa_id = ap.apa_id | AE60: Remove the field [7/23/24]: To be restored as there are consumers. Product Backlog Item 1948982: Update columns in Activity Fact and Activity Detail Fact | AH60: N
A61: Aggregate Statement Fees | B61: AGRT_STMT_FEES | C61: Aggregate_statement_fee | D61: NUMBER | E61: Yes | F61: NUMBER | G61: Yes | H61: **Deprecated field. Not supported anymore.** | J61: Remove Restore | K61: 3 | O61: =VLOOKUP(A61,[1]Model!C$2:J$559,2,FALSE)=B61 -> TRUE | P61: =VLOOKUP(A61,Model!C$2:G$228,5,FALSE)=D61 -> FALSE | Q61: =VLOOKUP(A61,[2]Model!C$2:L$228,8,FALSE) -> 88 | R61: =VLOOKUP(A61,[2]Model!C$2:G$228,3,FALSE)=[3]!Table14[[#This Row],[Business Definition (To go into comments and into Meta Data Hub)]] -> #REF! | S61: =IF([3]!Table14[[#This Row],[Nullable in Table and in Oracle View NULL, NOT NULL]]="No","NOT NULL","NULL")=VLOOKUP(A61,[2]Model!C$2:I$228,6,FALSE) -> #REF! | T61: =VLOOKUP(B61,[2]Table!A$2:F$415,1,FALSE)=[3]!Table14[[#This Row],[Physical Name of Attribute (Name of column in Table) Supplied by DA Team]] -> #REF! | U61: =VLOOKUP(B61,Table!A$2:F$319,2,FALSE)=Table14[[#This Row],[Data type in Oracle VARCHAR2(n), DATE, NUMBER(m,n), TIMETSTAMP(6)]] -> TRUE | V61: =VLOOKUP(B61,Table!A$2:F$231,3,FALSE)=Table14[[#This Row],[Nullable in Table and in Oracle View NULL, NOT NULL]] -> TRUE | W61: =VLOOKUP(B61,Table!A$2:H$228,6,FALSE)=Table14[[#This Row],[Business Definition (To go into comments and into Meta Data Hub)]] -> FALSE | X61: =VLOOKUP((UPPER(SUBSTITUTE(A61," ","_"))),'[2]Consumer View'!A$2:I$329,1,FALSE) -> AGGREGATE_STATEMENT_FEES | Y61: CCAL_REPL_OWNER | Z61: FIP | AA61: FIP_STMT_AMT | AD61: ccal_repl_owner.txn t join ccal_repl_owner.apa ap ON ap.exec_id = t.txn_id LEFT join ccal_repl_owner.fip f ON f.apa_id = ap.apa_id | AE61: Remove the field [7/23/24]: To be restored as there are consumers. Product Backlog Item 1948982: Update columns in Activity Fact and Activity Detail Fact | AH61: N
A62: Arrangement Id | B62: AR_ID | C62: Arrangement_Id | D62: NUMBER(38,0) | E62: Yes | F62: NUMERIC(38,0) | G62: Yes | H62: Arrangement Id of the Arrangement this APA belongs to. | J62: Existing | K62: 3 | O62: =VLOOKUP(A62,[1]Model!C$2:J$559,2,FALSE)=B62 -> TRUE | P62: =VLOOKUP(A62,Model!C$2:G$228,5,FALSE)=D62 -> TRUE | Q62: =VLOOKUP(A62,[2]Model!C$2:L$228,8,FALSE) -> 103 | R62: =VLOOKUP(A62,[2]Model!C$2:G$228,3,FALSE)=[3]!Table14[[#This Row],[Business Definition (To go into comments and into Meta Data Hub)]] -> #REF! | S62: =IF([3]!Table14[[#This Row],[Nullable in Table and in Oracle View NULL, NOT NULL]]="No","NOT NULL","NULL")=VLOOKUP(A62,[2]Model!C$2:I$228,6,FALSE) -> #REF! | T62: =VLOOKUP(B62,[2]Table!A$2:F$415,1,FALSE)=[3]!Table14[[#This Row],[Physical Name of Attribute (Name of column in Table) Supplied by DA Team]] -> #REF! | U62: =VLOOKUP(B62,Table!A$2:F$319,2,FALSE)=Table14[[#This Row],[Data type in Oracle VARCHAR2(n), DATE, NUMBER(m,n), TIMETSTAMP(6)]] -> TRUE | V62: =VLOOKUP(B62,Table!A$2:F$231,3,FALSE)=Table14[[#This Row],[Nullable in Table and in Oracle View NULL, NOT NULL]] -> TRUE | W62: =VLOOKUP(B62,Table!A$2:H$228,6,FALSE)=Table14[[#This Row],[Business Definition (To go into comments and into Meta Data Hub)]] -> TRUE | X62: =VLOOKUP((UPPER(SUBSTITUTE(A62," ","_"))),'[2]Consumer View'!A$2:I$329,1,FALSE) -> ARRANGEMENT_ID | Y62: CCAL_REPL_OWNER | Z62: TXN | AA62: AR_ID | AE62: [9/6/24]: Changed source table from APA to TXN. Product Backlog Item 1998220: Fix Activity issues for Historical Load | AH62: N
A63: Batch Date | B63: BATCH_DT | C63: Batch_Date | D63: DATE | E63: Yes | F63: timestamp without time zone | G63: Yes | H63: Business Date for the Load run of the Activity Asset Packager row | J63: Existing | K63: 3 | O63: =VLOOKUP(A63,[1]Model!C$2:J$559,2,FALSE)=B63 -> TRUE | P63: =VLOOKUP(A63,Model!C$2:G$228,5,FALSE)=D63 -> TRUE | Q63: =VLOOKUP(A63,[2]Model!C$2:L$228,8,FALSE) -> 104 | R63: =VLOOKUP(A63,[2]Model!C$2:G$228,3,FALSE)=[3]!Table14[[#This Row],[Business Definition (To go into comments and into Meta Data Hub)]] -> #REF! | S63: =IF([3]!Table14[[#This Row],[Nullable in Table and in Oracle View NULL, NOT NULL]]="No","NOT NULL","NULL")=VLOOKUP(A63,[2]Model!C$2:I$228,6,FALSE) -> #REF! | T63: =VLOOKUP(B63,[2]Table!A$2:F$415,1,FALSE)=[3]!Table14[[#This Row],[Physical Name of Attribute (Name of column in Table) Supplied by DA Team]] -> #REF! | U63: =VLOOKUP(B63,Table!A$2:F$319,2,FALSE)=Table14[[#This Row],[Data type in Oracle VARCHAR2(n), DATE, NUMBER(m,n), TIMETSTAMP(6)]] -> TRUE | V63: =VLOOKUP(B63,Table!A$2:F$231,3,FALSE)=Table14[[#This Row],[Nullable in Table and in Oracle View NULL, NOT NULL]] -> TRUE | W63: =VLOOKUP(B63,Table!A$2:H$228,6,FALSE)=Table14[[#This Row],[Business Definition (To go into comments and into Meta Data Hub)]] -> FALSE | X63: =VLOOKUP((UPPER(SUBSTITUTE(A63," ","_"))),'[2]Consumer View'!A$2:I$329,1,FALSE) -> BATCH_DATE | Y63: CCAL_REPL_OWNER | Z63: J$TXN | AA63: BATCH_DT | AD63: ccal_repl_owner.txn t join ccal_repl_owner.j$txn jt ON jt.txn_id = t.txn_id | AH63: N
A64: Booking Date | B64: BKG_DT | C64: Booking_Date | D64: DATE | E64: Yes | F64: timestamp without time zone | G64: Yes | H64: System generated Date Time stamp when the record was created. In SIS would be represented by Effective Date. | J64: Existing | K64: 3 | O64: =VLOOKUP(A64,[1]Model!C$2:J$559,2,FALSE)=B64 -> TRUE | P64: =VLOOKUP(A64,Model!C$2:G$228,5,FALSE)=D64 -> TRUE | Q64: =VLOOKUP(A64,[2]Model!C$2:L$228,8,FALSE) -> 21 | R64: =VLOOKUP(A64,[2]Model!C$2:G$228,3,FALSE)=[3]!Table14[[#This Row],[Business Definition (To go into comments and into Meta Data Hub)]] -> #REF! | S64: =IF([3]!Table14[[#This Row],[Nullable in Table and in Oracle View NULL, NOT NULL]]="No","NOT NULL","NULL")=VLOOKUP(A64,[2]Model!C$2:I$228,6,FALSE) -> #REF! | T64: =VLOOKUP(B64,[2]Table!A$2:F$415,1,FALSE)=[3]!Table14[[#This Row],[Physical Name of Attribute (Name of column in Table) Supplied by DA Team]] -> #REF! | U64: =VLOOKUP(B64,Table!A$2:F$319,2,FALSE)=Table14[[#This Row],[Data type in Oracle VARCHAR2(n), DATE, NUMBER(m,n), TIMETSTAMP(6)]] -> TRUE | V64: =VLOOKUP(B64,Table!A$2:F$231,3,FALSE)=Table14[[#This Row],[Nullable in Table and in Oracle View NULL, NOT NULL]] -> TRUE | W64: =VLOOKUP(B64,Table!A$2:H$228,6,FALSE)=Table14[[#This Row],[Business Definition (To go into comments and into Meta Data Hub)]] -> TRUE | X64: =VLOOKUP((UPPER(SUBSTITUTE(A64," ","_"))),'[2]Consumer View'!A$2:I$329,1,FALSE) -> BOOKING_DATE | Y64: CCAL_REPL_OWNER | Z64: TXN | AA64: BKG_DT | AH64: N
A65: Branch Code | B65: BR_CD | C65: Associate_Department_Branch_Code | D65: VARCHAR2(20) | E65: Yes | F65: character varying(20) | G65: Yes | H65: Entity Code of the Financial Advisor that is executing the trade. | J65: Existing | K65: 3 | O65: =VLOOKUP(A65,[1]Model!C$2:J$559,2,FALSE)=B65 -> TRUE | P65: =VLOOKUP(A65,Model!C$2:G$228,5,FALSE)=D65 -> TRUE | Q65: =VLOOKUP(A65,[2]Model!C$2:L$228,8,FALSE) -> 92 | R65: =VLOOKUP(A65,[2]Model!C$2:G$228,3,FALSE)=[3]!Table14[[#This Row],[Business Definition (To go into comments and into Meta Data Hub)]] -> #REF! | S65: =IF([3]!Table14[[#This Row],[Nullable in Table and in Oracle View NULL, NOT NULL]]="No","NOT NULL","NULL")=VLOOKUP(A65,[2]Model!C$2:I$228,6,FALSE) -> #REF! | T65: =VLOOKUP(B65,[2]Table!A$2:F$415,1,FALSE)=[3]!Table14[[#This Row],[Physical Name of Attribute (Name of column in Table) Supplied by DA Team]] -> #REF! | U65: =VLOOKUP(B65,Table!A$2:F$319,2,FALSE)=Table14[[#This Row],[Data type in Oracle VARCHAR2(n), DATE, NUMBER(m,n), TIMETSTAMP(6)]] -> FALSE | V65: =VLOOKUP(B65,Table!A$2:F$231,3,FALSE)=Table14[[#This Row],[Nullable in Table and in Oracle View NULL, NOT NULL]] -> TRUE | W65: =VLOOKUP(B65,Table!A$2:H$228,6,FALSE)=Table14[[#This Row],[Business Definition (To go into comments and into Meta Data Hub)]] -> TRUE | X65: =VLOOKUP((UPPER(SUBSTITUTE(A65," ","_"))),'[2]Consumer View'!A$2:I$329,1,FALSE) -> BRANCH_CODE | Y65: CCAL_REPL_OWNER | Z65: TXN | AA65: BR_CODE | AH65: N
A66: Brokerage Arrangement Id | B66: BKR_AR_ID | C66: Brokerage_Arrangement_Id | D66: NUMBER(38,0) | E66: Yes | F66: NUMERIC(38,0) | G66: Yes | H66: Brokerage arrangement associated with the Arrangement id. If the transaction is for a brokerage arrangement than both will have same value. | J66: Existing | K66: 3 | O66: =VLOOKUP(A66,[1]Model!C$2:J$559,2,FALSE)=B66 -> TRUE | P66: =VLOOKUP(A66,Model!C$2:G$228,5,FALSE)=D66 -> TRUE | Q66: =VLOOKUP(A66,[2]Model!C$2:L$228,8,FALSE) -> 105 | R66: =VLOOKUP(A66,[2]Model!C$2:G$228,3,FALSE)=[3]!Table14[[#This Row],[Business Definition (To go into comments and into Meta Data Hub)]] -> #REF! | S66: =IF([3]!Table14[[#This Row],[Nullable in Table and in Oracle View NULL, NOT NULL]]="No","NOT NULL","NULL")=VLOOKUP(A66,[2]Model!C$2:I$228,6,FALSE) -> #REF! | T66: =VLOOKUP(B66,[2]Table!A$2:F$415,1,FALSE)=[3]!Table14[[#This Row],[Physical Name of Attribute (Name of column in Table) Supplied by DA Team]] -> #REF! | U66: =VLOOKUP(B66,Table!A$2:F$319,2,FALSE)=Table14[[#This Row],[Data type in Oracle VARCHAR2(n), DATE, NUMBER(m,n), TIMETSTAMP(6)]] -> TRUE | V66: =VLOOKUP(B66,Table!A$2:F$231,3,FALSE)=Table14[[#This Row],[Nullable in Table and in Oracle View NULL, NOT NULL]] -> TRUE | W66: =VLOOKUP(B66,Table!A$2:H$228,6,FALSE)=Table14[[#This Row],[Business Definition (To go into comments and into Meta Data Hub)]] -> TRUE | X66: =VLOOKUP((UPPER(SUBSTITUTE(A66," ","_"))),'[2]Consumer View'!A$2:I$329,1,FALSE) -> BROKERAGE_ARRANGEMENT_ID | Y66: CCAL_REPL_OWNER | Z66: APA TXN | AA66: BKR_AR_ID AR_ID | AD66: ccal_repl_owner.txn t join ccal_repl_owner.apa ap ON ap.exec_id = t.txn_id join ccal_repl_owner.AR_DIM BKR_AR_DIM ON T.AR_ID = BKR_AR_DIM.AR_ID and TD >= BKR_AR_DIM.EFF_DT (+) and TD < BKR_AR_DIM.END_DT (+)) If BKR_AR_DIM.ORIG_SRC_STM_CD = 'BKRBO1' then populate with T.AR_ID Else if AP.BKR_AR_ID is not NULL then use ap.BKR_AR_ID Else join ccsi_owner.AR_GRP_SUBDIM asd ON asd.AR_ID = t.AR_ID and t.td >= asd.EFF_DT and t.td < asd.END_DT and populate with asd.LINKED_BKR_AR_ID | AE66: [9/6/24]: Does not require any ETL. It's a direct map from CCAL. [9/17/24]: There is a logic for SIS AR_IDs. Reflecting the same and changing to use TXN.AR_ID per Product Backlog Item 1998220: Fix Activity issues for Historical Load. Adding a lookup for non-SIS activity use case if APA.BKR_AR_ID is missing to use base group. | AH66: N
A67: Buy Sell Indicator | B67: BUY_SELL_IND | C67: Buy_or_Sell_Indicator | D67: VARCHAR2(10) | E67: Yes | F67: character varying(10) | G67: Yes | H67: Indicator to determine whether the transaction is a sale or a purchase | J67: Existing | K67: 3 | O67: =VLOOKUP(A67,[1]Model!C$2:J$559,2,FALSE)=B67 -> TRUE | P67: =VLOOKUP(A67,Model!C$2:G$228,5,FALSE)=D67 -> TRUE | Q67: =VLOOKUP(A67,[2]Model!C$2:L$228,8,FALSE) -> 52 | R67: =VLOOKUP(A67,[2]Model!C$2:G$228,3,FALSE)=[3]!Table14[[#This Row],[Business Definition (To go into comments and into Meta Data Hub)]] -> #REF! | S67: =IF([3]!Table14[[#This Row],[Nullable in Table and in Oracle View NULL, NOT NULL]]="No","NOT NULL","NULL")=VLOOKUP(A67,[2]Model!C$2:I$228,6,FALSE) -> #REF! | T67: =VLOOKUP(B67,[2]Table!A$2:F$415,1,FALSE)=[3]!Table14[[#This Row],[Physical Name of Attribute (Name of column in Table) Supplied by DA Team]] -> #REF! | U67: =VLOOKUP(B67,Table!A$2:F$319,2,FALSE)=Table14[[#This Row],[Data type in Oracle VARCHAR2(n), DATE, NUMBER(m,n), TIMETSTAMP(6)]] -> FALSE | V67: =VLOOKUP(B67,Table!A$2:F$231,3,FALSE)=Table14[[#This Row],[Nullable in Table and in Oracle View NULL, NOT NULL]] -> TRUE | W67: =VLOOKUP(B67,Table!A$2:H$228,6,FALSE)=Table14[[#This Row],[Business Definition (To go into comments and into Meta Data Hub)]] -> TRUE | X67: =VLOOKUP((UPPER(SUBSTITUTE(A67," ","_"))),'[2]Consumer View'!A$2:I$329,1,FALSE) -> BUY_SELL_INDICATOR | Y67: CCAL_REPL_OWNER | Z67: TXN | AA67: BUY_SELL_IND | AE67: [6/3/24]: Modified target data type for Oracle and Redshift. PBI 1912566 | AH67: N
A68: Cash Activity Category | B68: CASH_AVY_CGY | C68: Cash_Activity_Category | D68: VARCHAR2(25) | E68: Yes | F68: character varying(25) | G68: Yes | H68: Represents the specific Category of activity such as a 'Purchase' or 'Income'. Further refinement of the categories are captured under Activity Type. This field will be populated only if the transaction has a Cash leg. | J68: Update | K68: 3 | O68: =VLOOKUP(A68,[1]Model!C$2:J$559,2,FALSE)=B68 -> TRUE | P68: =VLOOKUP(A68,Model!C$2:G$228,5,FALSE)=D68 -> TRUE | Q68: =VLOOKUP(A68,[2]Model!C$2:L$228,8,FALSE) -> 85 | R68: =VLOOKUP(A68,[2]Model!C$2:G$228,3,FALSE)=[3]!Table14[[#This Row],[Business Definition (To go into comments and into Meta Data Hub)]] -> #REF! | S68: =IF([3]!Table14[[#This Row],[Nullable in Table and in Oracle View NULL, NOT NULL]]="No","NOT NULL","NULL")=VLOOKUP(A68,[2]Model!C$2:I$228,6,FALSE) -> #REF! | T68: =VLOOKUP(B68,[2]Table!A$2:F$415,1,FALSE)=[3]!Table14[[#This Row],[Physical Name of Attribute (Name of column in Table) Supplied by DA Team]] -> #REF! | U68: =VLOOKUP(B68,Table!A$2:F$319,2,FALSE)=Table14[[#This Row],[Data type in Oracle VARCHAR2(n), DATE, NUMBER(m,n), TIMETSTAMP(6)]] -> FALSE | V68: =VLOOKUP(B68,Table!A$2:F$231,3,FALSE)=Table14[[#This Row],[Nullable in Table and in Oracle View NULL, NOT NULL]] -> TRUE | W68: =VLOOKUP(B68,Table!A$2:H$228,6,FALSE)=Table14[[#This Row],[Business Definition (To go into comments and into Meta Data Hub)]] -> FALSE | X68: =VLOOKUP((UPPER(SUBSTITUTE(A68," ","_"))),'[2]Consumer View'!A$2:I$329,1,FALSE) -> CASH_ACTIVITY_CATEGORY | Y68: CCAL_REPL_OWNER | Z68: AVY_CL | AA68: AVY_CGY | AD68: Use APACSH logic from 'ETL Notes' tab and below logic: ccal_repl_owner.txn t join ccal_repl_owner.apa ap ON ap.exec_id = t.txn_id left join ccal_repl_owner.txn_avy_cl tac ON tac.txn_id = t.txn_id and tac.actv_f = 'Y' and ap.apa_id = tac.apa_id left join ccal_repl_owner.avy_cl acl ON acl.avy_cl_id = tac.avy_cl_id | AH68: N
A69: Cash Simplified Display Activity Category | B69: CASH_SIMP_DSPL_AVY_CGY | C69: Cash_Simplified_Display_Activity_Category | D69: VARCHAR2(25) | E69: Yes | F69: character varying(25) | G69: Yes | H69: Simplified Display activity category shown to advisor in applications like client center. This field will be populated only if the transaction has a Cash leg. | J69: Add | K69: 3 | O69: =VLOOKUP(A69,[1]Model!C$2:J$559,2,FALSE)=B69 -> TRUE | P69: =VLOOKUP(A69,Model!C$2:G$228,5,FALSE)=D69 -> TRUE | Q69: =VLOOKUP(A69,[2]Model!C$2:L$228,8,FALSE) -> 174 | R69: =VLOOKUP(A69,[2]Model!C$2:G$228,3,FALSE)=[3]!Table14[[#This Row],[Business Definition (To go into comments and into Meta Data Hub)]] -> #REF! | S69: =IF([3]!Table14[[#This Row],[Nullable in Table and in Oracle View NULL, NOT NULL]]="No","NOT NULL","NULL")=VLOOKUP(A69,[2]Model!C$2:I$228,6,FALSE) -> #REF! | T69: =VLOOKUP(B69,[2]Table!A$2:F$415,1,FALSE)=[3]!Table14[[#This Row],[Physical Name of Attribute (Name of column in Table) Supplied by DA Team]] -> #REF! | U69: =VLOOKUP(B69,Table!A$2:F$319,2,FALSE)=Table14[[#This Row],[Data type in Oracle VARCHAR2(n), DATE, NUMBER(m,n), TIMETSTAMP(6)]] -> FALSE | V69: =VLOOKUP(B69,Table!A$2:F$231,3,FALSE)=Table14[[#This Row],[Nullable in Table and in Oracle View NULL, NOT NULL]] -> TRUE | W69: =VLOOKUP(B69,Table!A$2:H$228,6,FALSE)=Table14[[#This Row],[Business Definition (To go into comments and into Meta Data Hub)]] -> FALSE | X69: =VLOOKUP((UPPER(SUBSTITUTE(A69," ","_"))),'[2]Consumer View'!A$2:I$329,1,FALSE) -> CASH_SIMPLIFIED_DISPLAY_ACTIVITY_CATEGORY | Y69: CCAL_REPL_OWNER | Z69: AVY_CL | AA69: DSPL_AVY_CGY | AD69: Use APACSH logic from 'ETL Notes' tab and below logic: ccal_repl_owner.txn t join ccal_repl_owner.apa ap ON ap.exec_id = t.txn_id left join ccal_repl_owner.txn_avy_cl tac ON tac.txn_id = t.txn_id and tac.actv_f = 'Y' and ap.apa_id = tac.apa_id left join ccal_repl_owner.avy_cl acl ON acl.avy_cl_id = tac.avy_cl_id | AH69: N
A70: Cash Activity Classification Id | B70: CSH_AVY_CL_ID | C70: Cash_activity_classification_code | D70: NUMBER(38,0) | E70: Yes | F70: NUMERIC(38,0) | G70: Yes | H70: CDS assigned identifier for the activity class. This field will be populated only if the transaction has a Cash leg. | J70: Existing | K70: 3 | O70: =VLOOKUP(A70,[1]Model!C$2:J$559,2,FALSE)=B70 -> TRUE | P70: =VLOOKUP(A70,Model!C$2:G$228,5,FALSE)=D70 -> TRUE | Q70: =VLOOKUP(A70,[2]Model!C$2:L$228,8,FALSE) -> 84 | R70: =VLOOKUP(A70,[2]Model!C$2:G$228,3,FALSE)=[3]!Table14[[#This Row],[Business Definition (To go into comments and into Meta Data Hub)]] -> #REF! | S70: =IF([3]!Table14[[#This Row],[Nullable in Table and in Oracle View NULL, NOT NULL]]="No","NOT NULL","NULL")=VLOOKUP(A70,[2]Model!C$2:I$228,6,FALSE) -> #REF! | T70: =VLOOKUP(B70,[2]Table!A$2:F$415,1,FALSE)=[3]!Table14[[#This Row],[Physical Name of Attribute (Name of column in Table) Supplied by DA Team]] -> #REF! | U70: =VLOOKUP(B70,Table!A$2:F$319,2,FALSE)=Table14[[#This Row],[Data type in Oracle VARCHAR2(n), DATE, NUMBER(m,n), TIMETSTAMP(6)]] -> TRUE | V70: =VLOOKUP(B70,Table!A$2:F$231,3,FALSE)=Table14[[#This Row],[Nullable in Table and in Oracle View NULL, NOT NULL]] -> TRUE | W70: =VLOOKUP(B70,Table!A$2:H$228,6,FALSE)=Table14[[#This Row],[Business Definition (To go into comments and into Meta Data Hub)]] -> FALSE | X70: =VLOOKUP((UPPER(SUBSTITUTE(A70," ","_"))),'[2]Consumer View'!A$2:I$329,1,FALSE) -> CASH_ACTIVITY_CLASSIFICATION_ID | Y70: CCAL_REPL_OWNER | Z70: TXN_AVY_CL | AA70: AVY_CL_ID | AD70: Use APACSH logic from 'ETL Notes' tab and below logic: ccal_repl_owner.txn t join ccal_repl_owner.apa ap ON ap.exec_id = t.txn_id left join ccal_repl_owner.txn_avy_cl tac ON tac.txn_id = t.txn_id and tac.actv_f = 'Y' and ap.apa_id = tac.apa_id | AH70: N
A71: Cash Activity Type | B71: CASH_AVY_TP | C71: Cash_Activity_Type | D71: VARCHAR2(100) | E71: Yes | F71: character varying(100) | G71: Yes | H71: Represents a more refined view of the Activity Category. This field will be populated only if the transaction has a Cash leg. | J71: Existing | K71: 3 | O71: =VLOOKUP(A71,[1]Model!C$2:J$559,2,FALSE)=B71 -> TRUE | P71: =VLOOKUP(A71,Model!C$2:G$228,5,FALSE)=D71 -> TRUE | Q71: =VLOOKUP(A71,[2]Model!C$2:L$228,8,FALSE) -> 86 | R71: =VLOOKUP(A71,[2]Model!C$2:G$228,3,FALSE)=[3]!Table14[[#This Row],[Business Definition (To go into comments and into Meta Data Hub)]] -> #REF! | S71: =IF([3]!Table14[[#This Row],[Nullable in Table and in Oracle View NULL, NOT NULL]]="No","NOT NULL","NULL")=VLOOKUP(A71,[2]Model!C$2:I$228,6,FALSE) -> #REF! | T71: =VLOOKUP(B71,[2]Table!A$2:F$415,1,FALSE)=[3]!Table14[[#This Row],[Physical Name of Attribute (Name of column in Table) Supplied by DA Team]] -> #REF! | U71: =VLOOKUP(B71,Table!A$2:F$319,2,FALSE)=Table14[[#This Row],[Data type in Oracle VARCHAR2(n), DATE, NUMBER(m,n), TIMETSTAMP(6)]] -> FALSE | V71: =VLOOKUP(B71,Table!A$2:F$231,3,FALSE)=Table14[[#This Row],[Nullable in Table and in Oracle View NULL, NOT NULL]] -> TRUE | W71: =VLOOKUP(B71,Table!A$2:H$228,6,FALSE)=Table14[[#This Row],[Business Definition (To go into comments and into Meta Data Hub)]] -> FALSE | X71: =VLOOKUP((UPPER(SUBSTITUTE(A71," ","_"))),'[2]Consumer View'!A$2:I$329,1,FALSE) -> CASH_ACTIVITY_TYPE | Y71: CCAL_REPL_OWNER | Z71: AVY_CL | AA71: AVY_TP | AD71: Use APACSH logic from 'ETL Notes' tab and below logic: ccal_repl_owner.txn t join ccal_repl_owner.apa ap ON ap.exec_id = t.txn_id left join ccal_repl_owner.txn_avy_cl tac ON tac.txn_id = t.txn_id and tac.actv_f = 'Y' and ap.apa_id = tac.apa_id left join ccal_repl_owner.avy_cl acl ON acl.avy_cl_id = tac.avy_cl_id | AH71: N
A72: Cash Simplified Display Activity Type | B72: CASH_SIMP_DSPL_AVY_TP | C72: Cash_Simplified_Display_Activity_Type | D72: VARCHAR2(100) | E72: Yes | F72: character varying(100) | G72: Yes | H72: Simplified Display activity type shown to advisor in applications like client center. This field will be populated only if the transaction has a Cash leg. | J72: Add | K72: 3 | O72: =VLOOKUP(A72,[1]Model!C$2:J$559,2,FALSE)=B72 -> TRUE | P72: =VLOOKUP(A72,Model!C$2:G$228,5,FALSE)=D72 -> TRUE | Q72: =VLOOKUP(A72,[2]Model!C$2:L$228,8,FALSE) -> 175 | R72: =VLOOKUP(A72,[2]Model!C$2:G$228,3,FALSE)=[3]!Table14[[#This Row],[Business Definition (To go into comments and into Meta Data Hub)]] -> #REF! | S72: =IF([3]!Table14[[#This Row],[Nullable in Table and in Oracle View NULL, NOT NULL]]="No","NOT NULL","NULL")=VLOOKUP(A72,[2]Model!C$2:I$228,6,FALSE) -> #REF! | T72: =VLOOKUP(B72,[2]Table!A$2:F$415,1,FALSE)=[3]!Table14[[#This Row],[Physical Name of Attribute (Name of column in Table) Supplied by DA Team]] -> #REF! | U72: =VLOOKUP(B72,Table!A$2:F$319,2,FALSE)=Table14[[#This Row],[Data type in Oracle VARCHAR2(n), DATE, NUMBER(m,n), TIMETSTAMP(6)]] -> FALSE | V72: =VLOOKUP(B72,Table!A$2:F$231,3,FALSE)=Table14[[#This Row],[Nullable in Table and in Oracle View NULL, NOT NULL]] -> TRUE | W72: =VLOOKUP(B72,Table!A$2:H$228,6,FALSE)=Table14[[#This Row],[Business Definition (To go into comments and into Meta Data Hub)]] -> FALSE | X72: =VLOOKUP((UPPER(SUBSTITUTE(A72," ","_"))),'[2]Consumer View'!A$2:I$329,1,FALSE) -> CASH_SIMPLIFIED_DISPLAY_ACTIVITY_TYPE | Y72: CCAL_REPL_OWNER | Z72: AVY_CL | AA72: DSPL_AVY_TP | AD72: Use APACSH logic from 'ETL Notes' tab and below logic: ccal_repl_owner.txn t join ccal_repl_owner.apa ap ON ap.exec_id = t.txn_id left join ccal_repl_owner.txn_avy_cl tac ON tac.txn_id = t.txn_id and tac.actv_f = 'Y' and ap.apa_id = tac.apa_id left join ccal_repl_owner.avy_cl acl ON acl.avy_cl_id = tac.avy_cl_id | AH72: N
A73: Cash Alternate Description Trailer 2 | B73: CASH_ALT_DSC_TRAILER_2 | C73: Cash_Alternate_Description_Trailer_2 | D73: VARCHAR2(256) | E73: Yes | F73: character varying(256) | G73: Yes | H73: Second line of unformatted, monolingual narrative booking information. SIS trailer field 2. This field will be populated only if the transaction has a Cash leg. | J73: Existing | K73: 3 | O73: =VLOOKUP(A73,[1]Model!C$2:J$559,2,FALSE)=B73 -> TRUE | P73: =VLOOKUP(A73,Model!C$2:G$228,5,FALSE)=D73 -> TRUE | Q73: =VLOOKUP(A73,[2]Model!C$2:L$228,8,FALSE) -> 50 | R73: =VLOOKUP(A73,[2]Model!C$2:G$228,3,FALSE)=[3]!Table14[[#This Row],[Business Definition (To go into comments and into Meta Data Hub)]] -> #REF! | S73: =IF([3]!Table14[[#This Row],[Nullable in Table and in Oracle View NULL, NOT NULL]]="No","NOT NULL","NULL")=VLOOKUP(A73,[2]Model!C$2:I$228,6,FALSE) -> #REF! | T73: =VLOOKUP(B73,[2]Table!A$2:F$415,1,FALSE)=[3]!Table14[[#This Row],[Physical Name of Attribute (Name of column in Table) Supplied by DA Team]] -> #REF! | U73: =VLOOKUP(B73,Table!A$2:F$319,2,FALSE)=Table14[[#This Row],[Data type in Oracle VARCHAR2(n), DATE, NUMBER(m,n), TIMETSTAMP(6)]] -> FALSE | V73: =VLOOKUP(B73,Table!A$2:F$231,3,FALSE)=Table14[[#This Row],[Nullable in Table and in Oracle View NULL, NOT NULL]] -> TRUE | W73: =VLOOKUP(B73,Table!A$2:H$228,6,FALSE)=Table14[[#This Row],[Business Definition (To go into comments and into Meta Data Hub)]] -> FALSE | X73: =VLOOKUP((UPPER(SUBSTITUTE(A73," ","_"))),'[2]Consumer View'!A$2:I$329,1,FALSE) -> CASH_ALTERNATE_DESCRIPTION_TRAILER_2 | Y73: CCAL_REPL_OWNER | Z73: APA | AA73: ALT_DSC | AD73: Use APACSH logic from 'ETL Notes' tab. | AH73: N
A74: Cash Asset Package External Qualifier | B74: CASH_APA_EXT_QUALFR | C74: Cash_Asset_Package_External_Qualifier | D74: VARCHAR2(50) | E74: Yes | F74: character varying(50) | G74: Yes | H74: Qualifier code from the external source system. This field will be populated only if the transaction has a Cash leg. | J74: Add | K74: 3 | O74: =VLOOKUP(A74,[1]Model!C$2:J$559,2,FALSE)=B74 -> TRUE | P74: =VLOOKUP(A74,Model!C$2:G$228,5,FALSE)=D74 -> TRUE | Q74: =VLOOKUP(A74,[2]Model!C$2:L$228,8,FALSE) -> 51 | R74: =VLOOKUP(A74,[2]Model!C$2:G$228,3,FALSE)=[3]!Table14[[#This Row],[Business Definition (To go into comments and into Meta Data Hub)]] -> #REF! | S74: =IF([3]!Table14[[#This Row],[Nullable in Table and in Oracle View NULL, NOT NULL]]="No","NOT NULL","NULL")=VLOOKUP(A74,[2]Model!C$2:I$228,6,FALSE) -> #REF! | T74: =VLOOKUP(B74,[2]Table!A$2:F$415,1,FALSE)=[3]!Table14[[#This Row],[Physical Name of Attribute (Name of column in Table) Supplied by DA Team]] -> #REF! | U74: =VLOOKUP(B74,Table!A$2:F$319,2,FALSE)=Table14[[#This Row],[Data type in Oracle VARCHAR2(n), DATE, NUMBER(m,n), TIMETSTAMP(6)]] -> FALSE | V74: =VLOOKUP(B74,Table!A$2:F$231,3,FALSE)=Table14[[#This Row],[Nullable in Table and in Oracle View NULL, NOT NULL]] -> TRUE | W74: =VLOOKUP(B74,Table!A$2:H$228,6,FALSE)=Table14[[#This Row],[Business Definition (To go into comments and into Meta Data Hub)]] -> FALSE | X74: =VLOOKUP((UPPER(SUBSTITUTE(A74," ","_"))),'[2]Consumer View'!A$2:I$329,1,FALSE) -> CASH_ASSET_PACKAGE_EXTERNAL_QUALIFIER | Y74: CCAL_REPL_OWNER | Z74: APA | AA74: APA_EXT_QUALFR | AD74: Use APACSH logic from 'ETL Notes' tab. | AH74: N
A75: Cash Asset Package Id | B75: CSH_APA_ID | D75: NUMBER(38,0) | E75: Yes | F75: NUMERIC(38,0) | G75: Yes | H75: APA_ID from CCAL APA table. It is recorded here for the purpose of maintaining a link with the source. This field will be populated only if the transaction has a Cash leg. | J75: Existing | K75: 3 | O75: =VLOOKUP(A75,[1]Model!C$2:J$559,2,FALSE)=B75 -> TRUE | P75: =VLOOKUP(A75,Model!C$2:G$228,5,FALSE)=D75 -> TRUE | Q75: =VLOOKUP(A75,[2]Model!C$2:L$228,8,FALSE) -> 24 | R75: =VLOOKUP(A75,[2]Model!C$2:G$228,3,FALSE)=[3]!Table14[[#This Row],[Business Definition (To go into comments and into Meta Data Hub)]] -> #REF! | S75: =IF([3]!Table14[[#This Row],[Nullable in Table and in Oracle View NULL, NOT NULL]]="No","NOT NULL","NULL")=VLOOKUP(A75,[2]Model!C$2:I$228,6,FALSE) -> #REF! | T75: =VLOOKUP(B75,[2]Table!A$2:F$415,1,FALSE)=[3]!Table14[[#This Row],[Physical Name of Attribute (Name of column in Table) Supplied by DA Team]] -> #REF! | U75: =VLOOKUP(B75,Table!A$2:F$319,2,FALSE)=Table14[[#This Row],[Data type in Oracle VARCHAR2(n), DATE, NUMBER(m,n), TIMETSTAMP(6)]] -> TRUE | V75: =VLOOKUP(B75,Table!A$2:F$231,3,FALSE)=Table14[[#This Row],[Nullable in Table and in Oracle View NULL, NOT NULL]] -> TRUE | W75: =VLOOKUP(B75,Table!A$2:H$228,6,FALSE)=Table14[[#This Row],[Business Definition (To go into comments and into Meta Data Hub)]] -> FALSE | X75: =VLOOKUP((UPPER(SUBSTITUTE(A75," ","_"))),'[2]Consumer View'!A$2:I$329,1,FALSE) -> CASH_ASSET_PACKAGE_ID | Y75: CCAL_REPL_OWNER | Z75: APA | AA75: APA_ID | AD75: Use APACSH logic from 'ETL Notes' tab. | AH75: N
A76: Cash Asset Package Type Code | B76: CASH_APA_TP_CD | C76: Cash_Asset_Package_Type_Code | D76: VARCHAR2(20) | E76: Yes | F76: character varying(20) | G76: Yes | H76: Code associated with Asset Package Type Id. This field will be populated only if the transaction has a Cash leg. | J76: Existing | K76: 3 | O76: =VLOOKUP(A76,[1]Model!C$2:J$559,2,FALSE)=B76 -> TRUE | P76: =VLOOKUP(A76,Model!C$2:G$228,5,FALSE)=D76 -> TRUE | Q76: =VLOOKUP(A76,[2]Model!C$2:L$228,8,FALSE) -> 81 | R76: =VLOOKUP(A76,[2]Model!C$2:G$228,3,FALSE)=[3]!Table14[[#This Row],[Business Definition (To go into comments and into Meta Data Hub)]] -> #REF! | S76: =IF([3]!Table14[[#This Row],[Nullable in Table and in Oracle View NULL, NOT NULL]]="No","NOT NULL","NULL")=VLOOKUP(A76,[2]Model!C$2:I$228,6,FALSE) -> #REF! | T76: =VLOOKUP(B76,[2]Table!A$2:F$415,1,FALSE)=[3]!Table14[[#This Row],[Physical Name of Attribute (Name of column in Table) Supplied by DA Team]] -> #REF! | U76: =VLOOKUP(B76,Table!A$2:F$319,2,FALSE)=Table14[[#This Row],[Data type in Oracle VARCHAR2(n), DATE, NUMBER(m,n), TIMETSTAMP(6)]] -> FALSE | V76: =VLOOKUP(B76,Table!A$2:F$231,3,FALSE)=Table14[[#This Row],[Nullable in Table and in Oracle View NULL, NOT NULL]] -> TRUE | W76: =VLOOKUP(B76,Table!A$2:H$228,6,FALSE)=Table14[[#This Row],[Business Definition (To go into comments and into Meta Data Hub)]] -> FALSE | X76: =VLOOKUP((UPPER(SUBSTITUTE(A76," ","_"))),'[2]Consumer View'!A$2:I$329,1,FALSE) -> CASH_ASSET_PACKAGE_TYPE_CODE | Y76: CCAL_REPL_OWNER | Z76: CL_VAL | AA76: CL_VAL_CODE | AD76: Use APACSH logic from 'ETL Notes' tab. | AH76: N
A77: Cash Asset Package Type Description | B77: CASH_APA_TP_DSC | C77: Cash_Asset_Package_Type_Description | D77: VARCHAR2(1000) | E77: Yes | F77: character varying(1000) | G77: Yes | H77: Description associated with Asset Package Type Id. This field will be populated only if the transaction has a Cash leg. | J77: Existing | K77: 3 | O77: =VLOOKUP(A77,[1]Model!C$2:J$559,2,FALSE)=B77 -> TRUE | P77: =VLOOKUP(A77,Model!C$2:G$228,5,FALSE)=D77 -> TRUE | Q77: =VLOOKUP(A77,[2]Model!C$2:L$228,8,FALSE) -> 83 | R77: =VLOOKUP(A77,[2]Model!C$2:G$228,3,FALSE)=[3]!Table14[[#This Row],[Business Definition (To go into comments and into Meta Data Hub)]] -> #REF! | S77: =IF([3]!Table14[[#This Row],[Nullable in Table and in Oracle View NULL, NOT NULL]]="No","NOT NULL","NULL")=VLOOKUP(A77,[2]Model!C$2:I$228,6,FALSE) -> #REF! | T77: =VLOOKUP(B77,[2]Table!A$2:F$415,1,FALSE)=[3]!Table14[[#This Row],[Physical Name of Attribute (Name of column in Table) Supplied by DA Team]] -> #REF! | U77: =VLOOKUP(B77,Table!A$2:F$319,2,FALSE)=Table14[[#This Row],[Data type in Oracle VARCHAR2(n), DATE, NUMBER(m,n), TIMETSTAMP(6)]] -> FALSE | V77: =VLOOKUP(B77,Table!A$2:F$231,3,FALSE)=Table14[[#This Row],[Nullable in Table and in Oracle View NULL, NOT NULL]] -> TRUE | W77: =VLOOKUP(B77,Table!A$2:H$228,6,FALSE)=Table14[[#This Row],[Business Definition (To go into comments and into Meta Data Hub)]] -> FALSE | X77: =VLOOKUP((UPPER(SUBSTITUTE(A77," ","_"))),'[2]Consumer View'!A$2:I$329,1,FALSE) -> CASH_ASSET_PACKAGE_TYPE_DESCRIPTION | Y77: CCAL_REPL_OWNER | Z77: CL_VAL | AA77: DSC | AD77: Use APACSH logic from 'ETL Notes' tab. | AH77: N
A78: Cash Asset Package Type Id | B78: CSH_APA_TP_ID | D78: NUMBER(38,0) | E78: Yes | F78: NUMERIC(38,0) | G78: Yes | H78: Asset Pacakge type Id from CCAL core. This field will be populated only if the transaction has a Cash leg. | J78: Existing | K78: 3 | O78: =VLOOKUP(A78,[1]Model!C$2:J$559,2,FALSE)=B78 -> TRUE | P78: =VLOOKUP(A78,Model!C$2:G$228,5,FALSE)=D78 -> TRUE | Q78: =VLOOKUP(A78,[2]Model!C$2:L$228,8,FALSE) -> 80 | R78: =VLOOKUP(A78,[2]Model!C$2:G$228,3,FALSE)=[3]!Table14[[#This Row],[Business Definition (To go into comments and into Meta Data Hub)]] -> #REF! | S78: =IF([3]!Table14[[#This Row],[Nullable in Table and in Oracle View NULL, NOT NULL]]="No","NOT NULL","NULL")=VLOOKUP(A78,[2]Model!C$2:I$228,6,FALSE) -> #REF! | T78: =VLOOKUP(B78,[2]Table!A$2:F$415,1,FALSE)=[3]!Table14[[#This Row],[Physical Name of Attribute (Name of column in Table) Supplied by DA Team]] -> #REF! | U78: =VLOOKUP(B78,Table!A$2:F$319,2,FALSE)=Table14[[#This Row],[Data type in Oracle VARCHAR2(n), DATE, NUMBER(m,n), TIMETSTAMP(6)]] -> TRUE | V78: =VLOOKUP(B78,Table!A$2:F$231,3,FALSE)=Table14[[#This Row],[Nullable in Table and in Oracle View NULL, NOT NULL]] -> TRUE | W78: =VLOOKUP(B78,Table!A$2:H$228,6,FALSE)=Table14[[#This Row],[Business Definition (To go into comments and into Meta Data Hub)]] -> FALSE | X78: =VLOOKUP((UPPER(SUBSTITUTE(A78," ","_"))),'[2]Consumer View'!A$2:I$329,1,FALSE) -> CASH_ASSET_PACKAGE_TYPE_ID | Y78: CCAL_REPL_OWNER | Z78: APA | AA78: APA_TP_ID | AD78: Use APACSH logic from 'ETL Notes' tab. | AH78: N
A79: Cash asset Package Type Name | B79: CASH_APA_TP_NM | C79: Cash_Asset_Package_Type | D79: VARCHAR2(200) | E79: Yes | F79: character varying(200) | G79: Yes | H79: Name of Asset Package Type Id. This field will be populated only if the transaction has a Cash leg. | J79: Update | K79: 3 | O79: =VLOOKUP(A79,[1]Model!C$2:J$559,2,FALSE)=B79 -> TRUE | P79: =VLOOKUP(A79,Model!C$2:G$228,5,FALSE)=D79 -> TRUE | Q79: =VLOOKUP(A79,[2]Model!C$2:L$228,8,FALSE) -> 82 | R79: =VLOOKUP(A79,[2]Model!C$2:G$228,3,FALSE)=[3]!Table14[[#This Row],[Business Definition (To go into comments and into Meta Data Hub)]] -> #REF! | S79: =IF([3]!Table14[[#This Row],[Nullable in Table and in Oracle View NULL, NOT NULL]]="No","NOT NULL","NULL")=VLOOKUP(A79,[2]Model!C$2:I$228,6,FALSE) -> #REF! | T79: =VLOOKUP(B79,[2]Table!A$2:F$415,1,FALSE)=[3]!Table14[[#This Row],[Physical Name of Attribute (Name of column in Table) Supplied by DA Team]] -> #REF! | U79: =VLOOKUP(B79,Table!A$2:F$319,2,FALSE)=Table14[[#This Row],[Data type in Oracle VARCHAR2(n), DATE, NUMBER(m,n), TIMETSTAMP(6)]] -> FALSE | V79: =VLOOKUP(B79,Table!A$2:F$231,3,FALSE)=Table14[[#This Row],[Nullable in Table and in Oracle View NULL, NOT NULL]] -> TRUE | W79: =VLOOKUP(B79,Table!A$2:H$228,6,FALSE)=Table14[[#This Row],[Business Definition (To go into comments and into Meta Data Hub)]] -> FALSE | X79: =VLOOKUP((UPPER(SUBSTITUTE(A79," ","_"))),'[2]Consumer View'!A$2:I$329,1,FALSE) -> CASH_ASSET_PACKAGE_TYPE_NAME | Y79: CCAL_REPL_OWNER | Z79: CL_VAL | AA79: CL_VAL_NM | AD79: Use APACSH logic from 'ETL Notes' tab. | AE79: [6/3/24]: Modified target data type for Oracle and Redshift. PBI 1912566 | AH79: N
A80: Cash Cird Product Id | B80: CASH_CIRD_PD_ID | C80: CASH_CIRD_PRODUCT_ID | D80: NUMBER(38,0) | E80: Yes | F80: NUMERIC(38,0) | G80: Yes | H80: CIRD identifier for product. This field will be populated only if the transaction has a Cash leg. | J80: Existing | K80: 3 | O80: =VLOOKUP(A80,[1]Model!C$2:J$559,2,FALSE)=B80 -> TRUE | P80: =VLOOKUP(A80,Model!C$2:G$228,5,FALSE)=D80 -> TRUE | Q80: =VLOOKUP(A80,[2]Model!C$2:L$228,8,FALSE) -> 106 | R80: =VLOOKUP(A80,[2]Model!C$2:G$228,3,FALSE)=[3]!Table14[[#This Row],[Business Definition (To go into comments and into Meta Data Hub)]] -> #REF! | S80: =IF([3]!Table14[[#This Row],[Nullable in Table and in Oracle View NULL, NOT NULL]]="No","NOT NULL","NULL")=VLOOKUP(A80,[2]Model!C$2:I$228,6,FALSE) -> #REF! | T80: =VLOOKUP(B80,[2]Table!A$2:F$415,1,FALSE)=[3]!Table14[[#This Row],[Physical Name of Attribute (Name of column in Table) Supplied by DA Team]] -> #REF! | U80: =VLOOKUP(B80,Table!A$2:F$319,2,FALSE)=Table14[[#This Row],[Data type in Oracle VARCHAR2(n), DATE, NUMBER(m,n), TIMETSTAMP(6)]] -> TRUE | V80: =VLOOKUP(B80,Table!A$2:F$231,3,FALSE)=Table14[[#This Row],[Nullable in Table and in Oracle View NULL, NOT NULL]] -> TRUE | W80: =VLOOKUP(B80,Table!A$2:H$228,6,FALSE)=Table14[[#This Row],[Business Definition (To go into comments and into Meta Data Hub)]] -> FALSE | X80: =VLOOKUP((UPPER(SUBSTITUTE(A80," ","_"))),'[2]Consumer View'!A$2:I$329,1,FALSE) -> CASH_CIRD_PRODUCT_ID | Y80: CCAL_REPL_OWNER | Z80: CCAL_CIRD_PD_MAP | AA80: CIRD_PD_ID | AD80: Use APACSH logic from 'ETL Notes' tab and below logic: ccal_repl_owner.apa ap left join ccal_repl_owner.ccal_cird_pd_map ccpd ON ap.pd_id = ccpd.ccal_pd_id and ccpm.actv_f = 'Y' | AH80: Y
A81: Cash Debit Credit Code | B81: CASH_DB_CR_CD | D81: VARCHAR2(20) | E81: Yes | F81: character varying(20) | G81: Yes | H81: A code representing Debit / Credit (e.g. D / C) This field will be populated only if the transaction has a Cash leg. | J81: Update | K81: 3 | O81: =VLOOKUP(A81,[1]Model!C$2:J$559,2,FALSE)=B81 -> TRUE | P81: =VLOOKUP(A81,Model!C$2:G$228,5,FALSE)=D81 -> TRUE | Q81: =VLOOKUP(A81,[2]Model!C$2:L$228,8,FALSE) -> 107 | R81: =VLOOKUP(A81,[2]Model!C$2:G$228,3,FALSE)=[3]!Table14[[#This Row],[Business Definition (To go into comments and into Meta Data Hub)]] -> #REF! | S81: =IF([3]!Table14[[#This Row],[Nullable in Table and in Oracle View NULL, NOT NULL]]="No","NOT NULL","NULL")=VLOOKUP(A81,[2]Model!C$2:I$228,6,FALSE) -> #REF! | T81: =VLOOKUP(B81,[2]Table!A$2:F$415,1,FALSE)=[3]!Table14[[#This Row],[Physical Name of Attribute (Name of column in Table) Supplied by DA Team]] -> #REF! | U81: =VLOOKUP(B81,Table!A$2:F$319,2,FALSE)=Table14[[#This Row],[Data type in Oracle VARCHAR2(n), DATE, NUMBER(m,n), TIMETSTAMP(6)]] -> FALSE | V81: =VLOOKUP(B81,Table!A$2:F$231,3,FALSE)=Table14[[#This Row],[Nullable in Table and in Oracle View NULL, NOT NULL]] -> TRUE | W81: =VLOOKUP(B81,Table!A$2:H$228,6,FALSE)=Table14[[#This Row],[Business Definition (To go into comments and into Meta Data Hub)]] -> FALSE | X81: =VLOOKUP((UPPER(SUBSTITUTE(A81," ","_"))),'[2]Consumer View'!A$2:I$329,1,FALSE) -> CASH_DEBIT_CREDIT_CODE | Y81: CCAL_REPL_OWNER | Z81: CL_VAL | AA81: CL_VAL_CODE | AD81: Use APACSH logic from 'ETL Notes' tab and below logic: ccal_repl_owner.apa ap left join ccal_repl_owner.cl_val cv ON ap.db_cr_id = cv.cl_val_id and cv.cl_scm_id = '15' | AH81: N
A82: Cash Debit Credit Name | B82: CASH_DB_CR_NM | C82: Cash_Debit_or_Credit | D82: VARCHAR2(100) | E82: Yes | F82: character varying(100) | G82: Yes | H82: A Name representing Debit / Credit (e.g. Debit / Credit) This field will be populated only if the transaction has a Cash leg. | J82: Update | K82: 3 | O82: =VLOOKUP(A82,[1]Model!C$2:J$559,2,FALSE)=B82 -> TRUE | P82: =VLOOKUP(A82,Model!C$2:G$228,5,FALSE)=D82 -> TRUE | Q82: =VLOOKUP(A82,[2]Model!C$2:L$228,8,FALSE) -> 108 | R82: =VLOOKUP(A82,[2]Model!C$2:G$228,3,FALSE)=[3]!Table14[[#This Row],[Business Definition (To go into comments and into Meta Data Hub)]] -> #REF! | S82: =IF([3]!Table14[[#This Row],[Nullable in Table and in Oracle View NULL, NOT NULL]]="No","NOT NULL","NULL")=VLOOKUP(A82,[2]Model!C$2:I$228,6,FALSE) -> #REF! | T82: =VLOOKUP(B82,[2]Table!A$2:F$415,1,FALSE)=[3]!Table14[[#This Row],[Physical Name of Attribute (Name of column in Table) Supplied by DA Team]] -> #REF! | U82: =VLOOKUP(B82,Table!A$2:F$319,2,FALSE)=Table14[[#This Row],[Data type in Oracle VARCHAR2(n), DATE, NUMBER(m,n), TIMETSTAMP(6)]] -> FALSE | V82: =VLOOKUP(B82,Table!A$2:F$231,3,FALSE)=Table14[[#This Row],[Nullable in Table and in Oracle View NULL, NOT NULL]] -> TRUE | W82: =VLOOKUP(B82,Table!A$2:H$228,6,FALSE)=Table14[[#This Row],[Business Definition (To go into comments and into Meta Data Hub)]] -> FALSE | X82: =VLOOKUP((UPPER(SUBSTITUTE(A82," ","_"))),'[2]Consumer View'!A$2:I$329,1,FALSE) -> CASH_DEBIT_CREDIT_NAME | Y82: CCAL_REPL_OWNER | Z82: CL_VAL | AA82: CL_VAL_NM | AD82: Use APACSH logic from 'ETL Notes' tab and below logic: ccal_repl_owner.apa ap left join ccal_repl_owner.cl_val cv ON ap.db_cr_id = cv.cl_val_id and cv.cl_scm_id = '15' | AH82: N
A83: Cash Description Trailer 1 | B83: CASH_DSC_TRAILER_1 | C83: Cash_Description_Trailer_1 | D83: VARCHAR2(256) | E83: Yes | F83: character varying(256) | G83: Yes | H83: First line of unformatted, monolingual narrative booking information. SIS Trailer field 1. This field will be populated only if the transaction has a Cash leg. | J83: Existing | K83: 3 | O83: =VLOOKUP(A83,[1]Model!C$2:J$559,2,FALSE)=B83 -> TRUE | P83: =VLOOKUP(A83,Model!C$2:G$228,5,FALSE)=D83 -> TRUE | Q83: =VLOOKUP(A83,[2]Model!C$2:L$228,8,FALSE) -> 49 | R83: =VLOOKUP(A83,[2]Model!C$2:G$228,3,FALSE)=[3]!Table14[[#This Row],[Business Definition (To go into comments and into Meta Data Hub)]] -> #REF! | S83: =IF([3]!Table14[[#This Row],[Nullable in Table and in Oracle View NULL, NOT NULL]]="No","NOT NULL","NULL")=VLOOKUP(A83,[2]Model!C$2:I$228,6,FALSE) -> #REF! | T83: =VLOOKUP(B83,[2]Table!A$2:F$415,1,FALSE)=[3]!Table14[[#This Row],[Physical Name of Attribute (Name of column in Table) Supplied by DA Team]] -> #REF! | U83: =VLOOKUP(B83,Table!A$2:F$319,2,FALSE)=Table14[[#This Row],[Data type in Oracle VARCHAR2(n), DATE, NUMBER(m,n), TIMETSTAMP(6)]] -> FALSE | V83: =VLOOKUP(B83,Table!A$2:F$231,3,FALSE)=Table14[[#This Row],[Nullable in Table and in Oracle View NULL, NOT NULL]] -> TRUE | W83: =VLOOKUP(B83,Table!A$2:H$228,6,FALSE)=Table14[[#This Row],[Business Definition (To go into comments and into Meta Data Hub)]] -> FALSE | X83: =VLOOKUP((UPPER(SUBSTITUTE(A83," ","_"))),'[2]Consumer View'!A$2:I$329,1,FALSE) -> CASH_DESCRIPTION_TRAILER_1 | Y83: CCAL_REPL_OWNER | Z83: APA | AA83: APA_DSC | AD83: Use APACSH logic from 'ETL Notes' tab. | AH83: N
A84: Cash Flow Generation Flag | B84: CF_GEN_F | D84: VARCHAR2(2) | E84: Yes | F84: character varying(2) | G84: Yes | H84: Cash Flow Generation Flag | J84: Existing | K84: 3 | O84: =VLOOKUP(A84,[1]Model!C$2:J$559,2,FALSE)=B84 -> TRUE | P84: =VLOOKUP(A84,Model!C$2:G$228,5,FALSE)=D84 -> TRUE | Q84: =VLOOKUP(A84,[2]Model!C$2:L$228,8,FALSE) -> 53 | R84: =VLOOKUP(A84,[2]Model!C$2:G$228,3,FALSE)=[3]!Table14[[#This Row],[Business Definition (To go into comments and into Meta Data Hub)]] -> #REF! | S84: =IF([3]!Table14[[#This Row],[Nullable in Table and in Oracle View NULL, NOT NULL]]="No","NOT NULL","NULL")=VLOOKUP(A84,[2]Model!C$2:I$228,6,FALSE) -> #REF! | T84: =VLOOKUP(B84,[2]Table!A$2:F$415,1,FALSE)=[3]!Table14[[#This Row],[Physical Name of Attribute (Name of column in Table) Supplied by DA Team]] -> #REF! | U84: =VLOOKUP(B84,Table!A$2:F$319,2,FALSE)=Table14[[#This Row],[Data type in Oracle VARCHAR2(n), DATE, NUMBER(m,n), TIMETSTAMP(6)]] -> FALSE | V84: =VLOOKUP(B84,Table!A$2:F$231,3,FALSE)=Table14[[#This Row],[Nullable in Table and in Oracle View NULL, NOT NULL]] -> TRUE | W84: =VLOOKUP(B84,Table!A$2:H$228,6,FALSE)=Table14[[#This Row],[Business Definition (To go into comments and into Meta Data Hub)]] -> TRUE | X84: =VLOOKUP((UPPER(SUBSTITUTE(A84," ","_"))),'[2]Consumer View'!A$2:I$329,1,FALSE) -> CASH_FLOW_GENERATION_FLAG | Y84: CCAL_REPL_OWNER | Z84: TXN | AA84: CF_GEN_F | AH84: N
A85: Cash Position Type Code | B85: CASH_POS_TP_CD | C85: Cash_Position_Type_Code | D85: VARCHAR2(10) | E85: Yes | F85: character varying(10) | G85: Yes | H85: Coded name for the Cash Postion Type e.g., rjtgs2i, rtc | J85: Existing | K85: 3 | O85: =VLOOKUP(A85,[1]Model!C$2:J$559,2,FALSE)=B85 -> TRUE | P85: =VLOOKUP(A85,Model!C$2:G$228,5,FALSE)=D85 -> TRUE | Q85: =VLOOKUP(A85,[2]Model!C$2:L$228,8,FALSE) -> 110 | R85: =VLOOKUP(A85,[2]Model!C$2:G$228,3,FALSE)=[3]!Table14[[#This Row],[Business Definition (To go into comments and into Meta Data Hub)]] -> #REF! | S85: =IF([3]!Table14[[#This Row],[Nullable in Table and in Oracle View NULL, NOT NULL]]="No","NOT NULL","NULL")=VLOOKUP(A85,[2]Model!C$2:I$228,6,FALSE) -> #REF! | T85: =VLOOKUP(B85,[2]Table!A$2:F$415,1,FALSE)=[3]!Table14[[#This Row],[Physical Name of Attribute (Name of column in Table) Supplied by DA Team]] -> #REF! | U85: =VLOOKUP(B85,Table!A$2:F$319,2,FALSE)=Table14[[#This Row],[Data type in Oracle VARCHAR2(n), DATE, NUMBER(m,n), TIMETSTAMP(6)]] -> FALSE | V85: =VLOOKUP(B85,Table!A$2:F$231,3,FALSE)=Table14[[#This Row],[Nullable in Table and in Oracle View NULL, NOT NULL]] -> TRUE | W85: =VLOOKUP(B85,Table!A$2:H$228,6,FALSE)=Table14[[#This Row],[Business Definition (To go into comments and into Meta Data Hub)]] -> TRUE | X85: =VLOOKUP((UPPER(SUBSTITUTE(A85," ","_"))),'[2]Consumer View'!A$2:I$329,1,FALSE) -> CASH_POSITION_TYPE_CODE | Y85: COMMON_OWNER | Z85: CASH_POS_TP_DIM | AA85: CASH_POS_TP_CD | AD85: ccal_repl_owner.apa ap left join common_owner.cash_pos_tp_dim cptd ON ap.CASH_POS_TP_ID = cptd.CASH_POS_TP_ID | AH85: N
A86: Cash Position Type Dimension Id | B86: CASH_POS_TP_DIM_ID | D86: NUMBER(38,0) | E86: No | F86: NUMERIC(38,0) | G86: Yes | H86: Surrogate Key for Cash Position Type | J86: Existing | K86: 3 | O86: =VLOOKUP(A86,[1]Model!C$2:J$559,2,FALSE)=B86 -> TRUE | P86: =VLOOKUP(A86,Model!C$2:G$228,5,FALSE)=D86 -> TRUE | Q86: =VLOOKUP(A86,[2]Model!C$2:L$228,8,FALSE) -> 6 | R86: =VLOOKUP(A86,[2]Model!C$2:G$228,3,FALSE)=[3]!Table14[[#This Row],[Business Definition (To go into comments and into Meta Data Hub)]] -> #REF! | S86: =IF([3]!Table14[[#This Row],[Nullable in Table and in Oracle View NULL, NOT NULL]]="No","NOT NULL","NULL")=VLOOKUP(A86,[2]Model!C$2:I$228,6,FALSE) -> #REF! | T86: =VLOOKUP(B86,[2]Table!A$2:F$415,1,FALSE)=[3]!Table14[[#This Row],[Physical Name of Attribute (Name of column in Table) Supplied by DA Team]] -> #REF! | U86: =VLOOKUP(B86,Table!A$2:F$319,2,FALSE)=Table14[[#This Row],[Data type in Oracle VARCHAR2(n), DATE, NUMBER(m,n), TIMETSTAMP(6)]] -> TRUE | V86: =VLOOKUP(B86,Table!A$2:F$231,3,FALSE)=Table14[[#This Row],[Nullable in Table and in Oracle View NULL, NOT NULL]] -> TRUE | W86: =VLOOKUP(B86,Table!A$2:H$228,6,FALSE)=Table14[[#This Row],[Business Definition (To go into comments and into Meta Data Hub)]] -> TRUE | X86: =VLOOKUP((UPPER(SUBSTITUTE(A86," ","_"))),'[2]Consumer View'!A$2:I$329,1,FALSE) -> CASH_POSITION_TYPE_DIMENSION_ID | Y86: COMMON_OWNER | Z86: CASH_POS_TP_DIM | AA86: CASH_POS_TP_DIM_ID | AD86: ccal_repl_owner.apa ap left join common_owner.cash_pos_tp_dim cptd ON ap.CASH_POS_TP_ID = cptd.CASH_POS_TP_ID | AH86: REMOVE (DIM_ID)
A87: Cash Position Type Name | B87: CASH_POS_TP_NM | C87: Cash_Position_Type | D87: VARCHAR2(75) | E87: Yes | F87: character varying(75) | G87: Yes | H87: Identifying how the cash position is treated at the end of the day for purposes of cash segregation and sweeps. e.g., Goldman Sachs Federal Fund - Income, Real Time Cash | J87: Existing | K87: 3 | O87: =VLOOKUP(A87,[1]Model!C$2:J$559,2,FALSE)=B87 -> TRUE | P87: =VLOOKUP(A87,Model!C$2:G$228,5,FALSE)=D87 -> TRUE | Q87: =VLOOKUP(A87,[2]Model!C$2:L$228,8,FALSE) -> 111 | R87: =VLOOKUP(A87,[2]Model!C$2:G$228,3,FALSE)=[3]!Table14[[#This Row],[Business Definition (To go into comments and into Meta Data Hub)]] -> #REF! | S87: =IF([3]!Table14[[#This Row],[Nullable in Table and in Oracle View NULL, NOT NULL]]="No","NOT NULL","NULL")=VLOOKUP(A87,[2]Model!C$2:I$228,6,FALSE) -> #REF! | T87: =VLOOKUP(B87,[2]Table!A$2:F$415,1,FALSE)=[3]!Table14[[#This Row],[Physical Name of Attribute (Name of column in Table) Supplied by DA Team]] -> #REF! | U87: =VLOOKUP(B87,Table!A$2:F$319,2,FALSE)=Table14[[#This Row],[Data type in Oracle VARCHAR2(n), DATE, NUMBER(m,n), TIMETSTAMP(6)]] -> FALSE | V87: =VLOOKUP(B87,Table!A$2:F$231,3,FALSE)=Table14[[#This Row],[Nullable in Table and in Oracle View NULL, NOT NULL]] -> TRUE | W87: =VLOOKUP(B87,Table!A$2:H$228,6,FALSE)=Table14[[#This Row],[Business Definition (To go into comments and into Meta Data Hub)]] -> TRUE | X87: =VLOOKUP((UPPER(SUBSTITUTE(A87," ","_"))),'[2]Consumer View'!A$2:I$329,1,FALSE) -> CASH_POSITION_TYPE_NAME | Y87: COMMON_OWNER | Z87: CASH_POS_TP_DIM | AA87: CASH_POS_TP_NM | AD87: ccal_repl_owner.apa ap left join common_owner.cash_pos_tp_dim cptd ON ap.CASH_POS_TP_ID = cptd.CASH_POS_TP_ID | AH87: N
A88: Cash Position Type Id | B88: CASH_POS_TP_ID | D88: NUMBER(38,0) | E88: Yes | F88: NUMERIC(38,0) | G88: Yes | H88: An Id representing Cash position type | J88: Add | K88: 3 | O88: =VLOOKUP(A88,[1]Model!C$2:J$559,2,FALSE)=B88 -> TRUE | P88: =VLOOKUP(A88,Model!C$2:G$228,5,FALSE)=D88 -> TRUE | Q88: =VLOOKUP(A88,[2]Model!C$2:L$228,8,FALSE) -> 196 | R88: =VLOOKUP(A88,[2]Model!C$2:G$228,3,FALSE)=[3]!Table14[[#This Row],[Business Definition (To go into comments and into Meta Data Hub)]] -> #REF! | S88: =IF([3]!Table14[[#This Row],[Nullable in Table and in Oracle View NULL, NOT NULL]]="No","NOT NULL","NULL")=VLOOKUP(A88,[2]Model!C$2:I$228,6,FALSE) -> #REF! | T88: =VLOOKUP(B88,[2]Table!A$2:F$415,1,FALSE)=[3]!Table14[[#This Row],[Physical Name of Attribute (Name of column in Table) Supplied by DA Team]] -> #REF! | U88: =VLOOKUP(B88,Table!A$2:F$319,2,FALSE)=Table14[[#This Row],[Data type in Oracle VARCHAR2(n), DATE, NUMBER(m,n), TIMETSTAMP(6)]] -> TRUE | V88: =VLOOKUP(B88,Table!A$2:F$231,3,FALSE)=Table14[[#This Row],[Nullable in Table and in Oracle View NULL, NOT NULL]] -> TRUE | W88: =VLOOKUP(B88,Table!A$2:H$228,6,FALSE)=Table14[[#This Row],[Business Definition (To go into comments and into Meta Data Hub)]] -> TRUE | X88: =VLOOKUP((UPPER(SUBSTITUTE(A88," ","_"))),'[2]Consumer View'!A$2:I$329,1,FALSE) -> CASH_POSITION_TYPE_ID | Y88: CCAL_REPL_OWNER | Z88: APA | AA88: CASH_POS_TP_ID | AD88: ccal_repl_owner.txn t join ccal_repl_owner.apa ap ON ap.exec_id = t.txn_id | AH88: N
A89: Cash CCAL Product Id | B89: CASH_PD_ID | C89: Cash_CCAL_Product_Id | D89: NUMBER(38,0) | E89: Yes | F89: NUMERIC(38,0) | G89: Yes | H89: Product Identifier from Cash Asset package | J89: Existing | K89: 3 | O89: =VLOOKUP(A89,[1]Model!C$2:J$559,2,FALSE)=B89 -> TRUE | P89: =VLOOKUP(A89,Model!C$2:G$228,5,FALSE)=D89 -> TRUE | Q89: =VLOOKUP(A89,[2]Model!C$2:L$228,8,FALSE) -> 109 | R89: =VLOOKUP(A89,[2]Model!C$2:G$228,3,FALSE)=[3]!Table14[[#This Row],[Business Definition (To go into comments and into Meta Data Hub)]] -> #REF! | S89: =IF([3]!Table14[[#This Row],[Nullable in Table and in Oracle View NULL, NOT NULL]]="No","NOT NULL","NULL")=VLOOKUP(A89,[2]Model!C$2:I$228,6,FALSE) -> #REF! | T89: =VLOOKUP(B89,[2]Table!A$2:F$415,1,FALSE)=[3]!Table14[[#This Row],[Physical Name of Attribute (Name of column in Table) Supplied by DA Team]] -> #REF! | U89: =VLOOKUP(B89,Table!A$2:F$319,2,FALSE)=Table14[[#This Row],[Data type in Oracle VARCHAR2(n), DATE, NUMBER(m,n), TIMETSTAMP(6)]] -> TRUE | V89: =VLOOKUP(B89,Table!A$2:F$231,3,FALSE)=Table14[[#This Row],[Nullable in Table and in Oracle View NULL, NOT NULL]] -> TRUE | W89: =VLOOKUP(B89,Table!A$2:H$228,6,FALSE)=Table14[[#This Row],[Business Definition (To go into comments and into Meta Data Hub)]] -> TRUE | X89: =VLOOKUP((UPPER(SUBSTITUTE(A89," ","_"))),'[2]Consumer View'!A$2:I$329,1,FALSE) -> #N/A | Y89: CCAL_REPL_OWNER | Z89: APA | AA89: PD_ID | AD89: Use APACSH logic from 'ETL Notes' tab. | AH89: N
A90: Cash Investment Product Dim Id | B90: CASH_PD_DIM_ID | D90: NUMBER(38,0) | E90: No | F90: NUMERIC(38,0) | G90: Yes | H90: Surrogate key for Instrument Product Dim. This field will be populated only if the transaction has a Cash leg. | J90: Existing | K90: 3 | O90: =VLOOKUP(A90,[1]Model!C$2:J$559,2,FALSE)=B90 -> TRUE | P90: =VLOOKUP(A90,Model!C$2:G$228,5,FALSE)=D90 -> TRUE | Q90: =VLOOKUP(A90,[2]Model!C$2:L$228,8,FALSE) -> 2 | R90: =VLOOKUP(A90,[2]Model!C$2:G$228,3,FALSE)=[3]!Table14[[#This Row],[Business Definition (To go into comments and into Meta Data Hub)]] -> #REF! | S90: =IF([3]!Table14[[#This Row],[Nullable in Table and in Oracle View NULL, NOT NULL]]="No","NOT NULL","NULL")=VLOOKUP(A90,[2]Model!C$2:I$228,6,FALSE) -> #REF! | T90: =VLOOKUP(B90,[2]Table!A$2:F$415,1,FALSE)=[3]!Table14[[#This Row],[Physical Name of Attribute (Name of column in Table) Supplied by DA Team]] -> #REF! | U90: =VLOOKUP(B90,Table!A$2:F$319,2,FALSE)=Table14[[#This Row],[Data type in Oracle VARCHAR2(n), DATE, NUMBER(m,n), TIMETSTAMP(6)]] -> TRUE | V90: =VLOOKUP(B90,Table!A$2:F$231,3,FALSE)=Table14[[#This Row],[Nullable in Table and in Oracle View NULL, NOT NULL]] -> TRUE | W90: =VLOOKUP(B90,Table!A$2:H$228,6,FALSE)=Table14[[#This Row],[Business Definition (To go into comments and into Meta Data Hub)]] -> FALSE | X90: =VLOOKUP((UPPER(SUBSTITUTE(A90," ","_"))),'[2]Consumer View'!A$2:I$329,1,FALSE) -> #N/A | Y90: CIRD_OWNER | Z90: IMT_PD_DIM | AA90: IMT_PD_DIM_ID | AD90: Use APACSH logic from 'ETL Notes' tab and below logic. ccal_repl_owner.txn t join ccal_repl_owner.apa ap ON ap.exec_id = t.txn_id LEFT join cird_owner.imt_pd_dim ipd ON ipd.CCAL_PD_ID = ap.PD_ID and ipd.eff_dt <= t.td and ipd.end_dt > t.td | AE90: [9/6/24]: Reflected the change to use TXN.TD from Product Backlog Item 1912566: Change join condition and update data types for Activity | AH90: REMOVE (DIM_ID)
A91: Cash Source Sequence Number | B91: CASH_SRC_SEQ_NUM | C91: Cash_Source_Sequence_Number | D91: NUMBER(38,0) | E91: Yes | F91: NUMERIC(38,0) | G91: Yes | H91: Sequence Number assigned by source system. This field will be populated only if the transaction has a Cash leg. | J91: Update | K91: 3 | O91: =VLOOKUP(A91,[1]Model!C$2:J$559,2,FALSE)=B91 -> TRUE | P91: =VLOOKUP(A91,Model!C$2:G$228,5,FALSE)=D91 -> TRUE | Q91: =VLOOKUP(A91,[2]Model!C$2:L$228,8,FALSE) -> 45 | R91: =VLOOKUP(A91,[2]Model!C$2:G$228,3,FALSE)=[3]!Table14[[#This Row],[Business Definition (To go into comments and into Meta Data Hub)]] -> #REF! | S91: =IF([3]!Table14[[#This Row],[Nullable in Table and in Oracle View NULL, NOT NULL]]="No","NOT NULL","NULL")=VLOOKUP(A91,[2]Model!C$2:I$228,6,FALSE) -> #REF! | T91: =VLOOKUP(B91,[2]Table!A$2:F$415,1,FALSE)=[3]!Table14[[#This Row],[Physical Name of Attribute (Name of column in Table) Supplied by DA Team]] -> #REF! | U91: =VLOOKUP(B91,Table!A$2:F$319,2,FALSE)=Table14[[#This Row],[Data type in Oracle VARCHAR2(n), DATE, NUMBER(m,n), TIMETSTAMP(6)]] -> TRUE | V91: =VLOOKUP(B91,Table!A$2:F$231,3,FALSE)=Table14[[#This Row],[Nullable in Table and in Oracle View NULL, NOT NULL]] -> TRUE | W91: =VLOOKUP(B91,Table!A$2:H$228,6,FALSE)=Table14[[#This Row],[Business Definition (To go into comments and into Meta Data Hub)]] -> FALSE | X91: =VLOOKUP((UPPER(SUBSTITUTE(A91," ","_"))),'[2]Consumer View'!A$2:I$329,1,FALSE) -> CASH_SOURCE_SEQUENCE_NUMBER | Y91: CCAL_REPL_OWNER | Z91: APA | AA91: SRC_SEQ_NUM | AD91: Use APACSH logic from 'ETL Notes' tab. | AH91: N
A92: Cash System Base Currency Amount | B92: CASH_SBC_AMT | C92: USD_Cash_Transaction_Amount | D92: NUMBER(38,6) | E92: Yes | F92: NUMERIC(38,6) | G92: Yes | H92: Transaction Amount expressed in System Base Currency. This field will be populated only if the transaction has a Cash leg. | J92: Update | K92: 3 | O92: =VLOOKUP(A92,[1]Model!C$2:J$559,2,FALSE)=B92 -> TRUE | P92: =VLOOKUP(A92,Model!C$2:G$228,5,FALSE)=D92 -> TRUE | Q92: =VLOOKUP(A92,[2]Model!C$2:L$228,8,FALSE) -> 40 | R92: =VLOOKUP(A92,[2]Model!C$2:G$228,3,FALSE)=[3]!Table14[[#This Row],[Business Definition (To go into comments and into Meta Data Hub)]] -> #REF! | S92: =IF([3]!Table14[[#This Row],[Nullable in Table and in Oracle View NULL, NOT NULL]]="No","NOT NULL","NULL")=VLOOKUP(A92,[2]Model!C$2:I$228,6,FALSE) -> #REF! | T92: =VLOOKUP(B92,[2]Table!A$2:F$415,1,FALSE)=[3]!Table14[[#This Row],[Physical Name of Attribute (Name of column in Table) Supplied by DA Team]] -> #REF! | U92: =VLOOKUP(B92,Table!A$2:F$319,2,FALSE)=Table14[[#This Row],[Data type in Oracle VARCHAR2(n), DATE, NUMBER(m,n), TIMETSTAMP(6)]] -> TRUE | V92: =VLOOKUP(B92,Table!A$2:F$231,3,FALSE)=Table14[[#This Row],[Nullable in Table and in Oracle View NULL, NOT NULL]] -> TRUE | W92: =VLOOKUP(B92,Table!A$2:H$228,6,FALSE)=Table14[[#This Row],[Business Definition (To go into comments and into Meta Data Hub)]] -> FALSE | X92: =VLOOKUP((UPPER(SUBSTITUTE(A92," ","_"))),'[2]Consumer View'!A$2:I$329,1,FALSE) -> CASH_SYSTEM_BASE_CURRENCY_AMOUNT | Y92: CCAL_REPL_OWNER | Z92: APA | AA92: STM_BASE_CCY_AMT | AD92: Use APACSH logic from 'ETL Notes' tab. For a Transaction, If 2 APACSH records exists If (one record is 'APACSH04' & other is 'APACSH11') then skip 'APACSH04' record and load 'APACSH11' but use the values to calculate aggregated value from APA.TXN_AMT fields from 'APACSH04' and 'APACSH11' and store it in Cash Transaction Amount and Cash System base currency amount else exception entire transaction | AH92: N
A93: Cash Transaction Amount | B93: CASH_TXN_AMT | C93: Cash_Transaction_Amount | D93: NUMBER(38,6) | E93: Yes | F93: NUMERIC(38,6) | G93: Yes | H93: Transaction amount applicable to the Asset package in transaction currency. This field will be populated only if the transaction has a Cash leg. | J93: Update | K93: 3 | O93: =VLOOKUP(A93,[1]Model!C$2:J$559,2,FALSE)=B93 -> TRUE | P93: =VLOOKUP(A93,Model!C$2:G$228,5,FALSE)=D93 -> TRUE | Q93: =VLOOKUP(A93,[2]Model!C$2:L$228,8,FALSE) -> 30 | R93: =VLOOKUP(A93,[2]Model!C$2:G$228,3,FALSE)=[3]!Table14[[#This Row],[Business Definition (To go into comments and into Meta Data Hub)]] -> #REF! | S93: =IF([3]!Table14[[#This Row],[Nullable in Table and in Oracle View NULL, NOT NULL]]="No","NOT NULL","NULL")=VLOOKUP(A93,[2]Model!C$2:I$228,6,FALSE) -> #REF! | T93: =VLOOKUP(B93,[2]Table!A$2:F$415,1,FALSE)=[3]!Table14[[#This Row],[Physical Name of Attribute (Name of column in Table) Supplied by DA Team]] -> #REF! | U93: =VLOOKUP(B93,Table!A$2:F$319,2,FALSE)=Table14[[#This Row],[Data type in Oracle VARCHAR2(n), DATE, NUMBER(m,n), TIMETSTAMP(6)]] -> TRUE | V93: =VLOOKUP(B93,Table!A$2:F$231,3,FALSE)=Table14[[#This Row],[Nullable in Table and in Oracle View NULL, NOT NULL]] -> TRUE | W93: =VLOOKUP(B93,Table!A$2:H$228,6,FALSE)=Table14[[#This Row],[Business Definition (To go into comments and into Meta Data Hub)]] -> FALSE | X93: =VLOOKUP((UPPER(SUBSTITUTE(A93," ","_"))),'[2]Consumer View'!A$2:I$329,1,FALSE) -> CASH_TRANSACTION_AMOUNT | Y93: CCAL_REPL_OWNER | Z93: APA | AA93: TXN_AMT | AD93: Use APACSH logic from 'ETL Notes' tab. For a Transaction, If 2 APACSH records exists If (one record is 'APACSH04' & other is 'APACSH11') then skip 'APACSH04' record and load 'APACSH11' but use the values to calculate aggregated value from APA.TXN_AMT fields from 'APACSH04' and 'APACSH11' and store it in Cash Transaction Amount and Cash System base currency amount else exception entire transaction | AH93: N
A94: Client Friendly Description | B94: CLNT_FRIENDLY_DSC | C94: Activity_Client_Friendly_Description | D94: VARCHAR2(256) | E94: Yes | F94: character varying(256) | G94: Yes | H94: Client friendly description of the Asset package. | J94: Existing | K94: 3 | O94: =VLOOKUP(A94,[1]Model!C$2:J$559,2,FALSE)=B94 -> TRUE | P94: =VLOOKUP(A94,Model!C$2:G$228,5,FALSE)=D94 -> TRUE | Q94: =VLOOKUP(A94,[2]Model!C$2:L$228,8,FALSE) -> 100 | R94: =VLOOKUP(A94,[2]Model!C$2:G$228,3,FALSE)=[3]!Table14[[#This Row],[Business Definition (To go into comments and into Meta Data Hub)]] -> #REF! | S94: =IF([3]!Table14[[#This Row],[Nullable in Table and in Oracle View NULL, NOT NULL]]="No","NOT NULL","NULL")=VLOOKUP(A94,[2]Model!C$2:I$228,6,FALSE) -> #REF! | T94: =VLOOKUP(B94,[2]Table!A$2:F$415,1,FALSE)=[3]!Table14[[#This Row],[Physical Name of Attribute (Name of column in Table) Supplied by DA Team]] -> #REF! | U94: =VLOOKUP(B94,Table!A$2:F$319,2,FALSE)=Table14[[#This Row],[Data type in Oracle VARCHAR2(n), DATE, NUMBER(m,n), TIMETSTAMP(6)]] -> FALSE | V94: =VLOOKUP(B94,Table!A$2:F$231,3,FALSE)=Table14[[#This Row],[Nullable in Table and in Oracle View NULL, NOT NULL]] -> TRUE | W94: =VLOOKUP(B94,Table!A$2:H$228,6,FALSE)=Table14[[#This Row],[Business Definition (To go into comments and into Meta Data Hub)]] -> TRUE | X94: =VLOOKUP((UPPER(SUBSTITUTE(A94," ","_"))),'[2]Consumer View'!A$2:I$329,1,FALSE) -> CLIENT_FRIENDLY_DESCRIPTION | Y94: CCAL_REPL_OWNER | Z94: APA | AA94: CLNT_FRIENDLY_DESC | AD94: ccal_repl_owner.txn t join ccal_repl_owner.apa ap ON ap.exec_id = t.txn_id | AH94: N
A95: Create Datetime | B95: CRT_DTM | C95: Create_Datetime | D95: DATE | E95: No | F95: timestamp without time zone | G95: Yes | H95: The exact date when a record was first created. | J95: Existing | K95: 3 | O95: =VLOOKUP(A95,[1]Model!C$2:J$559,2,FALSE)=B95 -> TRUE | P95: =VLOOKUP(A95,Model!C$2:G$228,5,FALSE)=D95 -> TRUE | Q95: =VLOOKUP(A95,[2]Model!C$2:L$228,8,FALSE) -> 91 | R95: =VLOOKUP(A95,[2]Model!C$2:G$228,3,FALSE)=[3]!Table14[[#This Row],[Business Definition (To go into comments and into Meta Data Hub)]] -> #REF! | S95: =IF([3]!Table14[[#This Row],[Nullable in Table and in Oracle View NULL, NOT NULL]]="No","NOT NULL","NULL")=VLOOKUP(A95,[2]Model!C$2:I$228,6,FALSE) -> #REF! | T95: =VLOOKUP(B95,[2]Table!A$2:F$415,1,FALSE)=[3]!Table14[[#This Row],[Physical Name of Attribute (Name of column in Table) Supplied by DA Team]] -> #REF! | U95: =VLOOKUP(B95,Table!A$2:F$319,2,FALSE)=Table14[[#This Row],[Data type in Oracle VARCHAR2(n), DATE, NUMBER(m,n), TIMETSTAMP(6)]] -> TRUE | V95: =VLOOKUP(B95,Table!A$2:F$231,3,FALSE)=Table14[[#This Row],[Nullable in Table and in Oracle View NULL, NOT NULL]] -> TRUE | W95: =VLOOKUP(B95,Table!A$2:H$228,6,FALSE)=Table14[[#This Row],[Business Definition (To go into comments and into Meta Data Hub)]] -> TRUE | X95: =VLOOKUP((UPPER(SUBSTITUTE(A95," ","_"))),'[2]Consumer View'!A$2:I$329,1,FALSE) -> CREATE_DATETIME | Y95: CCAL_REPL_OWNER | Z95: TXN | AA95: CRT_DTM | AH95: N
A96: Create User Name | B96: CRT_USR_NM | C96: Create_User_name | D96: VARCHAR2(256) | E96: No | F96: character varying(256) | G96: Yes | H96: The name that represents the user who created an occurrence of a record. | J96: Update | K96: 3 | O96: =VLOOKUP(A96,[1]Model!C$2:J$559,2,FALSE)=B96 -> TRUE | P96: =VLOOKUP(A96,Model!C$2:G$228,5,FALSE)=D96 -> TRUE | Q96: =VLOOKUP(A96,[2]Model!C$2:L$228,8,FALSE) -> 90 | R96: =VLOOKUP(A96,[2]Model!C$2:G$228,3,FALSE)=[3]!Table14[[#This Row],[Business Definition (To go into comments and into Meta Data Hub)]] -> #REF! | S96: =IF([3]!Table14[[#This Row],[Nullable in Table and in Oracle View NULL, NOT NULL]]="No","NOT NULL","NULL")=VLOOKUP(A96,[2]Model!C$2:I$228,6,FALSE) -> #REF! | T96: =VLOOKUP(B96,[2]Table!A$2:F$415,1,FALSE)=[3]!Table14[[#This Row],[Physical Name of Attribute (Name of column in Table) Supplied by DA Team]] -> #REF! | U96: =VLOOKUP(B96,Table!A$2:F$319,2,FALSE)=Table14[[#This Row],[Data type in Oracle VARCHAR2(n), DATE, NUMBER(m,n), TIMETSTAMP(6)]] -> FALSE | V96: =VLOOKUP(B96,Table!A$2:F$231,3,FALSE)=Table14[[#This Row],[Nullable in Table and in Oracle View NULL, NOT NULL]] -> TRUE | W96: =VLOOKUP(B96,Table!A$2:H$228,6,FALSE)=Table14[[#This Row],[Business Definition (To go into comments and into Meta Data Hub)]] -> TRUE | X96: =VLOOKUP((UPPER(SUBSTITUTE(A96," ","_"))),'[2]Consumer View'!A$2:I$329,1,FALSE) -> CREATE_USER_NAME | Y96: CCAL_REPL_OWNER | Z96: TXN | AA96: CRT_USR_NM | AH96: N
A97: Currency Code | B97: CCY_CD | C97: Transaction_Currency_Code | D97: VARCHAR2(3) | E97: Yes | F97: character varying(3) | G97: Yes | H97: ISO Currency Code for transaction amount | J97: Existing | K97: 3 | O97: =VLOOKUP(A97,[1]Model!C$2:J$559,2,FALSE)=B97 -> TRUE | P97: =VLOOKUP(A97,Model!C$2:G$228,5,FALSE)=D97 -> TRUE | Q97: =VLOOKUP(A97,[2]Model!C$2:L$228,8,FALSE) -> 112 | R97: =VLOOKUP(A97,[2]Model!C$2:G$228,3,FALSE)=[3]!Table14[[#This Row],[Business Definition (To go into comments and into Meta Data Hub)]] -> #REF! | S97: =IF([3]!Table14[[#This Row],[Nullable in Table and in Oracle View NULL, NOT NULL]]="No","NOT NULL","NULL")=VLOOKUP(A97,[2]Model!C$2:I$228,6,FALSE) -> #REF! | T97: =VLOOKUP(B97,[2]Table!A$2:F$415,1,FALSE)=[3]!Table14[[#This Row],[Physical Name of Attribute (Name of column in Table) Supplied by DA Team]] -> #REF! | U97: =VLOOKUP(B97,Table!A$2:F$319,2,FALSE)=Table14[[#This Row],[Data type in Oracle VARCHAR2(n), DATE, NUMBER(m,n), TIMETSTAMP(6)]] -> FALSE | V97: =VLOOKUP(B97,Table!A$2:F$231,3,FALSE)=Table14[[#This Row],[Nullable in Table and in Oracle View NULL, NOT NULL]] -> TRUE | W97: =VLOOKUP(B97,Table!A$2:H$228,6,FALSE)=Table14[[#This Row],[Business Definition (To go into comments and into Meta Data Hub)]] -> TRUE | X97: =VLOOKUP((UPPER(SUBSTITUTE(A97," ","_"))),'[2]Consumer View'!A$2:I$329,1,FALSE) -> CURRENCY_CODE | Y97: CCAL_REPL_OWNER | Z97: APA | AA97: txn_iso_ccy_code | AH97: N (Bug 2258384)
A98: Currency Dimension Id | B98: CCY_DIM_ID | D98: NUMBER(38,0) | E98: Yes | F98: NUMERIC(38,0) | G98: Yes | H98: Surrogate key for Currency dimension based on Currency Code. | J98: Existing | K98: 3 | O98: =VLOOKUP(A98,[1]Model!C$2:J$559,2,FALSE)=B98 -> TRUE | P98: =VLOOKUP(A98,Model!C$2:G$228,5,FALSE)=D98 -> TRUE | Q98: =VLOOKUP(A98,[2]Model!C$2:L$228,8,FALSE) -> 18 | R98: =VLOOKUP(A98,[2]Model!C$2:G$228,3,FALSE)=[3]!Table14[[#This Row],[Business Definition (To go into comments and into Meta Data Hub)]] -> #REF! | S98: =IF([3]!Table14[[#This Row],[Nullable in Table and in Oracle View NULL, NOT NULL]]="No","NOT NULL","NULL")=VLOOKUP(A98,[2]Model!C$2:I$228,6,FALSE) -> #REF! | T98: =VLOOKUP(B98,[2]Table!A$2:F$415,1,FALSE)=[3]!Table14[[#This Row],[Physical Name of Attribute (Name of column in Table) Supplied by DA Team]] -> #REF! | U98: =VLOOKUP(B98,Table!A$2:F$319,2,FALSE)=Table14[[#This Row],[Data type in Oracle VARCHAR2(n), DATE, NUMBER(m,n), TIMETSTAMP(6)]] -> TRUE | V98: =VLOOKUP(B98,Table!A$2:F$231,3,FALSE)=Table14[[#This Row],[Nullable in Table and in Oracle View NULL, NOT NULL]] -> TRUE | W98: =VLOOKUP(B98,Table!A$2:H$228,6,FALSE)=Table14[[#This Row],[Business Definition (To go into comments and into Meta Data Hub)]] -> TRUE | X98: =VLOOKUP((UPPER(SUBSTITUTE(A98," ","_"))),'[2]Consumer View'!A$2:I$329,1,FALSE) -> CURRENCY_DIMENSION_ID | Y98: CIRD_OWNER | Z98: CCY_DIM | AA98: CCY_DIM_ID | AD98: ccal_repl_owner.txn t join ccal_repl_owner.apa ap ON ap.exec_id = t.txn_id left join cird_owner.ccy_dim cd ON cd.ccy_cd = ap.txn_iso_ccy_code | AH98: REMOVE (DIM_ID)
A99: Department Of Labor Indicator Code | B99: DOL_IND_CD | C99: Transaction_Department_of_Labor_Eligible_Account_Code | D99: VARCHAR2(20) | E99: Yes | F99: character varying(20) | G99: Yes | H99: A code that identifies whether or not an account is deemed eligible in accordance with the DOL fiduciary rule. | J99: Existing | K99: 3 | O99: =VLOOKUP(A99,[1]Model!C$2:J$559,2,FALSE)=B99 -> TRUE | P99: =VLOOKUP(A99,Model!C$2:G$228,5,FALSE)=D99 -> TRUE | Q99: =VLOOKUP(A99,[2]Model!C$2:L$228,8,FALSE) -> 113 | R99: =VLOOKUP(A99,[2]Model!C$2:G$228,3,FALSE)=[3]!Table14[[#This Row],[Business Definition (To go into comments and into Meta Data Hub)]] -> #REF! | S99: =IF([3]!Table14[[#This Row],[Nullable in Table and in Oracle View NULL, NOT NULL]]="No","NOT NULL","NULL")=VLOOKUP(A99,[2]Model!C$2:I$228,6,FALSE) -> #REF! | T99: =VLOOKUP(B99,[2]Table!A$2:F$415,1,FALSE)=[3]!Table14[[#This Row],[Physical Name of Attribute (Name of column in Table) Supplied by DA Team]] -> #REF! | U99: =VLOOKUP(B99,Table!A$2:F$319,2,FALSE)=Table14[[#This Row],[Data type in Oracle VARCHAR2(n), DATE, NUMBER(m,n), TIMETSTAMP(6)]] -> FALSE | V99: =VLOOKUP(B99,Table!A$2:F$231,3,FALSE)=Table14[[#This Row],[Nullable in Table and in Oracle View NULL, NOT NULL]] -> TRUE | W99: =VLOOKUP(B99,Table!A$2:H$228,6,FALSE)=Table14[[#This Row],[Business Definition (To go into comments and into Meta Data Hub)]] -> TRUE | X99: =VLOOKUP((UPPER(SUBSTITUTE(A99," ","_"))),'[2]Consumer View'!A$2:I$329,1,FALSE) -> DEPARTMENT_OF_LABOR_INDICATOR_CODE | Y99: CCAL_REPL_OWNER | Z99: CL_VAL | AA99: CL_VAL_CODE | AD99: ccal_repl_owner.txn t left join ccal_repl_owner.cl_val cv ON t.dol_ind_id = cv.cl_val_id and cv.cl_scm_id = '35' | AE99: select cv.cl_val_code from ccal_repl_owner.txn t, ccal_repl_owner.cl_val cv where t.dol_ind_id = cv.cl_val_id and t.txn_id = ap.exec_id | AH99: N
A100: Department Of Labor Indicator Id | B100: DOL_IND_ID | D100: NUMBER(38,0) | E100: Yes | F100: NUMERIC(38,0) | G100: Yes | H100: Identifier of whether or not an account is deemed eligible in accordance with the DOL fiduciary rule. | J100: Existing | K100: 3 | O100: =VLOOKUP(A100,[1]Model!C$2:J$559,2,FALSE)=B100 -> TRUE | P100: =VLOOKUP(A100,Model!C$2:G$228,5,FALSE)=D100 -> TRUE | Q100: =VLOOKUP(A100,[2]Model!C$2:L$228,8,FALSE) -> 114 | R100: =VLOOKUP(A100,[2]Model!C$2:G$228,3,FALSE)=[3]!Table14[[#This Row],[Business Definition (To go into comments and into Meta Data Hub)]] -> #REF! | S100: =IF([3]!Table14[[#This Row],[Nullable in Table and in Oracle View NULL, NOT NULL]]="No","NOT NULL","NULL")=VLOOKUP(A100,[2]Model!C$2:I$228,6,FALSE) -> #REF! | T100: =VLOOKUP(B100,[2]Table!A$2:F$415,1,FALSE)=[3]!Table14[[#This Row],[Physical Name of Attribute (Name of column in Table) Supplied by DA Team]] -> #REF! | U100: =VLOOKUP(B100,Table!A$2:F$319,2,FALSE)=Table14[[#This Row],[Data type in Oracle VARCHAR2(n), DATE, NUMBER(m,n), TIMETSTAMP(6)]] -> TRUE | V100: =VLOOKUP(B100,Table!A$2:F$231,3,FALSE)=Table14[[#This Row],[Nullable in Table and in Oracle View NULL, NOT NULL]] -> TRUE | W100: =VLOOKUP(B100,Table!A$2:H$228,6,FALSE)=Table14[[#This Row],[Business Definition (To go into comments and into Meta Data Hub)]] -> TRUE | X100: =VLOOKUP((UPPER(SUBSTITUTE(A100," ","_"))),'[2]Consumer View'!A$2:I$329,1,FALSE) -> DEPARTMENT_OF_LABOR_INDICATOR_ID | Y100: CCAL_REPL_OWNER | Z100: TXN | AA100: DOL_IND_ID | AH100: N
...

Sheet Table-View
A1: 1. View Name - | B1: ACTIVITY_FACT_V | I1: Please read review comments on Table Functional Description, Data Type and Business Definition
A2: 2. Table Name - | B2: AVY_FACT
A3: 3. View Schema Name - | B3: SSDS_DAL_OWNER
A4: 4. Table Schema Name - | B4: TRANSACTIONS_OWNER
A5: 5. Table Functional Description - | B5: This table consists of trades and transactions (Cash and Securities) to meet investment objective of a client. | I5: BA Responsbility | J5: BA Responsbility | K5: BA Responsbility | L5: DA Responsibility
A6: 6. Filter Criteria - | B6: Transaction Trade Date >= DATE '2017-10-01'. Refer to [ETL Notes] tab for more filters
A7: 7. Grain (Logical primary key) - | B7: Refer to [ETL Notes] tab
A8: 8. Semantic View Schema Name - | B8: ENTERPRISE_SEMANTIC_OWNER
A9: 9. Semantic View Name - | B9: Activity_Fact_cross_domain_V
A10: Note:
A11: Lighthouse Target | Y11: Source | AD11: Transformation
A12: Logical Name of Attribute (Name of column in View without underscores) | B12: Physical Name of Attribute (Name of column in Table) Supplied by DA Team | C12: Semantic Column Name | D12: Data type in Oracle VARCHAR2(n), DATE, NUMBER(m,n), TIMETSTAMP(6) | E12: Nullable in Table and in Oracle View NULL, NOT NULL | F12: Data type in Redshift | G12: Nullable in RedshiftTable | H12: Business Definition (To go into comments and into Meta Data Hub) | I12: Sample data values | J12: Action on Attribute Add,Update,Remove, Blank | K12: Action Version | L12: Table PBI Number | M12: List Functional PBI | N12: Include in View. Populated with N only when not to be shown in the view. | O12: Is on Data Model DA responsibility | P12: Model Data Type match TRUE/FALSE DA Responsibilty | Q12: Column2 | R12: Model Defs. Match | S12: Model Nullable Match | T12: On Table | U12: table data type | V12: table Nullable | W12: table defintions | X12: On View | Y12: Source Schema | Z12: Source Table | AA12: Source Attribute Name | AB12: Data Type | AC12: Nullable? | AD12: Transformation /Business Rules /Join Conditions | AE12: Notes / Comments | AF12: Indicator | AG12: Domain | AH12: Cross-Domain
A13: SHADOW Transaction Type Code | B13: SHDW_TXN_TP_CD | C13: Shadow_Transaction_Type_Code | D13: VARCHAR2(50) | E13: Yes | F13: character varying(50) | G13: Yes | H13: Possible values: ORG, OLD, NEW, REV, REP. | I13: OLD ORG REP REV NEW | J13: Add | K13: 3 | O13: =VLOOKUP(A13,[1]Model!C$2:J$559,2,FALSE)=B13 -> TRUE | P13: =VLOOKUP(A13,Model!C$2:G$228,5,FALSE)=D13 -> #N/A | Q13: =VLOOKUP(A13,[2]Model!C$2:L$228,8,FALSE) -> 179 | R13: =VLOOKUP(A13,[2]Model!C$2:G$228,3,FALSE)=[3]!Table14[[#This Row],[Business Definition (To go into comments and into Meta Data Hub)]] -> #REF! | S13: =IF([3]!Table14[[#This Row],[Nullable in Table and in Oracle View NULL, NOT NULL]]="No","NOT NULL","NULL")=VLOOKUP(A13,[2]Model!C$2:I$228,6,FALSE) -> #REF! | T13: =VLOOKUP(B13,[2]Table!A$2:F$415,1,FALSE)=[3]!Table14[[#This Row],[Physical Name of Attribute (Name of column in Table) Supplied by DA Team]] -> #REF! | U13: =VLOOKUP(B13,Table!A$2:F$319,2,FALSE)=Table1[[#This Row],[Data type in Oracle VARCHAR2(n), DATE, NUMBER(m,n), TIMETSTAMP(6)]] -> FALSE | V13: =VLOOKUP(B13,Table!A$2:F$231,3,FALSE)=Table1[[#This Row],[Nullable in Table and in Oracle View NULL, NOT NULL]] -> TRUE | W13: =VLOOKUP(B13,Table!A$2:H$228,6,FALSE)=Table1[[#This Row],[Business Definition (To go into comments and into Meta Data Hub)]] -> TRUE | X13: =VLOOKUP((UPPER(SUBSTITUTE(A13," ","_"))),'[2]Consumer View'!A$2:I$329,1,FALSE) -> SHADOW_TRANSACTION_TYPE_CODE | Y13: CCAL_REPL_OWNER | Z13: TXN | AA13: SRC_TXN_TP | AH13: N
A14: SHADOW Transaction Type Name | B14: SHDW_TXN_TP_NM | C14: Shadow_Transaction_Type | D14: VARCHAR2(50) | E14: Yes | F14: character varying(50) | G14: Yes | H14: Name of the Shadow Transaction Type Code. | J14: Add | K14: 3 | O14: =VLOOKUP(A14,[1]Model!C$2:J$559,2,FALSE)=B14 -> TRUE | P14: =VLOOKUP(A14,Model!C$2:G$228,5,FALSE)=D14 -> #N/A | Q14: =VLOOKUP(A14,[2]Model!C$2:L$228,8,FALSE) -> 177 | R14: =VLOOKUP(A14,[2]Model!C$2:G$228,3,FALSE)=[3]!Table14[[#This Row],[Business Definition (To go into comments and into Meta Data Hub)]] -> #REF! | S14: =IF([3]!Table14[[#This Row],[Nullable in Table and in Oracle View NULL, NOT NULL]]="No","NOT NULL","NULL")=VLOOKUP(A14,[2]Model!C$2:I$228,6,FALSE) -> #REF! | T14: =VLOOKUP(B14,[2]Table!A$2:F$415,1,FALSE)=[3]!Table14[[#This Row],[Physical Name of Attribute (Name of column in Table) Supplied by DA Team]] -> #REF! | U14: =VLOOKUP(B14,Table!A$2:F$319,2,FALSE)=Table1[[#This Row],[Data type in Oracle VARCHAR2(n), DATE, NUMBER(m,n), TIMETSTAMP(6)]] -> FALSE | V14: =VLOOKUP(B14,Table!A$2:F$231,3,FALSE)=Table1[[#This Row],[Nullable in Table and in Oracle View NULL, NOT NULL]] -> TRUE | W14: =VLOOKUP(B14,Table!A$2:H$228,6,FALSE)=Table1[[#This Row],[Business Definition (To go into comments and into Meta Data Hub)]] -> TRUE | X14: =VLOOKUP((UPPER(SUBSTITUTE(A14," ","_"))),'[2]Consumer View'!A$2:I$329,1,FALSE) -> SHADOW_TRANSACTION_TYPE_NAME | Y14: CCAL_REPL_OWNER | Z14: SHDW_TXN_TP | AA14: SRC_TXN_TP_NM | AD14: Look up using TXN.SRC_TXN_TP=SHDW_TXN_TP.SRC_TXN_TP | AH14: N
A15: IMPACT Source Action Code | B15: IMP_SRC_ACTN_CD | C15: IMPACT_Source_Action_Code | D15: VARCHAR2(1) | E15: Yes | F15: character varying(1) | G15: Yes | H15: Code representing Action Type in IMPACT source system | I15: M C I F A P N R Y S K Q U V T | J15: Add | K15: 3 | O15: =VLOOKUP(A15,[1]Model!C$2:J$559,2,FALSE)=B15 -> TRUE | P15: =VLOOKUP(A15,Model!C$2:G$228,5,FALSE)=D15 -> TRUE | Q15: =VLOOKUP(A15,[2]Model!C$2:L$228,8,FALSE) -> 181 | R15: =VLOOKUP(A15,[2]Model!C$2:G$228,3,FALSE)=[3]!Table14[[#This Row],[Business Definition (To go into comments and into Meta Data Hub)]] -> #REF! | S15: =IF([3]!Table14[[#This Row],[Nullable in Table and in Oracle View NULL, NOT NULL]]="No","NOT NULL","NULL")=VLOOKUP(A15,[2]Model!C$2:I$228,6,FALSE) -> #REF! | T15: =VLOOKUP(B15,[2]Table!A$2:F$415,1,FALSE)=[3]!Table14[[#This Row],[Physical Name of Attribute (Name of column in Table) Supplied by DA Team]] -> #REF! | U15: =VLOOKUP(B15,Table!A$2:F$319,2,FALSE)=Table1[[#This Row],[Data type in Oracle VARCHAR2(n), DATE, NUMBER(m,n), TIMETSTAMP(6)]] -> FALSE | V15: =VLOOKUP(B15,Table!A$2:F$231,3,FALSE)=Table1[[#This Row],[Nullable in Table and in Oracle View NULL, NOT NULL]] -> TRUE | W15: =VLOOKUP(B15,Table!A$2:H$228,6,FALSE)=Table1[[#This Row],[Business Definition (To go into comments and into Meta Data Hub)]] -> TRUE | X15: =VLOOKUP((UPPER(SUBSTITUTE(A15," ","_"))),'[2]Consumer View'!A$2:I$329,1,FALSE) -> IMPACT_SOURCE_ACTION_CODE | Y15: CCAL_REPL_OWNER | Z15: TXN | AA15: SRC_ACTN_CODE | AH15: N
A16: IMPACT Source Action Name | B16: IMP_SRC_ACTN_NM | C16: IMPACT_Source_Action | D16: VARCHAR2(100) | E16: Yes | F16: character varying(100) | G16: Yes | H16: Name representing Action Type in IMPACT source system | I16: 1 Security offering document is changed A Amend B Blind Broker Fail C Cancel D Trade Settled F Pool Factor Change I Insert K Failed Trade L Trade Canceled (was matched) M Trade Matched (was unmatched) N Trade Settled O Failed obligation in Net P Trade Settled Q Trade Revision R Rate Revision S Trade Settled T Failed Trade U Trade Un-Netted V DK W Trade Revision X Trade Unmatched (was matched) Y Trade Settled | J16: Add | K16: 3 | O16: =VLOOKUP(A16,[1]Model!C$2:J$559,2,FALSE)=B16 -> TRUE | P16: =VLOOKUP(A16,Model!C$2:G$228,5,FALSE)=D16 -> TRUE | Q16: =VLOOKUP(A16,[2]Model!C$2:L$228,8,FALSE) -> 183 | R16: =VLOOKUP(A16,[2]Model!C$2:G$228,3,FALSE)=[3]!Table14[[#This Row],[Business Definition (To go into comments and into Meta Data Hub)]] -> #REF! | S16: =IF([3]!Table14[[#This Row],[Nullable in Table and in Oracle View NULL, NOT NULL]]="No","NOT NULL","NULL")=VLOOKUP(A16,[2]Model!C$2:I$228,6,FALSE) -> #REF! | T16: =VLOOKUP(B16,[2]Table!A$2:F$415,1,FALSE)=[3]!Table14[[#This Row],[Physical Name of Attribute (Name of column in Table) Supplied by DA Team]] -> #REF! | U16: =VLOOKUP(B16,Table!A$2:F$319,2,FALSE)=Table1[[#This Row],[Data type in Oracle VARCHAR2(n), DATE, NUMBER(m,n), TIMETSTAMP(6)]] -> FALSE | V16: =VLOOKUP(B16,Table!A$2:F$231,3,FALSE)=Table1[[#This Row],[Nullable in Table and in Oracle View NULL, NOT NULL]] -> TRUE | W16: =VLOOKUP(B16,Table!A$2:H$228,6,FALSE)=Table1[[#This Row],[Business Definition (To go into comments and into Meta Data Hub)]] -> TRUE | X16: =VLOOKUP((UPPER(SUBSTITUTE(A16," ","_"))),'[2]Consumer View'!A$2:I$329,1,FALSE) -> IMPACT_SOURCE_ACTION_NAME | Y16: REFERENCE_REPL_OWNER | Z16: IMPCT_ACTION_LKU | AA16: desc_text | AD16: ccal_repl_owner.txn t left join ccal_repl_owner.impct_action_lku lk ON t.src_actn_code = impct_action_lku.action_code | AE16: Note to Dev team: IMPCT_ACTION_LKU table exists only in CDS DB but not available in SSDS/Lighthouse DB. [6/3/24]: Modified target data type for Oracle and Redshift. PBI 1912566 | AH16: N
A17: SIS Detailed Events Id | B17: SIS_DLTD_EV_ID | D17: NUMBER(38,0) | E17: Yes | F17: numeric (38,0) | G17: Yes | H17: Identifier that determines what type of transaction the record contains. For SIS activity the values depend on the record type. | I17: 3214 | J17: Add | K17: 3 | O17: =VLOOKUP(A17,[1]Model!C$2:J$559,2,FALSE)=B17 -> TRUE | P17: =VLOOKUP(A17,Model!C$2:G$228,5,FALSE)=D17 -> #N/A | Q17: =VLOOKUP(A17,[2]Model!C$2:L$228,8,FALSE) -> 144 | R17: =VLOOKUP(A17,[2]Model!C$2:G$228,3,FALSE)=[3]!Table14[[#This Row],[Business Definition (To go into comments and into Meta Data Hub)]] -> #REF! | S17: =IF([3]!Table14[[#This Row],[Nullable in Table and in Oracle View NULL, NOT NULL]]="No","NOT NULL","NULL")=VLOOKUP(A17,[2]Model!C$2:I$228,6,FALSE) -> #REF! | T17: =VLOOKUP(B17,[2]Table!A$2:F$415,1,FALSE)=[3]!Table14[[#This Row],[Physical Name of Attribute (Name of column in Table) Supplied by DA Team]] -> #REF! | U17: =VLOOKUP(B17,Table!A$2:F$319,2,FALSE)=Table1[[#This Row],[Data type in Oracle VARCHAR2(n), DATE, NUMBER(m,n), TIMETSTAMP(6)]] -> TRUE | V17: =VLOOKUP(B17,Table!A$2:F$231,3,FALSE)=Table1[[#This Row],[Nullable in Table and in Oracle View NULL, NOT NULL]] -> TRUE | W17: =VLOOKUP(B17,Table!A$2:H$228,6,FALSE)=Table1[[#This Row],[Business Definition (To go into comments and into Meta Data Hub)]] -> TRUE | X17: =VLOOKUP((UPPER(SUBSTITUTE(A17," ","_"))),'[2]Consumer View'!A$2:I$329,1,FALSE) -> SIS_DETAILED_EVENTS_ID | Y17: CCAL_REPL_OWNER | Z17: TXN | AA17: SRC_BUY_SELL_MULTI_ID | AE17: [6/3/24]: Modified target data type for Oracle and Redshift. PBI 1912566 | AH17: N
A18: SIS Detailed Events Name | B18: SIS_DLTD_EV_NM | C18: SIS_Detailed_Event_Name | D18: VARCHAR2(200) | E18: Yes | F18: character varying(200) | G18: Yes | H18: Name that determines what type of transaction the record contains. For SIS activity the values depend on the record type. | I18: 3219 Stock dividends 3214 Cash Dividend 3247 Corporate actions 3229 Cash receipts 3230 Disbursements 3234 Credit interest or Foreign Withholding 3246 Disbursements (receive stock) 3233 Debit interest 3231 Journals, Income, Expenses 3245 Cash receipts (deliver stock) | J18: Add | K18: 3 | O18: =VLOOKUP(A18,[1]Model!C$2:J$559,2,FALSE)=B18 -> TRUE | P18: =VLOOKUP(A18,Model!C$2:G$228,5,FALSE)=D18 -> #N/A | Q18: =VLOOKUP(A18,[2]Model!C$2:L$228,8,FALSE) -> 145 | R18: =VLOOKUP(A18,[2]Model!C$2:G$228,3,FALSE)=[3]!Table14[[#This Row],[Business Definition (To go into comments and into Meta Data Hub)]] -> #REF! | S18: =IF([3]!Table14[[#This Row],[Nullable in Table and in Oracle View NULL, NOT NULL]]="No","NOT NULL","NULL")=VLOOKUP(A18,[2]Model!C$2:I$228,6,FALSE) -> #REF! | T18: =VLOOKUP(B18,[2]Table!A$2:F$415,1,FALSE)=[3]!Table14[[#This Row],[Physical Name of Attribute (Name of column in Table) Supplied by DA Team]] -> #REF! | U18: =VLOOKUP(B18,Table!A$2:F$319,2,FALSE)=Table1[[#This Row],[Data type in Oracle VARCHAR2(n), DATE, NUMBER(m,n), TIMETSTAMP(6)]] -> FALSE | V18: =VLOOKUP(B18,Table!A$2:F$231,3,FALSE)=Table1[[#This Row],[Nullable in Table and in Oracle View NULL, NOT NULL]] -> TRUE | W18: =VLOOKUP(B18,Table!A$2:H$228,6,FALSE)=Table1[[#This Row],[Business Definition (To go into comments and into Meta Data Hub)]] -> TRUE | X18: =VLOOKUP((UPPER(SUBSTITUTE(A18," ","_"))),'[2]Consumer View'!A$2:I$329,1,FALSE) -> SIS_DETAILED_EVENTS_NAME | Y18: CCAL_REPL_OWNER | Z18: CL_VAL | AA18: CL_VAL_NM | AD18: ccal_repl_owner.cl_val cv left join ccal_repl_owner.cl_val cv ON cv.cl_val_id = t.SRC_BUY_SELL_MULTI_ID and cv.CL_SCM_ID = '99' | AE18: [6/3/24]: Modified target data type for Oracle and Redshift. PBI 1912566 | AH18: N (add Code, existing PBI)
A19: SIS User Id | B19: SIS_USR_ID | C19: SIS_User_Id | D19: VARCHAR2(255) | E19: Yes | F19: character varying(255) | G19: Yes | H19: Identifier of the process or user that creates the records sourced from SIS Money Movement | I19: LL015 | J19: Add | K19: 3 | O19: =VLOOKUP(A19,[1]Model!C$2:J$559,2,FALSE)=B19 -> TRUE | P19: =VLOOKUP(A19,Model!C$2:G$228,5,FALSE)=D19 -> #N/A | Q19: =VLOOKUP(A19,[2]Model!C$2:L$228,8,FALSE) -> 146 | R19: =VLOOKUP(A19,[2]Model!C$2:G$228,3,FALSE)=[3]!Table14[[#This Row],[Business Definition (To go into comments and into Meta Data Hub)]] -> #REF! | S19: =IF([3]!Table14[[#This Row],[Nullable in Table and in Oracle View NULL, NOT NULL]]="No","NOT NULL","NULL")=VLOOKUP(A19,[2]Model!C$2:I$228,6,FALSE) -> #REF! | T19: =VLOOKUP(B19,[2]Table!A$2:F$415,1,FALSE)=[3]!Table14[[#This Row],[Physical Name of Attribute (Name of column in Table) Supplied by DA Team]] -> #REF! | U19: =VLOOKUP(B19,Table!A$2:F$319,2,FALSE)=Table1[[#This Row],[Data type in Oracle VARCHAR2(n), DATE, NUMBER(m,n), TIMETSTAMP(6)]] -> FALSE | V19: =VLOOKUP(B19,Table!A$2:F$231,3,FALSE)=Table1[[#This Row],[Nullable in Table and in Oracle View NULL, NOT NULL]] -> TRUE | W19: =VLOOKUP(B19,Table!A$2:H$228,6,FALSE)=Table1[[#This Row],[Business Definition (To go into comments and into Meta Data Hub)]] -> TRUE | X19: =VLOOKUP((UPPER(SUBSTITUTE(A19," ","_"))),'[2]Consumer View'!A$2:I$329,1,FALSE) -> SIS_USER_ID | Y19: CCAL_REPL_OWNER | Z19: TXN | AA19: USR_ID | AH19: N
A20: SIS Account Classification Code | B20: SIS_AC_CL_CD | C20: SIS_Account_Classification_Code | D20: VARCHAR2(50) | E20: Yes | F20: character varying(50) | G20: Yes | H20: SIS account classification codes | I20: Z | J20: Add | K20: 3 | O20: =VLOOKUP(A20,[1]Model!C$2:J$559,2,FALSE)=B20 -> TRUE | P20: =VLOOKUP(A20,Model!C$2:G$228,5,FALSE)=D20 -> #N/A | Q20: =VLOOKUP(A20,[2]Model!C$2:L$228,8,FALSE) -> 147 | R20: =VLOOKUP(A20,[2]Model!C$2:G$228,3,FALSE)=[3]!Table14[[#This Row],[Business Definition (To go into comments and into Meta Data Hub)]] -> #REF! | S20: =IF([3]!Table14[[#This Row],[Nullable in Table and in Oracle View NULL, NOT NULL]]="No","NOT NULL","NULL")=VLOOKUP(A20,[2]Model!C$2:I$228,6,FALSE) -> #REF! | T20: =VLOOKUP(B20,[2]Table!A$2:F$415,1,FALSE)=[3]!Table14[[#This Row],[Physical Name of Attribute (Name of column in Table) Supplied by DA Team]] -> #REF! | U20: =VLOOKUP(B20,Table!A$2:F$319,2,FALSE)=Table1[[#This Row],[Data type in Oracle VARCHAR2(n), DATE, NUMBER(m,n), TIMETSTAMP(6)]] -> FALSE | V20: =VLOOKUP(B20,Table!A$2:F$231,3,FALSE)=Table1[[#This Row],[Nullable in Table and in Oracle View NULL, NOT NULL]] -> TRUE | W20: =VLOOKUP(B20,Table!A$2:H$228,6,FALSE)=Table1[[#This Row],[Business Definition (To go into comments and into Meta Data Hub)]] -> TRUE | X20: =VLOOKUP((UPPER(SUBSTITUTE(A20," ","_"))),'[2]Consumer View'!A$2:I$329,1,FALSE) -> SIS_ACCOUNT_CLASSIFICATION_CODE | Y20: CCAL_REPL_OWNER | Z20: TXN | AA20: SRC_PRIM_CL | AH20: N
A21: Source Cancellation Reason Id | B21: SRC_CNCL_RSN_ID | D21: NUMBER(38,0) | E21: Yes | F21: NUMERIC(38,0) | G21: Yes | H21: Id representing Reason for cancellation in source system | I21: 3248, 3249 | J21: Add | K21: 3 | O21: =VLOOKUP(A21,[1]Model!C$2:J$559,2,FALSE)=B21 -> TRUE | P21: =VLOOKUP(A21,Model!C$2:G$228,5,FALSE)=D21 -> #N/A | Q21: =VLOOKUP(A21,[2]Model!C$2:L$228,8,FALSE) -> 148 | R21: =VLOOKUP(A21,[2]Model!C$2:G$228,3,FALSE)=[3]!Table14[[#This Row],[Business Definition (To go into comments and into Meta Data Hub)]] -> #REF! | S21: =IF([3]!Table14[[#This Row],[Nullable in Table and in Oracle View NULL, NOT NULL]]="No","NOT NULL","NULL")=VLOOKUP(A21,[2]Model!C$2:I$228,6,FALSE) -> #REF! | T21: =VLOOKUP(B21,[2]Table!A$2:F$415,1,FALSE)=[3]!Table14[[#This Row],[Physical Name of Attribute (Name of column in Table) Supplied by DA Team]] -> #REF! | U21: =VLOOKUP(B21,Table!A$2:F$319,2,FALSE)=Table1[[#This Row],[Data type in Oracle VARCHAR2(n), DATE, NUMBER(m,n), TIMETSTAMP(6)]] -> TRUE | V21: =VLOOKUP(B21,Table!A$2:F$231,3,FALSE)=Table1[[#This Row],[Nullable in Table and in Oracle View NULL, NOT NULL]] -> TRUE | W21: =VLOOKUP(B21,Table!A$2:H$228,6,FALSE)=Table1[[#This Row],[Business Definition (To go into comments and into Meta Data Hub)]] -> TRUE | X21: =VLOOKUP((UPPER(SUBSTITUTE(A21," ","_"))),'[2]Consumer View'!A$2:I$329,1,FALSE) -> SOURCE_CANCELLATION_REASON_ID | Y21: CCAL_REPL_OWNER | Z21: TXN | AA21: SRC_CNCL_RSN_ID | AH21: N
A22: Source Cancellation Reason Code | B22: SRC_CNCL_RSN_CD | C22: Source_Cancellation_Reason_Code | D22: VARCHAR2(20) | E22: Yes | F22: character varying(20) | G22: Yes | H22: Code representing Reason for cancellation in source system Valid Values - A ,N, Y, null/blank Valid values include: 'Y' - Trade is cancelled due to correction, and will not be processed as a new trade 'N' - Trade is an outright cancel. 'A' - Trade is a cancel/correction due to allocation, and will be processed as allocated trade. | I22: Y, N, A, null | J22: Add | K22: 3 | O22: =VLOOKUP(A22,[1]Model!C$2:J$559,2,FALSE)=B22 -> TRUE | P22: =VLOOKUP(A22,Model!C$2:G$228,5,FALSE)=D22 -> #N/A | Q22: =VLOOKUP(A22,[2]Model!C$2:L$228,8,FALSE) -> 149 | R22: =VLOOKUP(A22,[2]Model!C$2:G$228,3,FALSE)=[3]!Table14[[#This Row],[Business Definition (To go into comments and into Meta Data Hub)]] -> #VALUE! | S22: =IF([3]!Table14[[#This Row],[Nullable in Table and in Oracle View NULL, NOT NULL]]="No","NOT NULL","NULL")=VLOOKUP(A22,[2]Model!C$2:I$228,6,FALSE) -> #REF! | T22: =VLOOKUP(B22,[2]Table!A$2:F$415,1,FALSE)=[3]!Table14[[#This Row],[Physical Name of Attribute (Name of column in Table) Supplied by DA Team]] -> #REF! | U22: =VLOOKUP(B22,Table!A$2:F$319,2,FALSE)=Table1[[#This Row],[Data type in Oracle VARCHAR2(n), DATE, NUMBER(m,n), TIMETSTAMP(6)]] -> FALSE | V22: =VLOOKUP(B22,Table!A$2:F$231,3,FALSE)=Table1[[#This Row],[Nullable in Table and in Oracle View NULL, NOT NULL]] -> TRUE | W22: =VLOOKUP(B22,Table!A$2:H$228,6,FALSE)=Table1[[#This Row],[Business Definition (To go into comments and into Meta Data Hub)]] -> FALSE | X22: =VLOOKUP((UPPER(SUBSTITUTE(A22," ","_"))),'[2]Consumer View'!A$2:I$329,1,FALSE) -> SOURCE_CANCELLATION_REASON_CODE | Y22: CCAL_REPL_OWNER | Z22: CL_VAL | AA22: CL_VAL_CODE | AD22: ccal_repl_owner.txn t left join ccal_repl_owner.cl_val cv ON cl_val.cl_val_id = t.SRC_CNCL_RSN_ID cs.cl_scm_id = '102' | AE22: [6/3/24]: Modified target data type for Oracle and Redshift. PBI 1912566 | AH22: N
A23: Source Cancellation Reason Name | B23: SRC_CNCL_RSN_NM | C23: Source_Cancellation_Reason | D23: VARCHAR2(200) | E23: Yes | F23: character varying(200) | G23: Yes | H23: Name representing Reason for cancellation in source system | I23: Correction Outright Cancel Account Allocation | J23: Add | K23: 3 | O23: =VLOOKUP(A23,[1]Model!C$2:J$559,2,FALSE)=B23 -> TRUE | P23: =VLOOKUP(A23,Model!C$2:G$228,5,FALSE)=D23 -> #N/A | Q23: =VLOOKUP(A23,[2]Model!C$2:L$228,8,FALSE) -> 150 | R23: =VLOOKUP(A23,[2]Model!C$2:G$228,3,FALSE)=[3]!Table14[[#This Row],[Business Definition (To go into comments and into Meta Data Hub)]] -> #REF! | S23: =IF([3]!Table14[[#This Row],[Nullable in Table and in Oracle View NULL, NOT NULL]]="No","NOT NULL","NULL")=VLOOKUP(A23,[2]Model!C$2:I$228,6,FALSE) -> #REF! | T23: =VLOOKUP(B23,[2]Table!A$2:F$415,1,FALSE)=[3]!Table14[[#This Row],[Physical Name of Attribute (Name of column in Table) Supplied by DA Team]] -> #REF! | U23: =VLOOKUP(B23,Table!A$2:F$319,2,FALSE)=Table1[[#This Row],[Data type in Oracle VARCHAR2(n), DATE, NUMBER(m,n), TIMETSTAMP(6)]] -> FALSE | V23: =VLOOKUP(B23,Table!A$2:F$231,3,FALSE)=Table1[[#This Row],[Nullable in Table and in Oracle View NULL, NOT NULL]] -> TRUE | W23: =VLOOKUP(B23,Table!A$2:H$228,6,FALSE)=Table1[[#This Row],[Business Definition (To go into comments and into Meta Data Hub)]] -> TRUE | X23: =VLOOKUP((UPPER(SUBSTITUTE(A23," ","_"))),'[2]Consumer View'!A$2:I$329,1,FALSE) -> SOURCE_CANCELLATION_REASON_NAME | Y23: CCAL_REPL_OWNER | Z23: CL_VAL | AA23: CL_VAL_NM | AD23: ccal_repl_owner.txn t left join ccal_repl_owner.cl_val cv ON cl_val.cl_val_id = t.SRC_CNCL_RSN_ID cs.cl_scm_id = '102' | AH23: N
A24: Source Transaction Sequence Number | B24: SRC_TXN_SEQ_NUM | C24: Source_Transaction_Sequence_Number | D24: NUMBER(38,0) | E24: Yes | F24: NUMERIC(38,0) | G24: Yes | H24: Transaction number assigned to the transaction in the source system. | I24: 2878 | J24: Add | K24: 3 | O24: =VLOOKUP(A24,[1]Model!C$2:J$559,2,FALSE)=B24 -> TRUE | P24: =VLOOKUP(A24,Model!C$2:G$228,5,FALSE)=D24 -> #N/A | Q24: =VLOOKUP(A24,[2]Model!C$2:L$228,8,FALSE) -> 151 | R24: =VLOOKUP(A24,[2]Model!C$2:G$228,3,FALSE)=[3]!Table14[[#This Row],[Business Definition (To go into comments and into Meta Data Hub)]] -> #REF! | S24: =IF([3]!Table14[[#This Row],[Nullable in Table and in Oracle View NULL, NOT NULL]]="No","NOT NULL","NULL")=VLOOKUP(A24,[2]Model!C$2:I$228,6,FALSE) -> #REF! | T24: =VLOOKUP(B24,[2]Table!A$2:F$415,1,FALSE)=[3]!Table14[[#This Row],[Physical Name of Attribute (Name of column in Table) Supplied by DA Team]] -> #REF! | U24: =VLOOKUP(B24,Table!A$2:F$319,2,FALSE)=Table1[[#This Row],[Data type in Oracle VARCHAR2(n), DATE, NUMBER(m,n), TIMETSTAMP(6)]] -> TRUE | V24: =VLOOKUP(B24,Table!A$2:F$231,3,FALSE)=Table1[[#This Row],[Nullable in Table and in Oracle View NULL, NOT NULL]] -> TRUE | W24: =VLOOKUP(B24,Table!A$2:H$228,6,FALSE)=Table1[[#This Row],[Business Definition (To go into comments and into Meta Data Hub)]] -> TRUE | X24: =VLOOKUP((UPPER(SUBSTITUTE(A24," ","_"))),'[2]Consumer View'!A$2:I$329,1,FALSE) -> SOURCE_TRANSACTION_SEQUENCE_NUMBER | Y24: CCAL_REPL_OWNER | Z24: TXN | AA24: SRC_TXN_SEQ_NUM | AH24: N
A25: Dividend Record Date | B25: DVDN_RCRD_DT | C25: Dividend_Record_Date | D25: DATE | E25: Yes | F25: timestamp without time zone | G25: Yes | H25: The cut-off date that an organization is expected to use to determine which shareholders are eligible to receive a dividend or income distribution. | I25: 42398 | J25: Add | K25: 3 | O25: =VLOOKUP(A25,[1]Model!C$2:J$559,2,FALSE)=B25 -> TRUE | P25: =VLOOKUP(A25,Model!C$2:G$228,5,FALSE)=D25 -> TRUE | Q25: =VLOOKUP(A25,[2]Model!C$2:L$228,8,FALSE) -> 152 | R25: =VLOOKUP(A25,[2]Model!C$2:G$228,3,FALSE)=[3]!Table14[[#This Row],[Business Definition (To go into comments and into Meta Data Hub)]] -> #REF! | S25: =IF([3]!Table14[[#This Row],[Nullable in Table and in Oracle View NULL, NOT NULL]]="No","NOT NULL","NULL")=VLOOKUP(A25,[2]Model!C$2:I$228,6,FALSE) -> #REF! | T25: =VLOOKUP(B25,[2]Table!A$2:F$415,1,FALSE)=[3]!Table14[[#This Row],[Physical Name of Attribute (Name of column in Table) Supplied by DA Team]] -> #REF! | U25: =VLOOKUP(B25,Table!A$2:F$319,2,FALSE)=Table1[[#This Row],[Data type in Oracle VARCHAR2(n), DATE, NUMBER(m,n), TIMETSTAMP(6)]] -> TRUE | V25: =VLOOKUP(B25,Table!A$2:F$231,3,FALSE)=Table1[[#This Row],[Nullable in Table and in Oracle View NULL, NOT NULL]] -> TRUE | W25: =VLOOKUP(B25,Table!A$2:H$228,6,FALSE)=Table1[[#This Row],[Business Definition (To go into comments and into Meta Data Hub)]] -> TRUE | X25: =VLOOKUP((UPPER(SUBSTITUTE(A25," ","_"))),'[2]Consumer View'!A$2:I$329,1,FALSE) -> DIVIDEND_RECORD_DATE | Y25: CCAL_REPL_OWNER | Z25: TXN | AA25: DVDN_RCRD_DT | AH25: N
A26: Owner IMPACT FA Number | B26: OWN_IMP_FA_NUM | C26: Brokerage_Owner_FA_Fixed_Income_IMPACT_Number | D26: VARCHAR2(20) | E26: Yes | F26: character varying(20) | G26: Yes | H26: FA Number as given in Impact system | I26: 01A | J26: Add | K26: 3 | O26: =VLOOKUP(A26,[1]Model!C$2:J$559,2,FALSE)=B26 -> TRUE | P26: =VLOOKUP(A26,Model!C$2:G$228,5,FALSE)=D26 -> TRUE | Q26: =VLOOKUP(A26,[2]Model!C$2:L$228,8,FALSE) -> 153 | R26: =VLOOKUP(A26,[2]Model!C$2:G$228,3,FALSE)=[3]!Table14[[#This Row],[Business Definition (To go into comments and into Meta Data Hub)]] -> #REF! | S26: =IF([3]!Table14[[#This Row],[Nullable in Table and in Oracle View NULL, NOT NULL]]="No","NOT NULL","NULL")=VLOOKUP(A26,[2]Model!C$2:I$228,6,FALSE) -> #REF! | T26: =VLOOKUP(B26,[2]Table!A$2:F$415,1,FALSE)=[3]!Table14[[#This Row],[Physical Name of Attribute (Name of column in Table) Supplied by DA Team]] -> #REF! | U26: =VLOOKUP(B26,Table!A$2:F$319,2,FALSE)=Table1[[#This Row],[Data type in Oracle VARCHAR2(n), DATE, NUMBER(m,n), TIMETSTAMP(6)]] -> FALSE | V26: =VLOOKUP(B26,Table!A$2:F$231,3,FALSE)=Table1[[#This Row],[Nullable in Table and in Oracle View NULL, NOT NULL]] -> TRUE | W26: =VLOOKUP(B26,Table!A$2:H$228,6,FALSE)=Table1[[#This Row],[Business Definition (To go into comments and into Meta Data Hub)]] -> TRUE | X26: =VLOOKUP((UPPER(SUBSTITUTE(A26," ","_"))),'[2]Consumer View'!A$2:I$329,1,FALSE) -> OWNER_IMPACT_FA_NUMBER | Y26: CCAL_REPL_OWNER | Z26: TXN | AA26: SALE_PSN_NUM | AH26: N
A27: Owner FA Number | B27: OWN_FA_NUM | C27: Brokerage_Owner_FA_Number | D27: VARCHAR2(6) | E27: Yes | F27: character varying(6) | G27: Yes | H27: Owner FA Number is a FA Number that owns the Arrangement for which activity is recorded | I27: 25T3 | J27: Add | K27: 3 | O27: =VLOOKUP(A27,[1]Model!C$2:J$559,2,FALSE)=B27 -> TRUE | P27: =VLOOKUP(A27,Model!C$2:G$228,5,FALSE)=D27 -> TRUE | Q27: =VLOOKUP(A27,[2]Model!C$2:L$228,8,FALSE) -> 154 | R27: =VLOOKUP(A27,[2]Model!C$2:G$228,3,FALSE)=[3]!Table14[[#This Row],[Business Definition (To go into comments and into Meta Data Hub)]] -> #REF! | S27: =IF([3]!Table14[[#This Row],[Nullable in Table and in Oracle View NULL, NOT NULL]]="No","NOT NULL","NULL")=VLOOKUP(A27,[2]Model!C$2:I$228,6,FALSE) -> #REF! | T27: =VLOOKUP(B27,[2]Table!A$2:F$415,1,FALSE)=[3]!Table14[[#This Row],[Physical Name of Attribute (Name of column in Table) Supplied by DA Team]] -> #REF! | U27: =VLOOKUP(B27,Table!A$2:F$319,2,FALSE)=Table1[[#This Row],[Data type in Oracle VARCHAR2(n), DATE, NUMBER(m,n), TIMETSTAMP(6)]] -> FALSE | V27: =VLOOKUP(B27,Table!A$2:F$231,3,FALSE)=Table1[[#This Row],[Nullable in Table and in Oracle View NULL, NOT NULL]] -> TRUE | W27: =VLOOKUP(B27,Table!A$2:H$228,6,FALSE)=Table1[[#This Row],[Business Definition (To go into comments and into Meta Data Hub)]] -> TRUE | X27: =VLOOKUP((UPPER(SUBSTITUTE(A27," ","_"))),'[2]Consumer View'!A$2:I$329,1,FALSE) -> OWNER_FA_NUMBER | Y27: CCSI_OWNER | Z27: AR_GRP_SUBDIM | AA27: FA_NUM | AD27: select fa.FA_NUM from ccal_repl_owner.txn t LEFT JOIN ccsi_owner.AR_GRP_SUBDIM fa ON t.AR_ID = fa.AR_ID and t.td >= fa.EFF_DT and t.td < fa.END_DT; | AE27: [9/11/24]: Reflected the change to use TXN.TD from Product Backlog Item 1912566: Change join condition and update data types for Activity | AH27: Y
A28: Owner FA Number Entity Code | B28: OWN_FA_NUM_ENT_CD | C28: Brokerage_Owner_FA_Number_Entity_Code | D28: VARCHAR2(20) | E28: Yes | F28: character varying(20) | G28: Yes | H28: Entity Code that owns the Owner FA Number | I28: 10D00 | J28: Add | K28: 3 | O28: =VLOOKUP(A28,[1]Model!C$2:J$559,2,FALSE)=B28 -> TRUE | P28: =VLOOKUP(A28,Model!C$2:G$228,5,FALSE)=D28 -> TRUE | Q28: =VLOOKUP(A28,[2]Model!C$2:L$228,8,FALSE) -> 155 | R28: =VLOOKUP(A28,[2]Model!C$2:G$228,3,FALSE)=[3]!Table14[[#This Row],[Business Definition (To go into comments and into Meta Data Hub)]] -> #REF! | S28: =IF([3]!Table14[[#This Row],[Nullable in Table and in Oracle View NULL, NOT NULL]]="No","NOT NULL","NULL")=VLOOKUP(A28,[2]Model!C$2:I$228,6,FALSE) -> #REF! | T28: =VLOOKUP(B28,[2]Table!A$2:F$415,1,FALSE)=[3]!Table14[[#This Row],[Physical Name of Attribute (Name of column in Table) Supplied by DA Team]] -> #REF! | U28: =VLOOKUP(B28,Table!A$2:F$319,2,FALSE)=Table1[[#This Row],[Data type in Oracle VARCHAR2(n), DATE, NUMBER(m,n), TIMETSTAMP(6)]] -> FALSE | V28: =VLOOKUP(B28,Table!A$2:F$231,3,FALSE)=Table1[[#This Row],[Nullable in Table and in Oracle View NULL, NOT NULL]] -> TRUE | W28: =VLOOKUP(B28,Table!A$2:H$228,6,FALSE)=Table1[[#This Row],[Business Definition (To go into comments and into Meta Data Hub)]] -> TRUE | X28: =VLOOKUP((UPPER(SUBSTITUTE(A28," ","_"))),'[2]Consumer View'!A$2:I$329,1,FALSE) -> OWNER_FA_NUMBER_ENTITY_CODE | Y28: SSDS_DAL_OWNER | Z28: FA_NUMBER_V | AA28: FA_NUMBER_ENTITY_CODE | AD28: Derive based on OWN_FA_NUM field. left join SSDS_DAL_OWNER.FA_NUMBER_V fn on fn.FA_NUMBER = OWN_FA_NUM and t.td >= fn.EFF_DT AND t.td < fn.END_DT | AE28: [6/8/24]: Modified target data type for Oracle and Redshift. PBI 1912566 [9/11/24]: Reflected the change to use TXN.TD from Product Backlog Item 1912566: Change join condition and update data types for Activity | AH28: Y
A29: Owner FA Employee Id | B29: FA_OWN_EMPE_ID | C29: Brokerage_Owner_FA_Responsible_Party_Employee_ID | D29: VARCHAR2(44) | E29: Yes | F29: character varying(44) | G29: Yes | H29: PeopleWorks Identifier for the Responsible Party for an FA Number | I29: 49139 | J29: Add | K29: 3 | O29: =VLOOKUP(A29,[1]Model!C$2:J$559,2,FALSE)=B29 -> TRUE | P29: =VLOOKUP(A29,Model!C$2:G$228,5,FALSE)=D29 -> TRUE | Q29: =VLOOKUP(A29,[2]Model!C$2:L$228,8,FALSE) -> 156 | R29: =VLOOKUP(A29,[2]Model!C$2:G$228,3,FALSE)=[3]!Table14[[#This Row],[Business Definition (To go into comments and into Meta Data Hub)]] -> #REF! | S29: =IF([3]!Table14[[#This Row],[Nullable in Table and in Oracle View NULL, NOT NULL]]="No","NOT NULL","NULL")=VLOOKUP(A29,[2]Model!C$2:I$228,6,FALSE) -> #REF! | T29: =VLOOKUP(B29,[2]Table!A$2:F$415,1,FALSE)=[3]!Table14[[#This Row],[Physical Name of Attribute (Name of column in Table) Supplied by DA Team]] -> #REF! | U29: =VLOOKUP(B29,Table!A$2:F$319,2,FALSE)=Table1[[#This Row],[Data type in Oracle VARCHAR2(n), DATE, NUMBER(m,n), TIMETSTAMP(6)]] -> FALSE | V29: =VLOOKUP(B29,Table!A$2:F$231,3,FALSE)=Table1[[#This Row],[Nullable in Table and in Oracle View NULL, NOT NULL]] -> TRUE | W29: =VLOOKUP(B29,Table!A$2:H$228,6,FALSE)=Table1[[#This Row],[Business Definition (To go into comments and into Meta Data Hub)]] -> TRUE | X29: =VLOOKUP((UPPER(SUBSTITUTE(A29," ","_"))),'[2]Consumer View'!A$2:I$329,1,FALSE) -> OWNER_FA_EMPLOYEE_ID | Y29: SSDS_DAL_OWNER | Z29: FA_NUMBER_V | AA29: RESPONSIBLE_PARTY_EMPLOYEE_ID | AE29: [6/8/24]: Modified target data type for Oracle and Redshift. PBI 1912566 | AH29: Y
A30: Owner FA Number Entity Enterprise Id | B30: OWN_FA_NUM_ENT_ENTP_ID | C30: Brokerage_Owner_FA_entity_enterprise_id | D30: NUMBER(22,0) | E30: Yes | F30: NUMERIC(22,0) | G30: Yes | H30: Enterprise Id of the Entity that owns the Owner FA Number | I30: AHK00 | J30: Add | K30: 3 | O30: =VLOOKUP(A30,[1]Model!C$2:J$559,2,FALSE)=B30 -> TRUE | P30: =VLOOKUP(A30,Model!C$2:G$228,5,FALSE)=D30 -> TRUE | Q30: =VLOOKUP(A30,[2]Model!C$2:L$228,8,FALSE) -> 157 | R30: =VLOOKUP(A30,[2]Model!C$2:G$228,3,FALSE)=[3]!Table14[[#This Row],[Business Definition (To go into comments and into Meta Data Hub)]] -> #REF! | S30: =IF([3]!Table14[[#This Row],[Nullable in Table and in Oracle View NULL, NOT NULL]]="No","NOT NULL","NULL")=VLOOKUP(A30,[2]Model!C$2:I$228,6,FALSE) -> #REF! | T30: =VLOOKUP(B30,[2]Table!A$2:F$415,1,FALSE)=[3]!Table14[[#This Row],[Physical Name of Attribute (Name of column in Table) Supplied by DA Team]] -> #REF! | U30: =VLOOKUP(B30,Table!A$2:F$319,2,FALSE)=Table1[[#This Row],[Data type in Oracle VARCHAR2(n), DATE, NUMBER(m,n), TIMETSTAMP(6)]] -> TRUE | V30: =VLOOKUP(B30,Table!A$2:F$231,3,FALSE)=Table1[[#This Row],[Nullable in Table and in Oracle View NULL, NOT NULL]] -> TRUE | W30: =VLOOKUP(B30,Table!A$2:H$228,6,FALSE)=Table1[[#This Row],[Business Definition (To go into comments and into Meta Data Hub)]] -> TRUE | X30: =VLOOKUP((UPPER(SUBSTITUTE(A30," ","_"))),'[2]Consumer View'!A$2:I$329,1,FALSE) -> OWNER_FA_NUMBER_ENTITY_ENTERPRISE_ID | Y30: SSDS_DAL_OWNER | Z30: ENTERPRISE_ENTITY_DIM_V | AA30: ENTITY_ENTERPRISE_ID | AD30: Derive based on OWN_FA_NUM_ENT_CD field. LEFT JOIN SSDS_DAL_OWNER.ENTERPRISE_ENTITY_DIM_V e ON e.Entity_code_long = OWN_FA_NUM_ENT_CD AND t.td >= e.EFF_DT AND t.td < e.END_DT AND e.ENTITY_RECYCLED_BOOLEAN='0' AND e.ENTITY_FINANCIAL_RIA_BOOLEAN = '0' | AE30: [6/5/24]: Updated data type from VARCHAR to NUMBER. PBI 1912566 [6/25/24]: As a part of PBI 1912566 ROWNUM logic to pick one record at the very last stage was implemented to avoid duplicates in Entity Dim. The logic is to be revised in the future to write an exception for dupes [9/11/24]: Reflected the change to use TXN.TD from Product Backlog Item 1912566: Change join condition and update data types for Activity | AH30: Y (PBI 1931139)
A31: ACAT Contra Firm Clearing Number | B31: ACAT_CNTRA_FIRM_CLRG_NUM | C31: ACAT_Contra_Firm_Clearing_Number | D31: VARCHAR2(4) | E31: Yes | F31: character varying(4) | G31: Yes | H31: This is the logical identifier for the entity/system (in this case ACAT) that is providing this transaction information or responsible for creation/maintenance of the information. In a case where the information is created and maintained. Identifier of the system from which CDS database receives/obtains the underlying record. This identifier is specifc to ACAT Contra Firm clearing | I31: 0352 | J31: Add | K31: 3 | O31: =VLOOKUP(A31,[1]Model!C$2:J$559,2,FALSE)=B31 -> TRUE | P31: =VLOOKUP(A31,Model!C$2:G$228,5,FALSE)=D31 -> TRUE | Q31: =VLOOKUP(A31,[2]Model!C$2:L$228,8,FALSE) -> 158 | R31: =VLOOKUP(A31,[2]Model!C$2:G$228,3,FALSE)=[3]!Table14[[#This Row],[Business Definition (To go into comments and into Meta Data Hub)]] -> #VALUE! | S31: =IF([3]!Table14[[#This Row],[Nullable in Table and in Oracle View NULL, NOT NULL]]="No","NOT NULL","NULL")=VLOOKUP(A31,[2]Model!C$2:I$228,6,FALSE) -> #REF! | T31: =VLOOKUP(B31,[2]Table!A$2:F$415,1,FALSE)=[3]!Table14[[#This Row],[Physical Name of Attribute (Name of column in Table) Supplied by DA Team]] -> #REF! | U31: =VLOOKUP(B31,Table!A$2:F$319,2,FALSE)=Table1[[#This Row],[Data type in Oracle VARCHAR2(n), DATE, NUMBER(m,n), TIMETSTAMP(6)]] -> FALSE | V31: =VLOOKUP(B31,Table!A$2:F$231,3,FALSE)=Table1[[#This Row],[Nullable in Table and in Oracle View NULL, NOT NULL]] -> TRUE | W31: =VLOOKUP(B31,Table!A$2:H$228,6,FALSE)=Table1[[#This Row],[Business Definition (To go into comments and into Meta Data Hub)]] -> FALSE | X31: =VLOOKUP((UPPER(SUBSTITUTE(A31," ","_"))),'[2]Consumer View'!A$2:I$329,1,FALSE) -> ACAT_CONTRA_FIRM_CLEARING_NUMBER | Y31: CCAL_REPL_OWNER | Z31: TXN | AA31: ORIG_SRC_STM_CODE | AD31: ccal_repl_owner.txn t where t.src_stm_id IN ( 53, 54 ) | AH31: N
A32: ACAT Contra Firm Name | B32: ACAT_CNTRA_FIRM_NM | C32: ACAT_Contra_Firm | D32: VARCHAR2(50) | E32: Yes | F32: character varying(50) | G32: Yes | H32: ACAT Contra Firm Clearing Name | I32: 0352 | J32: Add | K32: 3 | O32: =VLOOKUP(A32,[1]Model!C$2:J$559,2,FALSE)=B32 -> TRUE | P32: =VLOOKUP(A32,Model!C$2:G$228,5,FALSE)=D32 -> TRUE | Q32: =VLOOKUP(A32,[2]Model!C$2:L$228,8,FALSE) -> 159 | R32: =VLOOKUP(A32,[2]Model!C$2:G$228,3,FALSE)=[3]!Table14[[#This Row],[Business Definition (To go into comments and into Meta Data Hub)]] -> #REF! | S32: =IF([3]!Table14[[#This Row],[Nullable in Table and in Oracle View NULL, NOT NULL]]="No","NOT NULL","NULL")=VLOOKUP(A32,[2]Model!C$2:I$228,6,FALSE) -> #REF! | T32: =VLOOKUP(B32,[2]Table!A$2:F$415,1,FALSE)=[3]!Table14[[#This Row],[Physical Name of Attribute (Name of column in Table) Supplied by DA Team]] -> #REF! | U32: =VLOOKUP(B32,Table!A$2:F$319,2,FALSE)=Table1[[#This Row],[Data type in Oracle VARCHAR2(n), DATE, NUMBER(m,n), TIMETSTAMP(6)]] -> FALSE | V32: =VLOOKUP(B32,Table!A$2:F$231,3,FALSE)=Table1[[#This Row],[Nullable in Table and in Oracle View NULL, NOT NULL]] -> TRUE | W32: =VLOOKUP(B32,Table!A$2:H$228,6,FALSE)=Table1[[#This Row],[Business Definition (To go into comments and into Meta Data Hub)]] -> TRUE | X32: =VLOOKUP((UPPER(SUBSTITUTE(A32," ","_"))),'[2]Consumer View'!A$2:I$329,1,FALSE) -> ACAT_CONTRA_FIRM_NAME | Y32: CCAL_REPL_OWNER | Z32: ACATS_BROKER | AA32: BROKER_NAME | AD32: ccal_repl_owner.txn t LEFT join ccal_repl_owner.acats_broker ON b.broker_id = t.orig_src_stm_code and t.src_stm_id IN ( 53, 54 ) | AE32: Note to Dev team: ACATS_BROKER table is available in CDS DB but not available in SSDS/Lighthouse DB. [11/18/25] Corrected orig_src_stm_id with orig_src_stm_code in mapping | AH32: N
A33: ACAT Contra Firm Short Name | B33: ACAT_CNTRA_FIRM_SHRT_NM | D33: VARCHAR2(15) | E33: Yes | F33: character varying(15) | G33: Yes | H33: ACAT Contra Firm Clearing Short Name | I33: 0352 | J33: Add | K33: 3 | O33: =VLOOKUP(A33,[1]Model!C$2:J$559,2,FALSE)=B33 -> TRUE | P33: =VLOOKUP(A33,Model!C$2:G$228,5,FALSE)=D33 -> TRUE | Q33: =VLOOKUP(A33,[2]Model!C$2:L$228,8,FALSE) -> 160 | R33: =VLOOKUP(A33,[2]Model!C$2:G$228,3,FALSE)=[3]!Table14[[#This Row],[Business Definition (To go into comments and into Meta Data Hub)]] -> #REF! | S33: =IF([3]!Table14[[#This Row],[Nullable in Table and in Oracle View NULL, NOT NULL]]="No","NOT NULL","NULL")=VLOOKUP(A33,[2]Model!C$2:I$228,6,FALSE) -> #REF! | T33: =VLOOKUP(B33,[2]Table!A$2:F$415,1,FALSE)=[3]!Table14[[#This Row],[Physical Name of Attribute (Name of column in Table) Supplied by DA Team]] -> #REF! | U33: =VLOOKUP(B33,Table!A$2:F$319,2,FALSE)=Table1[[#This Row],[Data type in Oracle VARCHAR2(n), DATE, NUMBER(m,n), TIMETSTAMP(6)]] -> FALSE | V33: =VLOOKUP(B33,Table!A$2:F$231,3,FALSE)=Table1[[#This Row],[Nullable in Table and in Oracle View NULL, NOT NULL]] -> TRUE | W33: =VLOOKUP(B33,Table!A$2:H$228,6,FALSE)=Table1[[#This Row],[Business Definition (To go into comments and into Meta Data Hub)]] -> TRUE | X33: =VLOOKUP((UPPER(SUBSTITUTE(A33," ","_"))),'[2]Consumer View'!A$2:I$329,1,FALSE) -> ACAT_CONTRA_FIRM_SHORT_NAME | Y33: CCAL_REPL_OWNER | Z33: ACATS_BROKER | AA33: BROKER_SHORT_NAME | AD33: ccal_repl_owner.txn t LEFT join ccal_repl_owner.acats_broker ON b.broker_id = t.orig_src_stm_code and t.src_stm_id IN ( 53, 54 ) | AE33: Note to Dev team: ACATS_BROKER table is available in CDS DB but not available in SSDS/Lighthouse DB. | AH33: N
A34: ACAT Contra Firm Clearing ID Type Code | B34: ACAT_CNTRA_FIRM_CLRG_ID_TP_CD | D34: VARCHAR2(1) | E34: Yes | F34: character varying(1) | G34: Yes | H34: ACAT Broker ID Type | I34: 2 | J34: Add | K34: 3 | O34: =VLOOKUP(A34,[1]Model!C$2:J$559,2,FALSE)=B34 -> TRUE | P34: =VLOOKUP(A34,Model!C$2:G$228,5,FALSE)=D34 -> TRUE | Q34: =VLOOKUP(A34,[2]Model!C$2:L$228,8,FALSE) -> 161 | R34: =VLOOKUP(A34,[2]Model!C$2:G$228,3,FALSE)=[3]!Table14[[#This Row],[Business Definition (To go into comments and into Meta Data Hub)]] -> #REF! | S34: =IF([3]!Table14[[#This Row],[Nullable in Table and in Oracle View NULL, NOT NULL]]="No","NOT NULL","NULL")=VLOOKUP(A34,[2]Model!C$2:I$228,6,FALSE) -> #REF! | T34: =VLOOKUP(B34,[2]Table!A$2:F$415,1,FALSE)=[3]!Table14[[#This Row],[Physical Name of Attribute (Name of column in Table) Supplied by DA Team]] -> #REF! | U34: =VLOOKUP(B34,Table!A$2:F$319,2,FALSE)=Table1[[#This Row],[Data type in Oracle VARCHAR2(n), DATE, NUMBER(m,n), TIMETSTAMP(6)]] -> FALSE | V34: =VLOOKUP(B34,Table!A$2:F$231,3,FALSE)=Table1[[#This Row],[Nullable in Table and in Oracle View NULL, NOT NULL]] -> TRUE | W34: =VLOOKUP(B34,Table!A$2:H$228,6,FALSE)=Table1[[#This Row],[Business Definition (To go into comments and into Meta Data Hub)]] -> TRUE | X34: =VLOOKUP((UPPER(SUBSTITUTE(A34," ","_"))),'[2]Consumer View'!A$2:I$329,1,FALSE) -> ACAT_CONTRA_FIRM_CLEARING_ID_TYPE_CODE | Y34: CCAL_REPL_OWNER | Z34: ACATS_BROKER | AA34: BROKER_ID_TYPE | AD34: ccal_repl_owner.txn t LEFT join ccal_repl_owner.acats_broker b ON b.broker_id = t.orig_src_stm_code and t.src_stm_id IN ( 53, 54 ) | AE34: Note to Dev team: ACATS_BROKER table is available in CDS DB but not available in SSDS/Lighthouse DB. | AH34: N
A35: Money Movement Alternate Id | B35: MM_ALT_ID | C35: Money_Movement_Alternate_Id | D35: VARCHAR2(50) | E35: Yes | F35: character varying(50) | G35: Yes | H35: Identifier on all Money movement transactions | I35: MM1423054 | J35: Add | K35: 3 | O35: =VLOOKUP(A35,[1]Model!C$2:J$559,2,FALSE)=B35 -> TRUE | P35: =VLOOKUP(A35,Model!C$2:G$228,5,FALSE)=D35 -> TRUE | Q35: =VLOOKUP(A35,[2]Model!C$2:L$228,8,FALSE) -> 162 | R35: =VLOOKUP(A35,[2]Model!C$2:G$228,3,FALSE)=[3]!Table14[[#This Row],[Business Definition (To go into comments and into Meta Data Hub)]] -> #REF! | S35: =IF([3]!Table14[[#This Row],[Nullable in Table and in Oracle View NULL, NOT NULL]]="No","NOT NULL","NULL")=VLOOKUP(A35,[2]Model!C$2:I$228,6,FALSE) -> #REF! | T35: =VLOOKUP(B35,[2]Table!A$2:F$415,1,FALSE)=[3]!Table14[[#This Row],[Physical Name of Attribute (Name of column in Table) Supplied by DA Team]] -> #REF! | U35: =VLOOKUP(B35,Table!A$2:F$319,2,FALSE)=Table1[[#This Row],[Data type in Oracle VARCHAR2(n), DATE, NUMBER(m,n), TIMETSTAMP(6)]] -> FALSE | V35: =VLOOKUP(B35,Table!A$2:F$231,3,FALSE)=Table1[[#This Row],[Nullable in Table and in Oracle View NULL, NOT NULL]] -> TRUE | W35: =VLOOKUP(B35,Table!A$2:H$228,6,FALSE)=Table1[[#This Row],[Business Definition (To go into comments and into Meta Data Hub)]] -> TRUE | X35: =VLOOKUP((UPPER(SUBSTITUTE(A35," ","_"))),'[2]Consumer View'!A$2:I$329,1,FALSE) -> MONEY_MOVEMENT_ALTERNATE_ID | Y35: CCAL_REPL_OWNER | Z35: TXN | AA35: ORIG_SRC_STM_CODE | AD35: ccal_repl_owner.txn t where t.src_stm_id= '60' and t.ORIG_SRC_STM_CODE like 'MM%' and t.SRC_CRT_USRNM = 'BPMWRAPB'; | AH35: N
A36: Arrangement Originating Source System Code | B36: AR_ORIG_SRC_STM_CD | C36: Arrangement_Originating_Source_System_Provider_Code | D36: VARCHAR2(20) | E36: Yes | F36: character varying(20) | G36: Yes | H36: Code that represents the source system from which CDS database receives/obtains the underlying Arrangement from. | I36: ZTNB.#B066 | J36: Add | K36: 3 | O36: =VLOOKUP(A36,[1]Model!C$2:J$559,2,FALSE)=B36 -> TRUE | P36: =VLOOKUP(A36,Model!C$2:G$228,5,FALSE)=D36 -> TRUE | Q36: =VLOOKUP(A36,[2]Model!C$2:L$228,8,FALSE) -> 185 | R36: =VLOOKUP(A36,[2]Model!C$2:G$228,3,FALSE)=[3]!Table14[[#This Row],[Business Definition (To go into comments and into Meta Data Hub)]] -> #REF! | S36: =IF([3]!Table14[[#This Row],[Nullable in Table and in Oracle View NULL, NOT NULL]]="No","NOT NULL","NULL")=VLOOKUP(A36,[2]Model!C$2:I$228,6,FALSE) -> #REF! | T36: =VLOOKUP(B36,[2]Table!A$2:F$415,1,FALSE)=[3]!Table14[[#This Row],[Physical Name of Attribute (Name of column in Table) Supplied by DA Team]] -> #REF! | U36: =VLOOKUP(B36,Table!A$2:F$319,2,FALSE)=Table1[[#This Row],[Data type in Oracle VARCHAR2(n), DATE, NUMBER(m,n), TIMETSTAMP(6)]] -> FALSE | V36: =VLOOKUP(B36,Table!A$2:F$231,3,FALSE)=Table1[[#This Row],[Nullable in Table and in Oracle View NULL, NOT NULL]] -> TRUE | W36: =VLOOKUP(B36,Table!A$2:H$228,6,FALSE)=Table1[[#This Row],[Business Definition (To go into comments and into Meta Data Hub)]] -> TRUE | X36: =VLOOKUP((UPPER(SUBSTITUTE(A36," ","_"))),'[2]Consumer View'!A$2:I$329,1,FALSE) -> ARRANGEMENT_ORIGINATING_SOURCE_SYSTEM_CODE | Y36: CCSI_OWNER | Z36: AR_DIM | AA36: ORIG_SRC_STM_CD | AD36: ccal_repl_owner.txn t join ccsi_owner.ar_dim ard ON ard.AR_ID = t.AR_ID and ard.eff_dt <= t.td and ard.end_dt > t.td | AE36: [9/6/24]: Reflected the change to use TXN.TD from Product Backlog Item 1912566: Change join condition and update data types for Activity. [9/17/24]: Changing to use TXN.AR_ID per Product Backlog Item 1998220: Fix Activity issues for Historical Load | AH36: Y
A37: Source System Id | B37: SRC_STM_ID | D37: NUMBER(38,0) | E37: Yes | F37: NUMERIC(38,0) | G37: Yes | H37: Source system Id coming from Transaction. This could be different from Source system Id coming from Arrangement information. | I37: 3 | J37: Add | K37: 3 | O37: =VLOOKUP(A37,[1]Model!C$2:J$559,2,FALSE)=B37 -> TRUE | P37: =VLOOKUP(A37,Model!C$2:G$228,5,FALSE)=D37 -> #N/A | Q37: =VLOOKUP(A37,[2]Model!C$2:L$228,8,FALSE) -> 163 | R37: =VLOOKUP(A37,[2]Model!C$2:G$228,3,FALSE)=[3]!Table14[[#This Row],[Business Definition (To go into comments and into Meta Data Hub)]] -> #REF! | S37: =IF([3]!Table14[[#This Row],[Nullable in Table and in Oracle View NULL, NOT NULL]]="No","NOT NULL","NULL")=VLOOKUP(A37,[2]Model!C$2:I$228,6,FALSE) -> #REF! | T37: =VLOOKUP(B37,[2]Table!A$2:F$415,1,FALSE)=[3]!Table14[[#This Row],[Physical Name of Attribute (Name of column in Table) Supplied by DA Team]] -> #REF! | U37: =VLOOKUP(B37,Table!A$2:F$319,2,FALSE)=Table1[[#This Row],[Data type in Oracle VARCHAR2(n), DATE, NUMBER(m,n), TIMETSTAMP(6)]] -> TRUE | V37: =VLOOKUP(B37,Table!A$2:F$231,3,FALSE)=Table1[[#This Row],[Nullable in Table and in Oracle View NULL, NOT NULL]] -> TRUE | W37: =VLOOKUP(B37,Table!A$2:H$228,6,FALSE)=Table1[[#This Row],[Business Definition (To go into comments and into Meta Data Hub)]] -> TRUE | X37: =VLOOKUP((UPPER(SUBSTITUTE(A37," ","_"))),'[2]Consumer View'!A$2:I$329,1,FALSE) -> SOURCE_SYSTEM_ID | Y37: CCAL_REPL_OWNER | Z37: TXN | AA37: SRC_STM_ID | AH37: N
